Workbook
Name WD_Well: 'Well Data'!$B$10
Name WD_Field: 'Well Data'!$B$11
Name WD_Rig: 'Well Data'!$B$12
Name WD_Engineer: 'Well Data'!$B$13
Name WD_Date: 'Well Data'!$B$14
Name WD_MD: 'Well Data'!$B$20
Name WD_TVD: 'Well Data'!$B$21
Name WD_ShoeMD: 'Well Data'!$B$22
Name WD_ShoeTVD: 'Well Data'!$B$23
Name WD_HoleDiam: 'Well Data'!$B$24
Name WD_CsgID: 'Well Data'!$B$25
Name WD_PerfTVD: 'Well Data'!$B$26
Name WD_OMW: 'Well Data'!$B$31
Name WD_PV: 'Well Data'!$B$32
Name WD_YP: 'Well Data'!$B$33
Name WD_LOT: 'Well Data'!$B$34
Name WD_FracGrad: 'Well Data'!$B$35
Name WD_ResP: 'Well Data'!$B$36
Name WD_SCR: 'Well Data'!$B$41
Name WD_SPR: 'Well Data'!$B$42
Name WD_KillRate: 'Well Data'!$B$43
Name WD_BlockWt: 'Well Data'!$B$48
Name WD_WOB: 'Well Data'!$B$49
Name WD_BitTq: 'Well Data'!$B$50
Name WD_TJOD: 'Well Data'!$B$51
Name WD_DPWt: 'Well Data'!$B$52
Name WD_BHAWt: 'Well Data'!$B$53
Name WD_BHALen: 'Well Data'!$B$54
Name WD_MuCased: 'Well Data'!$B$55
Name WD_MuOpen: 'Well Data'!$B$56
Name WD_WaterDepth: 'Well Data'!$B$61
Name WD_AirGap: 'Well Data'!$B$62
Name WD_SWGrad: 'Well Data'!$B$63
Name WD_CLF: 'Well Data'!$B$64
Name WD_TbgOD: 'Well Data'!$B$69
Name WD_TbgID: 'Well Data'!$B$70
Name TL_Names: 'Tubular Library'!$A$9:$A$47
Name TL_Table: 'Tubular Library'!$A$9:$D$47
Name RU_Names: 'Surface Rig-Up'!$A$9:$A$28
Name RU_Table: 'Surface Rig-Up'!$A$9:$E$28

Sheet Cover
A1: Drilling, Completion & Intervention Engineering Suite
B4: How to use
B5: Yellow cells | C5: User inputs - overwrite the example values with your well data.
B6: Blue cells | C6: Linked to the Well Data master sheet - update the well there once, or overwrite locally for a one-off value.
B7: Green cells | C7: Live calculated results - do not type over them.
B8: Red / amber highlights | C8: Automatic alarms on status cells (limits exceeded, buckling, marginal margins).
B9: SI columns | C9: Every value is mirrored to SI units automatically (columns D-E).
B10: Notes / Equation | C10: The governing equation for every calculation is written out in column F.
B11: Protection | C11: Sheets are protected with no password so formulas can't be typed over by accident - Review > Unprotect Sheet to edit structure.
B13: Field units are primary (ppg, psi, ft, in, bbl). All formulas are standard API/IADC/IWCF-form oilfield equations; see each sheet's notes for assumptions.
B15: Reference
B16: Well Data | C16: Single source of well inputs (WD_* named cells) feeding the linked light-blue cells on other sheets
B17: Tubular Library | C17: API tubular catalog (TL_Names/TL_Table named ranges), capacities/displacements per size, and a lookup calculator
B18: Unit Converter | C18: Live converters (density, pressure, volume, flow, force...) and conversion factor table
B19: Wellbore Schematic | C19: Customizable wellbore schematic: casing strings, tubing, packer, TRSV, perfs, PBTD drawn to scale on a chart
B21: Drilling
B22: Mud & Hydrostatics | C22: Pressure gradients, hydrostatic pressure, EMW, ECD, barite weight-up, dilution
B23: Capacities & Displacement | C23: Capacities, displacements, pump output, stroke/lag times, tripping and slug volumes
B24: Kill Sheet | C24: Full kill sheet: string & annulus component tables, KMW, ICP, FCP, survey-driven step-down schedule for deviated/horizontal wells, kill plot
B25: Kill Form | C25: One-page printable kill sheet (all values pulled live from Kill Sheet / Well Data)
B26: Kill Sheet - Subsea | C26: Subsea supplement: CLF-corrected MAASP and choke pressure, choke line volume, kill mud weight, riser margin, disconnected-riser BHP
B27: Well Control | C27: Kick tolerance, MAASP, margins, gas migration/expansion, kill mud, volumetric control
B28: Hydraulics | C28: Velocities, slip velocity, PV/YP, n and K, annular pressure loss, ECD, surge/swab
B29: Bit Hydraulics | C29: TFA, nozzle velocity, bit pressure drop, HHP, HSI, impact force, optimization targets
B30: Drill String & Tension | C30: Buoyancy factor, hook load, MOP, DC length, pipe stretch, slip crush, critical RPM, ton-miles
B31: Directional Drilling | C31: DLS, minimum curvature, closure and vertical section, build planning, slide/rotate split
B32: Directional Survey | C32: Survey upload table (100 stations, minimum curvature), TVD/NS/EW/VS/DLS, profile & plan charts, MD->TVD interpolator
B33: Torque & Drag | C33: Johancsik soft-string T&D over the Directional Survey: hookloads, surface torque, Dawson-Paslay buckling flags, profile charts
... B40: Procedure - Drilling | C40: Editable template drilling procedure whose step text embeds live Well Data values
B42: Completions
B43: Completion Fluids & Brines | C43: Brine density for overbalance, blending, temperature correction, CaCl2 weight-up, packer fluids
B44: Tubing & Packer Forces | C44: Tubing areas and volumes, stretch, packer setting force, Lubinski force-length effects, buckling
B45: Tubing Stress Analysis | C45: Bellarby-style TSA screening: piston/ballooning/thermal axial loads, Barlow burst, triaxial von Mises with design factors, buckling, APB
B46: Perforating | C46: Optimal underbalance, wellbore pressure at perfs, cushion design, perf flow area, gun string totals
B47: Stimulation & Fracturing | C47: Frac/closure gradients, BHTP and STP, HHP, perf friction, proppant schedule totals, acid volumes
B48: Inflow & Productivity | C48: PI, Darcy radial rate, Vogel IPR and Qmax, gas C-and-n deliverability, AOF, skin pressure drop
B49: Nodal Analysis | C49: Vogel IPR vs simplified VLP, 21-point system curves, interpolated natural-flow operating point and IPR/VLP chart
B50: ESP Design | C50: ESP sizing: PIP and free gas at intake, TDH, stages, motor HP/kW, surface voltage, current and kVA
B51: Gas Lift Design | C51: Gas lift: 10-valve load-fluid spacing table with spacing diagram, injection gas rate and valve test-rack pressures
B52: Rod Pump Design | C52: Beam pump: displacement, PPRL/MPRL, counterbalance, peak torque, motor HP, Goodman check and plunger stroke
B53: Completion Design | C53: Sand control method selection, gravel/screen/proppant sizing, API RP 14E erosional velocity, Turner critical rate
B54: Production Chemistry | C54: CO2/H2S corrosion screening, material selection, hydrate formation and inhibition, scale screening (Bellarby-style)
... B57: Procedure - Completion | C57: Editable template completion procedure whose step text embeds live Well Data values
B59: Interventions
B60: Surface Rig-Up | C60: Treating-iron catalog (RU_Names/RU_Table named ranges) and an ordered flow-path builder with footage, volume, restriction and rating tallies plus a line-test check
B61: Coiled Tubing | C61: CT volumes, pipe-light check, pull to yield, burst/collapse, annular velocity, N2 displacement
B62: Wireline | C62: Buoyed cable weight, head tension, safe pull, weak point, stretch and depth correction
B63: Snubbing & Hydraulic Workover | C63: Ejection force, balance point, snubbing force, jack SF, Euler buckling, shear ram check
B64: Well Kill - Interventions | C64: Kill weight fluid, bullhead pressures/volumes, lube & bleed cycles, forward/reverse circulation, volumetric
B65: Fishing & Stuck Pipe | C65: Free point, overpull margin, spot/chase volumes, sticking force, soak pills, milling time
B66: Procedure - Intervention | C66: Editable template intervention procedure whose step text embeds live Well Data values
B69: Engineering reference only - verify against current company standards and manufacturer data before operational use.

Sheet Well Data
A1: Well Data - Master Inputs
A2: Enter the well once; light-blue cells across the workbook pull from here (overwrite them locally when a calc needs a different value)
A4: Parameter | B4: Value | C4: Unit | D4: SI Value | E4: SI Unit | F4: Notes / Equation
A6: Well Identification
A8: Identification
F9: Free text - appears on the printable Kill Form.
A10: Well name | B10: EXAMPLE 1-H
A11: Field / lease | B11: EXAMPLE FIELD
A12: Rig | B12: RIG 00
A13: Engineer | B13: K. Keel
A14: Date | B14: 2026-08-18
A16: Depths & Geometry
A18: Depths & Geometry
F19: TVDs from the Directional Survey sheet (TVD at TD cell).
A20: Bit / TD measured depth | B20: 10500 | C20: ft | D20: =IFERROR($B$20*0.3048,NA()) | E20: m
A21: Bit / TD true vertical depth | B21: 5573 | C21: ft | D21: =IFERROR($B$21*0.3048,NA()) | E21: m
A22: Casing shoe MD | B22: 5900 | C22: ft | D22: =IFERROR($B$22*0.3048,NA()) | E22: m
A23: Casing shoe TVD | B23: 5573 | C23: ft | D23: =IFERROR($B$23*0.3048,NA()) | E23: m
A24: Open hole diameter | B24: 8.5 | C24: in | D24: =IFERROR($B$24*25.4,NA()) | E24: mm
A25: Last casing ID | B25: 8.681 | C25: in | D25: =IFERROR($B$25*25.4,NA()) | E25: mm
A26: Perforation / reservoir TVD | B26: 5573 | C26: ft | D26: =IFERROR($B$26*0.3048,NA()) | E26: m
A28: Mud & Formation Pressures
A30: Mud & Pressures
A31: Current mud / fluid weight | B31: 12.5 | C31: ppg | D31: =IFERROR($B$31*119.8264,NA()) | E31: kg/m3
A32: Plastic viscosity (PV) | B32: 15 | C32: cP | F32: mPa-s in SI
A33: Yield point (YP) | B33: 12 | F33: lb/100ft2
A34: LOT / FIT equivalent mud weight | B34: 15.2 | C34: ppg | D34: =IFERROR($B$34*119.8264,NA()) | E34: kg/m3
A35: Fracture gradient (at TD/perfs) | B35: 0.79 | C35: psi/ft | D35: =IFERROR($B$35*22.62059,NA()) | E35: kPa/m
A36: Reservoir / formation pressure | B36: 4122 | C36: psi | D36: =IFERROR($B$36*6.894757,NA()) | E36: kPa
A38: Pumps & Kill Parameters
A40: Pumps & Kill
A41: Slow circulating rate pressure (SCR) | B41: 750 | C41: psi | D41: =IFERROR($B$41*6.894757,NA()) | E41: kPa
A42: Pump output | B42: 0.102 | C42: bbl/stk | D42: =IFERROR($B$42*158.9873,NA()) | E42: L/stk
A43: Kill rate | B43: 30 | F43: strokes per minute
A45: Rig & Drill String (for Torque & Drag)
A47: Rig & String
A48: Travelling block + top drive weight | B48: 85 | C48: klbf | D48: =IFERROR($B$48*4.448222,NA()) | E48: kN
A49: Weight on bit (slack-off case) | B49: 15 | C49: klbf | D49: =IFERROR($B$49*4.448222,NA()) | E49: kN
A50: Bit torque | B50: 4000 | C50: ft-lbf | D50: =IFERROR($B$50*1.355818,NA()) | E50: N-m
A51: Tool joint OD | B51: 6.625 | C51: in | D51: =IFERROR($B$51*25.4,NA()) | E51: mm
A52: Drill pipe adjusted weight | B52: 20.9 | C52: lb/ft | D52: =IFERROR($B$52*1.488164,NA()) | E52: kg/m | F52: Nominal weight + tool joints (approx nominal x 1.07).
A53: BHA weight per foot | B53: 92 | C53: lb/ft | D53: =IFERROR($B$53*1.488164,NA()) | E53: kg/m
A54: BHA length | B54: 300 | C54: ft | D54: =IFERROR($B$54*0.3048,NA()) | E54: m
A55: Friction factor - cased hole | B55: 0.25 | F55: Typical 0.15-0.25 in WBM, lower in OBM.
A56: Friction factor - open hole | B56: 0.3 | F56: Typical 0.25-0.40 in WBM.
A58: Subsea (leave 0 for land / surface BOP)
A60: Subsea
A61: Water depth | B61: 0 | C61: ft | D61: =IFERROR($B$61*0.3048,NA()) | E61: m
A62: Air gap (RKB to sea level) | B62: 0 | C62: ft | D62: =IFERROR($B$62*0.3048,NA()) | E62: m
A63: Seawater gradient | B63: 0.445 | C63: psi/ft | D63: =IFERROR($B$63*22.62059,NA()) | E63: kPa/m
A64: Choke line friction at kill rate | B64: 0 | C64: psi | D64: =IFERROR($B$64*6.894757,NA()) | E64: kPa
A66: Completion / Intervention Tubulars
A68: Tubing
A69: Tubing OD | B69: 3.5 | C69: in | D69: =IFERROR($B$69*25.4,NA()) | E69: mm
A70: Tubing ID | B70: 2.992 | C70: in | D70: =IFERROR($B$70*25.4,NA()) | E70: mm

Sheet Tubular Library
A1: Tubular Library - API Catalog
A2: Standard drill pipe, HWDP, collars, casing, tubing and CT dimensions. Feeds the dropdowns and OD/ID auto-fill on the Kill Sheet.
A4: Parameter | B4: Value | C4: Unit | D4: SI Value | E4: SI Unit | F4: Notes / Equation
A6: Catalog
A7: Nominal API dimensions. DP weights are nominal - for string weight use adjusted weight (incl. tool joints, ~7% higher). Pressure ratings are grade-specific: enter them on the Casing & Tubular Design sheet.
A8: Name | B8: OD (in) | C8: ID (in) | D8: Weight (lb/ft) | E8: Capacity (bbl/ft) | F8: Disp. closed (bbl/ft) | G8: Disp. open (bbl/ft) | H8: Wall (in)
A9: DP 3-1/2 13.30# | B9: 3.5 | C9: 2.764 | D9: 13.3 | E9: =$C9^2/1029.4 | F9: =$B9^2/1029.4 | G9: =($B9^2-$C9^2)/1029.4 | H9: =($B9-$C9)/2
A10: DP 4 14.00# | B10: 4 | C10: 3.34 | D10: 14 | E10: =$C10^2/1029.4 | F10: =$B10^2/1029.4 | G10: =($B10^2-$C10^2)/1029.4 | H10: =($B10-$C10)/2
A11: DP 4-1/2 16.60# | B11: 4.5 | C11: 3.826 | D11: 16.6 | E11: =$C11^2/1029.4 | F11: =$B11^2/1029.4 | G11: =($B11^2-$C11^2)/1029.4 | H11: =($B11-$C11)/2
A12: DP 5 19.50# | B12: 5 | C12: 4.276 | D12: 19.5 | E12: =$C12^2/1029.4 | F12: =$B12^2/1029.4 | G12: =($B12^2-$C12^2)/1029.4 | H12: =($B12-$C12)/2
A13: DP 5 25.60# | B13: 5 | C13: 4 | D13: 25.6 | E13: =$C13^2/1029.4 | F13: =$B13^2/1029.4 | G13: =($B13^2-$C13^2)/1029.4 | H13: =($B13-$C13)/2
A14: DP 5-1/2 21.90# | B14: 5.5 | C14: 4.778 | D14: 21.9 | E14: =$C14^2/1029.4 | F14: =$B14^2/1029.4 | G14: =($B14^2-$C14^2)/1029.4 | H14: =($B14-$C14)/2
A15: DP 5-1/2 24.70# | B15: 5.5 | C15: 4.67 | D15: 24.7 | E15: =$C15^2/1029.4 | F15: =$B15^2/1029.4 | G15: =($B15^2-$C15^2)/1029.4 | H15: =($B15-$C15)/2
A16: DP 6-5/8 25.20# | B16: 6.625 | C16: 5.965 | D16: 25.2 | E16: =$C16^2/1029.4 | F16: =$B16^2/1029.4 | G16: =($B16^2-$C16^2)/1029.4 | H16: =($B16-$C16)/2
A17: HWDP 3-1/2 25.3# | B17: 3.5 | C17: 2.063 | D17: 25.3 | E17: =$C17^2/1029.4 | F17: =$B17^2/1029.4 | G17: =($B17^2-$C17^2)/1029.4 | H17: =($B17-$C17)/2
A18: HWDP 4 29.7# | B18: 4 | C18: 2.563 | D18: 29.7 | E18: =$C18^2/1029.4 | F18: =$B18^2/1029.4 | G18: =($B18^2-$C18^2)/1029.4 | H18: =($B18-$C18)/2
A19: HWDP 4-1/2 41.0# | B19: 4.5 | C19: 2.75 | D19: 41 | E19: =$C19^2/1029.4 | F19: =$B19^2/1029.4 | G19: =($B19^2-$C19^2)/1029.4 | H19: =($B19-$C19)/2
A20: HWDP 5 49.3# | B20: 5 | C20: 3 | D20: 49.3 | E20: =$C20^2/1029.4 | F20: =$B20^2/1029.4 | G20: =($B20^2-$C20^2)/1029.4 | H20: =($B20-$C20)/2
... A47: CT 2-3/8 x 0.175w | B47: 2.375 | C47: 2.025 | D47: 4.11 | E47: =$C47^2/1029.4 | F47: =$B47^2/1029.4 | G47: =($B47^2-$C47^2)/1029.4 | H47: =($B47-$C47)/2
A49: Lookup Calculator
A51: Pipe Properties Lookup | F51: Capacity = ID^2/1029.4; Disp closed = OD^2/1029.4; Disp open = (OD^2-ID^2)/1029.4
F52: Type or pick any catalog name (dropdowns available on the Kill Sheet).
A53: Catalog name | B53: DP 5 19.50#
A54: OD | B54: =VLOOKUP($B$53,TL_Table,2,FALSE) | C54: in | D54: =IFERROR($B$54*25.4,NA()) | E54: mm
A55: ID | B55: =VLOOKUP($B$53,TL_Table,3,FALSE) | C55: in | D55: =IFERROR($B$55*25.4,NA()) | E55: mm
A56: Nominal weight | B56: =VLOOKUP($B$53,TL_Table,4,FALSE) | C56: lb/ft | D56: =IFERROR($B$56*1.488164,NA()) | E56: kg/m
A57: Capacity | B57: =$B$55^2/1029.4 | C57: bbl/ft | D57: =IFERROR($B$57*0.5216119,NA()) | E57: m3/m
A58: Displacement (closed end) | B58: =$B$54^2/1029.4 | C58: bbl/ft | D58: =IFERROR($B$58*0.5216119,NA()) | E58: m3/m
A59: Displacement (open end) | B59: =($B$54^2-$B$55^2)/1029.4 | C59: bbl/ft | D59: =IFERROR($B$59*0.5216119,NA()) | E59: m3/m
A60: Hole / casing ID for annulus | B60: 8.681 | C60: in | D60: =IFERROR($B$60*25.4,NA()) | E60: mm
A61: Annular capacity around pipe | B61: =($B$60^2-$B$54^2)/1029.4 | C61: bbl/ft | D61: =IFERROR($B$61*0.5216119,NA()) | E61: m3/m

Sheet Unit Converter
A1: Unit Conversions
A2: Live two-way converters for common oilfield quantities, plus the full factor table
A4: Parameter | B4: Value | C4: Unit | D4: SI Value | E4: SI Unit | F4: Notes / Equation
A6: Live Converters (enter a field-unit value; SI computes)
A8: Field -> SI
F9: Yellow cells are inputs; SI Value column converts live.
A10: Density (ppg) | B10: 12.5 | C10: ppg | D10: =IFERROR($B$10*119.8264,NA()) | E10: kg/m3
A11: Pressure (psi) | B11: 5000 | C11: psi | D11: =IFERROR($B$11*6.894757,NA()) | E11: kPa
A12: Pressure gradient (psi/ft) | B12: 0.65 | C12: psi/ft | D12: =IFERROR($B$12*22.62059,NA()) | E12: kPa/m
A13: Length / depth (ft) | B13: 10000 | C13: ft | D13: =IFERROR($B$13*0.3048,NA()) | E13: m
A14: Diameter (in) | B14: 8.5 | C14: in | D14: =IFERROR($B$14*25.4,NA()) | E14: mm
A15: Volume (bbl) | B15: 500 | C15: bbl | D15: =IFERROR($B$15*0.1589873,NA()) | E15: m3
A16: Volume (small) (gal) | B16: 42 | C16: gal | D16: =IFERROR($B$16*3.785412,NA()) | E16: L
A17: Capacity (bbl/ft) | B17: 0.0459 | C17: bbl/ft | D17: =IFERROR($B$17*0.5216119,NA()) | E17: m3/m
A18: Flow rate (gpm) | B18: 350 | C18: gpm | D18: =IFERROR($B$18*3.785412,NA()) | E18: L/min
A19: Flow rate (bbl/min) | B19: 8.5 | C19: bbl/min | D19: =IFERROR($B$19*0.1589873,NA()) | E19: m3/min
A20: Velocity (ft/min) | B20: 150 | C20: ft/min | D20: =IFERROR($B$20*0.3048,NA()) | E20: m/min
A21: Force (lbf) | B21: 45000 | C21: lbf | D21: =IFERROR($B$21*0.004448222,NA()) | E21: kN
A22: Mass (lbm) | B22: 25000 | C22: lbm | D22: =IFERROR($B$22*0.4535924,NA()) | E22: kg
A23: Weight per length (lb/ft) | B23: 19.5 | C23: lb/ft | D23: =IFERROR($B$23*1.488164,NA()) | E23: kg/m
A24: Power (hp) | B24: 1600 | C24: hp | D24: =IFERROR($B$24*0.7456999,NA()) | E24: kW
A26: Temperature | F26: degC = (degF - 32) / 1.8
A27: Temperature | B27: 250 | F27: degF
A28: Temperature | B28: =($B$27-32)/1.8 | F28: degC
A30: SI -> Field (generic) | F30: Field value = SI value / factor
F31: Enter an SI value and the factor from the table below.
A32: SI value | B32: 1500
A33: Factor (field -> SI) | B33: 6.894757
A34: Field value | B34: =$B$32/$B$33
A36: Conversion Factor Table (multiply field value by factor to get SI)
A38: Field unit | B38: Factor | C38: SI unit
A39: bbl | B39: 0.1589873 | C39: m3
A40: bbl/ft | B40: 0.5216119 | C40: m3/m
A41: bbl/hr | B41: 0.1589873 | C41: m3/hr
A42: bbl/mi | B42: 0.0987974 | C42: m3/km
A43: bbl/min | B43: 0.1589873 | C43: m3/min
A44: bbl/stk | B44: 158.9873 | C44: L/stk
A45: cuft/bbl | B45: 0.1781076 | C45: m3/m3
A46: deg/100ft | B46: 0.984252 | C46: deg/30m
A47: ft | B47: 0.3048 | C47: m
A48: ft-lbf | B48: 1.355818 | C48: N-m
A49: ft/hr | B49: 0.3048 | C49: m/hr
A50: ft/min | B50: 0.3048 | C50: m/min
... A78: sk/bbl | B78: 6.289811 | C78: sk/m3

Sheet Mud & Hydrostatics
A1: Mud Density & Hydrostatic Pressure
A2: Gradients, hydrostatic pressure, equivalent mud weight, ECD, weight-up and dilution
A4: Parameter | B4: Value | C4: Unit | D4: SI Value | E4: SI Unit | F4: Notes / Equation
A6: Gradients & Hydrostatic Pressure
A8: Pressure Gradient from Mud Weight | F8: Grad [psi/ft] = 0.052 x MW [ppg]
A9: Mud weight (MW) | B9: 12.5 | C9: ppg | D9: =IFERROR($B$9*119.8264,NA()) | E9: kg/m3
A10: Pressure gradient | B10: =0.052*$B$9 | C10: psi/ft | D10: =IFERROR($B$10*22.62059,NA()) | E10: kPa/m
A12: Hydrostatic Pressure | F12: P_hyd [psi] = 0.052 x MW [ppg] x TVD [ft]
F13: Always use true vertical depth, never measured depth.
A14: Mud weight (MW) | B14: 12.5 | C14: ppg | D14: =IFERROR($B$14*119.8264,NA()) | E14: kg/m3
A15: True vertical depth (TVD) | B15: 10000 | C15: ft | D15: =IFERROR($B$15*0.3048,NA()) | E15: m
A16: Hydrostatic pressure (P_hyd) | B16: =0.052*$B$14*$B$15 | C16: psi | D16: =IFERROR($B$16*6.894757,NA()) | E16: kPa
A18: Mud Weight from Pressure Gradient | F18: MW [ppg] = Grad [psi/ft] / 0.052
A19: Pressure gradient | B19: 0.65 | C19: psi/ft | D19: =IFERROR($B$19*22.62059,NA()) | E19: kPa/m
A20: Equivalent mud weight | B20: =$B$19/0.052 | C20: ppg | D20: =IFERROR($B$20*119.8264,NA()) | E20: kg/m3
A22: Equivalent Mud Weight (EMW) at Depth | F22: EMW [ppg] = P [psi] / (0.052 x TVD [ft])
A23: Pressure at depth (P) | B23: 6500 | C23: psi | D23: =IFERROR($B$23*6.894757,NA()) | E23: kPa
A24: True vertical depth (TVD) | B24: 10000 | C24: ft | D24: =IFERROR($B$24*0.3048,NA()) | E24: m
A25: Equivalent mud weight (EMW) | B25: =$B$23/(0.052*$B$24) | C25: ppg | D25: =IFERROR($B$25*119.8264,NA()) | E25: kg/m3
A27: Hydrostatic Pressure of a Column of Multiple Fluids | F27: P_hyd = 0.052 x [ MW1 x L1_tvd + MW2 x L2_tvd ]
F28: Extend by summing 0.052 x MW x TVD-length for each fluid in the column.
A29: Fluid 1 density | B29: 8.6 | C29: ppg | D29: =IFERROR($B$29*119.8264,NA()) | E29: kg/m3
A30: Fluid 1 vertical length | B30: 4000 | C30: ft | D30: =IFERROR($B$30*0.3048,NA()) | E30: m
A31: Fluid 2 density | B31: 12.5 | C31: ppg | D31: =IFERROR($B$31*119.8264,NA()) | E31: kg/m3
A32: Fluid 2 vertical length | B32: 6000 | C32: ft | D32: =IFERROR($B$32*0.3048,NA()) | E32: m
A33: Total hydrostatic pressure | B33: =0.052*($B$29*$B$30+$B$31*$B$32) | C33: psi | D33: =IFERROR($B$33*6.894757,NA()) | E33: kPa
A35: Density Conversions
A37: Specific Gravity <-> Mud Weight | F37: MW [ppg] = SG x 8.345; SG = MW / 8.345
A38: Specific gravity (SG) | B38: 1.2
A39: Mud weight | B39: =$B$38*8.345 | C39: ppg | D39: =IFERROR($B$39*119.8264,NA()) | E39: kg/m3
A40: Mud weight (MW) | B40: 12.5 | C40: ppg | D40: =IFERROR($B$40*119.8264,NA()) | E40: kg/m3
A41: Specific gravity | B41: =$B$40/8.345
A43: Mud Weight <-> lb/ft3 | F43: MW [lb/ft3] = MW [ppg] x 7.48
A44: Mud weight | B44: 12.5 | C44: ppg | D44: =IFERROR($B$44*119.8264,NA()) | E44: kg/m3
A45: Density | B45: =$B$44*7.48 | C45: lb/ft3 | D45: =IFERROR($B$45*16.01846,NA()) | E45: kg/m3
A47: ECD & Annular Friction
A49: Equivalent Circulating Density (ECD) | F49: ECD [ppg] = MW + APL / (0.052 x TVD)
F50: APL = annular pressure loss while circulating.
A51: Mud weight (MW) | B51: 12.5 | C51: ppg | D51: =IFERROR($B$51*119.8264,NA()) | E51: kg/m3
A52: Annular pressure loss (APL) | B52: 200 | C52: psi | D52: =IFERROR($B$52*6.894757,NA()) | E52: kPa
A53: True vertical depth (TVD) | B53: 10000 | C53: ft | D53: =IFERROR($B$53*0.3048,NA()) | E53: m
A54: Equivalent circulating density | B54: =$B$51+$B$52/(0.052*$B$53) | C54: ppg | D54: =IFERROR($B$54*119.8264,NA()) | E54: kg/m3
A56: Bottomhole Pressure While Circulating | F56: BHP = P_hyd + APL = 0.052 x ECD x TVD
A57: Mud weight (MW) | B57: 12.5 | C57: ppg | D57: =IFERROR($B$57*119.8264,NA()) | E57: kg/m3
A58: Annular pressure loss (APL) | B58: 200 | C58: psi | D58: =IFERROR($B$58*6.894757,NA()) | E58: kPa
A59: True vertical depth (TVD) | B59: 10000 | C59: ft | D59: =IFERROR($B$59*0.3048,NA()) | E59: m
A60: Circulating bottomhole pressure | B60: =0.052*$B$57*$B$59+$B$58 | C60: psi | D60: =IFERROR($B$60*6.894757,NA()) | E60: kPa
A62: Weight-Up & Dilution
A64: Barite Required to Weight Up | F64: Sacks/100 bbl = 1470 x (MW2 - MW1) / (35 - MW2)
F65: Barite SG 4.20 (35 ppg); 100 lb sacks. Final volume increases.
A66: Initial mud volume | B66: 800 | C66: bbl | D66: =IFERROR($B$66*0.1589873,NA()) | E66: m3
A67: Initial mud weight (MW1) | B67: 12.5 | C67: ppg | D67: =IFERROR($B$67*119.8264,NA()) | E67: kg/m3
A68: Desired mud weight (MW2) | B68: 13.5 | C68: ppg | D68: =IFERROR($B$68*119.8264,NA()) | E68: kg/m3
A69: Barite required | B69: =1470*($B$68-$B$67)/(35-$B$68)*$B$66/100 | F69: 100-lb sacks
A70: Volume increase | B70: =$B$69*100/(35*42) | C70: bbl | D70: =IFERROR($B$70*0.1589873,NA()) | E70: m3 | F70: V_inc [bbl] = sacks x 100 lb / (35 ppg x 42 gal/bbl)
A72: Calcium Carbonate Required to Weight Up | F72: Sacks/100 bbl = 945 x (MW2 - MW1) / (22.5 - MW2)
F73: CaCO3 SG 2.70 (22.5 ppg); 100 lb sacks. Acid-soluble, for reservoir drill-in fluids.
A74: Initial mud volume | B74: 400 | C74: bbl | D74: =IFERROR($B$74*0.1589873,NA()) | E74: m3
A75: Initial mud weight (MW1) | B75: 9 | C75: ppg | D75: =IFERROR($B$75*119.8264,NA()) | E75: kg/m3
A76: Desired mud weight (MW2) | B76: 10 | C76: ppg | D76: =IFERROR($B$76*119.8264,NA()) | E76: kg/m3
A77: CaCO3 required | B77: =945*($B$76-$B$75)/(22.5-$B$76)*$B$74/100 | F77: 100-lb sacks
A79: Dilution to Reduce Mud Weight | F79: V_dil [bbl] = V1 x (MW1 - MW2) / (MW2 - MW_dil)
F80: Volume of dilution fluid (water/base oil) to add to V1 to cut density from MW1 to MW2.
A81: Initial mud volume (V1) | B81: 800 | C81: bbl | D81: =IFERROR($B$81*0.1589873,NA()) | E81: m3
A82: Initial mud weight (MW1) | B82: 13 | C82: ppg | D82: =IFERROR($B$82*119.8264,NA()) | E82: kg/m3
A83: Desired mud weight (MW2) | B83: 12.2 | C83: ppg | D83: =IFERROR($B$83*119.8264,NA()) | E83: kg/m3
A84: Dilution fluid density (MW_dil) | B84: 8.34 | C84: ppg | D84: =IFERROR($B$84*119.8264,NA()) | E84: kg/m3
A85: Dilution volume required | B85: =$B$81*($B$82-$B$83)/($B$83-$B$84) | C85: bbl | D85: =IFERROR($B$85*0.1589873,NA()) | E85: m3
A87: Blending Two Fluids (Final Density) | F87: MW_f = (V1 x MW1 + V2 x MW2) / (V1 + V2)
A88: Volume of fluid 1 (V1) | B88: 500 | C88: bbl | D88: =IFERROR($B$88*0.1589873,NA()) | E88: m3
A89: Density of fluid 1 (MW1) | B89: 12 | C89: ppg | D89: =IFERROR($B$89*119.8264,NA()) | E89: kg/m3
A90: Volume of fluid 2 (V2) | B90: 300 | C90: bbl | D90: =IFERROR($B$90*0.1589873,NA()) | E90: m3
A91: Density of fluid 2 (MW2) | B91: 9 | C91: ppg | D91: =IFERROR($B$91*119.8264,NA()) | E91: kg/m3
A92: Blended density | B92: =($B$88*$B$89+$B$90*$B$91)/($B$88+$B$90) | C92: ppg | D92: =IFERROR($B$92*119.8264,NA()) | E92: kg/m3
A93: Total volume | B93: =$B$88+$B$90 | C93: bbl | D93: =IFERROR($B$93*0.1589873,NA()) | E93: m3

Sheet Capacities & Displacement
A1: Capacities, Displacement & Pump Output
A2: Pipe and annular capacities, hole volume, pump output, circulation strokes, tripping and slug
A4: Parameter | B4: Value | C4: Unit | D4: SI Value | E4: SI Unit | F4: Notes / Equation
A6: Pipe, Annulus & Hole Capacities
A8: Pipe (Internal) Capacity | F8: C_pipe [bbl/ft] = ID^2 / 1029.4
A9: Pipe inside diameter (ID) | B9: 4.276 | C9: in | D9: =IFERROR($B$9*25.4,NA()) | E9: mm
A10: Pipe capacity | B10: =$B$9^2/1029.4 | C10: bbl/ft | D10: =IFERROR($B$10*0.5216119,NA()) | E10: m3/m | F10: 5 in 19.5 lb/ft drill pipe shown.
A12: Annular Capacity | F12: C_ann [bbl/ft] = (Dh^2 - Dp^2) / 1029.4
A13: Hole (or casing ID) diameter (Dh) | B13: 8.5 | C13: in | D13: =IFERROR($B$13*25.4,NA()) | E13: mm
A14: Pipe outside diameter (Dp) | B14: 5 | C14: in | D14: =IFERROR($B$14*25.4,NA()) | E14: mm
A15: Annular capacity | B15: =($B$13^2-$B$14^2)/1029.4 | C15: bbl/ft | D15: =IFERROR($B$15*0.5216119,NA()) | E15: m3/m
A17: Pipe Displacement | F17: Closed-end [bbl/ft] = OD^2 / 1029.4; Open-end (steel) [bbl/ft] = (OD^2 - ID^2) / 1029.4
F18: Open-end = steel displacement (tripping with open pipe). Closed-end = capacity + steel (plugged bit / float).
A19: Pipe outside diameter (OD) | B19: 5 | C19: in | D19: =IFERROR($B$19*25.4,NA()) | E19: mm
A20: Pipe inside diameter (ID) | B20: 4.276 | C20: in | D20: =IFERROR($B$20*25.4,NA()) | E20: mm
A21: Closed-end displacement | B21: =$B$19^2/1029.4 | C21: bbl/ft | D21: =IFERROR($B$21*0.5216119,NA()) | E21: m3/m
A22: Open-end (steel) displacement | B22: =($B$19^2-$B$20^2)/1029.4 | C22: bbl/ft | D22: =IFERROR($B$22*0.5216119,NA()) | E22: m3/m
A24: Hole Volume | F24: V [bbl] = Dh^2 / 1029.4 x L x (1 + washout)
F25: Washout entered as a fraction (0.10 = 10% over-gauge).
A26: Hole diameter (Dh) | B26: 8.5 | C26: in | D26: =IFERROR($B$26*25.4,NA()) | E26: mm
A27: Hole length | B27: 10000 | C27: ft | D27: =IFERROR($B$27*0.3048,NA()) | E27: m
A28: Washout factor | B28: 0.1 | F28: Fraction of excess over gauge hole.
A29: Hole volume | B29: =$B$26^2/1029.4*$B$27*(1+$B$28) | C29: bbl | D29: =IFERROR($B$29*0.1589873,NA()) | E29: m3
A31: Pump Output & Flow Rate
A33: Triplex Pump Output | F33: Q [bbl/stk] = 0.000243 x D_liner^2 x L_stroke x eff
F34: Single-acting, three cylinders. D and stroke in inches; eff as a fraction (0.95-0.98 typical).
A35: Liner diameter (D) | B35: 6 | C35: in | D35: =IFERROR($B$35*25.4,NA()) | E35: mm
A36: Stroke length (L) | B36: 12 | C36: in | D36: =IFERROR($B$36*25.4,NA()) | E36: mm
A37: Volumetric efficiency | B37: 0.95
A38: Pump output | B38: =0.000243*$B$35^2*$B$36*$B$37 | C38: bbl/stk | D38: =IFERROR($B$38*158.9873,NA()) | E38: L/stk
A40: Duplex Pump Output | F40: Q [bbl/stk] = 0.000162 x L_stroke x (2 x D_liner^2 - d_rod^2) x eff
F41: Double-acting, two cylinders; d = piston rod diameter. Eff 0.85-0.90 typical.
A42: Liner diameter (D) | B42: 6.5 | C42: in | D42: =IFERROR($B$42*25.4,NA()) | E42: mm
A43: Rod diameter (d) | B43: 2.5 | C43: in | D43: =IFERROR($B$43*25.4,NA()) | E43: mm
A44: Stroke length (L) | B44: 14 | C44: in | D44: =IFERROR($B$44*25.4,NA()) | E44: mm
A45: Volumetric efficiency | B45: 0.9
A46: Pump output | B46: =0.000162*$B$44*(2*$B$42^2-$B$43^2)*$B$45 | C46: bbl/stk | D46: =IFERROR($B$46*158.9873,NA()) | E46: L/stk
A48: Pump Flow Rate from Stroke Rate | F48: Q [bbl/min] = output [bbl/stk] x SPM; Q [gpm] = bbl/min x 42
A49: Pump output | B49: 0.0997 | C49: bbl/stk | D49: =IFERROR($B$49*158.9873,NA()) | E49: L/stk
A50: Pump speed | B50: 60 | C50: spm | F50: Strokes per minute.
A51: Flow rate | B51: =$B$49*$B$50 | C51: bbl/min | D51: =IFERROR($B$51*0.1589873,NA()) | E51: m3/min
A52: Flow rate | B52: =$B$51*42 | C52: gpm | D52: =IFERROR($B$52*3.785412,NA()) | E52: L/min
A54: Circulation Strokes & Lag Time
A56: Surface-to-Bit Strokes & Time | F56: Strokes = string volume / pump output; Time [min] = strokes / SPM
F57: String volume = drill string internal capacity x measured length (add BHA capacity if significant).
A58: Drill string capacity | B58: 0.01776 | C58: bbl/ft | D58: =IFERROR($B$58*0.5216119,NA()) | E58: m3/m
A59: Drill string measured length | B59: 10000 | C59: ft | D59: =IFERROR($B$59*0.3048,NA()) | E59: m
A60: Pump output | B60: 0.0997 | C60: bbl/stk | D60: =IFERROR($B$60*158.9873,NA()) | E60: L/stk
A61: Pump speed | B61: 60 | C61: spm
A62: String volume | B62: =$B$58*$B$59 | C62: bbl | D62: =IFERROR($B$62*0.1589873,NA()) | E62: m3
A63: Surface-to-bit strokes | B63: =ROUNDUP(ROUND($B$62/$B$60,6),0) | C63: stk
A64: Surface-to-bit time | B64: =$B$63/$B$61 | C64: min
A66: Bottoms-Up Strokes & Lag Time | F66: Strokes = annular volume / pump output; Lag time [min] = strokes / SPM
F67: Annular volume = annular capacity x length; sum open-hole and cased-hole sections for accuracy.
A68: Annular capacity | B68: 0.0459 | C68: bbl/ft | D68: =IFERROR($B$68*0.5216119,NA()) | E68: m3/m
A69: Annulus length | B69: 10000 | C69: ft | D69: =IFERROR($B$69*0.3048,NA()) | E69: m
A70: Pump output | B70: 0.0997 | C70: bbl/stk | D70: =IFERROR($B$70*158.9873,NA()) | E70: L/stk
A71: Pump speed | B71: 60 | C71: spm
A72: Annular volume | B72: =$B$68*$B$69 | C72: bbl | D72: =IFERROR($B$72*0.1589873,NA()) | E72: m3
A73: Bottoms-up strokes | B73: =ROUNDUP(ROUND($B$72/$B$70,6),0) | C73: stk
A74: Bottoms-up (lag) time | B74: =$B$73/$B$71 | C74: min
A76: Total Circulation (Surface-to-Surface) | F76: Total = surface-to-bit + bottoms-up
F77: Uses the two calculators above. Total cycle time is one complete circulation of the well.
A78: Total circulating volume | B78: =$B$62+$B$72 | C78: bbl | D78: =IFERROR($B$78*0.1589873,NA()) | E78: m3
A79: Total circulation strokes | B79: =$B$63+$B$73 | C79: stk
A80: Total circulation time | B80: =$B$64+$B$74 | C80: min
A82: Tripping & Slug
A84: Drill String Displacement While Tripping | F84: Dry [bbl/ft] = (OD^2 - ID^2)/1029.4; Wet [bbl/ft] = OD^2/1029.4 (steel + contents)
F85: Dry pipe: hole fill (pulling) or pit gain (running) equals steel volume only. Wet pipe (no float / plugged bit not draining): add the pipe contents.
A86: Pipe outside diameter (OD) | B86: 5 | C86: in | D86: =IFERROR($B$86*25.4,NA()) | E86: mm
A87: Pipe inside diameter (ID) | B87: 4.276 | C87: in | D87: =IFERROR($B$87*25.4,NA()) | E87: mm
A88: Average stand length | B88: 93 | C88: ft | D88: =IFERROR($B$88*0.3048,NA()) | E88: m
A89: Number of stands pulled | B89: 10 | F89: Stands between flow checks / trip tank readings.
A90: Dry displacement | B90: =($B$86^2-$B$87^2)/1029.4 | C90: bbl/ft | D90: =IFERROR($B$90*0.5216119,NA()) | E90: m3/m
A91: Wet displacement | B91: =$B$86^2/1029.4 | C91: bbl/ft | D91: =IFERROR($B$91*0.5216119,NA()) | E91: m3/m
A92: Expected pit change - dry pipe | B92: =$B$90*$B$88*$B$89 | C92: bbl | D92: =IFERROR($B$92*0.1589873,NA()) | E92: m3 | F92: Hole should take this much mud when pulling dry; deviation indicates swabbing or losses.
A93: Expected pit change - wet pipe | B93: =$B$91*$B$88*$B$89 | C93: bbl | D93: =IFERROR($B$93*0.1589873,NA()) | E93: m3
A95: Slug Volume for Desired Dry Pipe | F95: V_slug [bbl] = L_dry x MW / (SW - MW) x C_pipe
F96: Heavy slug pumped before tripping drops the fluid level inside the pipe so stands pull dry.
A97: Desired dry pipe length | B97: 200 | C97: ft | D97: =IFERROR($B$97*0.3048,NA()) | E97: m
A98: Mud weight (MW) | B98: 12.5 | C98: ppg | D98: =IFERROR($B$98*119.8264,NA()) | E98: kg/m3
A99: Slug weight (SW) | B99: 14 | C99: ppg | D99: =IFERROR($B$99*119.8264,NA()) | E99: kg/m3
A100: Pipe capacity | B100: 0.01776 | C100: bbl/ft | D100: =IFERROR($B$100*0.5216119,NA()) | E100: m3/m
A101: Slug volume required | B101: =$B$97*$B$98/($B$99-$B$98)*$B$100 | C101: bbl | D101: =IFERROR($B$101*0.1589873,NA()) | E101: m3
A103: Dry Pipe Length from Slug Pumped | F103: L_dry [ft] = V_slug / C_pipe x (SW - MW) / MW
A104: Slug volume pumped | B104: 30 | C104: bbl | D104: =IFERROR($B$104*0.1589873,NA()) | E104: m3
A105: Slug weight (SW) | B105: 14 | C105: ppg | D105: =IFERROR($B$105*119.8264,NA()) | E105: kg/m3
A106: Mud weight (MW) | B106: 12.5 | C106: ppg | D106: =IFERROR($B$106*119.8264,NA()) | E106: kg/m3
A107: Pipe capacity | B107: 0.01776 | C107: bbl/ft | D107: =IFERROR($B$107*0.5216119,NA()) | E107: m3/m
A108: Expected dry pipe length | B108: =$B$104/$B$107*($B$105-$B$106)/$B$106 | C108: ft | D108: =IFERROR($B$108*0.3048,NA()) | E108: m

Sheet Kill Sheet
A1: Well Control Kill Sheet - Surface BOP (Vertical / Deviated / Horizontal)
A2: Component-level volumes, kill mud weight, ICP/FCP, survey-driven pressure schedule and auto-generated kill plot
A4: Parameter | B4: Value | C4: Unit | D4: SI Value | E4: SI Unit | F4: Notes / Equation
A6: 1. Pre-Recorded Data (light blue = linked to Well Data sheet)
A8: Well & Pump Data
F9: Linked to the Well Data sheet - update there, or overwrite locally. The schedule below also reads the Directional Survey sheet directly.
A10: Current mud weight (OMW) | B10: =WD_OMW | C10: ppg | D10: =IFERROR($B$10*119.8264,NA()) | E10: kg/m3 | F10: Linked to Well Data sheet - overwrite locally if this well differs.
A11: Bit / hole measured depth (MD) | B11: =WD_MD | C11: ft | D11: =IFERROR($B$11*0.3048,NA()) | E11: m | F11: Linked to Well Data sheet - overwrite locally if this well differs.
A12: Bit / hole true vertical depth (TVD) | B12: =WD_TVD | C12: ft | D12: =IFERROR($B$12*0.3048,NA()) | E12: m | F12: Linked to Well Data sheet - overwrite locally if this well differs.
A13: Casing shoe MD | B13: =WD_ShoeMD | C13: ft | D13: =IFERROR($B$13*0.3048,NA()) | E13: m | F13: Linked to Well Data sheet - overwrite locally if this well differs.
A14: Casing shoe TVD | B14: =WD_ShoeTVD | C14: ft | D14: =IFERROR($B$14*0.3048,NA()) | E14: m | F14: Linked to Well Data sheet - overwrite locally if this well differs.
A15: LOT / FIT equivalent mud weight | B15: =WD_LOT | C15: ppg | D15: =IFERROR($B$15*119.8264,NA()) | E15: kg/m3 | F15: Linked to Well Data sheet - overwrite locally if this well differs.
A16: Slow circulating rate pressure (SCR) | B16: =WD_SCR | C16: psi | D16: =IFERROR($B$16*6.894757,NA()) | E16: kPa | F16: Linked to Well Data sheet - overwrite locally if this well differs.
A17: Pump output | B17: =WD_SPR | C17: bbl/stk | D17: =IFERROR($B$17*158.9873,NA()) | E17: L/stk | F17: Linked to Well Data sheet - overwrite locally if this well differs.
A18: Kill rate | B18: =WD_KillRate | F18: strokes per minute (spm); linked to Well Data.
A20: Maximum Allowable Annular Surface Pressure (MAASP) | F20: MAASP = (LOT_EMW - MW) x 0.052 x Shoe TVD
F21: Valid only while the annulus above the shoe contains mud of density MW. Rounding rule: maximized values round UP to whole psi (1000.1 -> 1001).
A22: MAASP (initial, with current mud) | B22: =ROUNDUP(ROUND(($B$15-$B$10)*0.052*$B$14,6),0) | C22: psi | D22: =IFERROR($B$22*6.894757,NA()) | E22: kPa
A24: 2. Drill String Volume (component by component, top down)
A25: Pick components from the dropdown (Tubular Library) - OD/ID auto-fill. For non-catalog pipe, type any name and overwrite OD/ID. Unused rows stay blank.
A26: Component | B26: OD (in) | C26: ID (in) | D26: Length (ft) | E26: Capacity (bbl/ft) | F26: Volume (bbl) | G26: Top MD (ft) | H26: Cum vol at top (bbl)
A27: DP 5 19.50# | B27: =IF($A27="","",IFERROR(VLOOKUP($A27,TL_Table,2,FALSE),"")) | C27: =IF($A27="","",IFERROR(VLOOKUP($A27,TL_Table,3,FALSE),"")) | D27: 9700 | E27: =IF($C27="",0,$C27^2/1029.4) | F27: =$E27*IF($D27="",0,$D27) | G27: =0 | H27: =0
A28: HWDP 5 49.3# | B28: =IF($A28="","",IFERROR(VLOOKUP($A28,TL_Table,2,FALSE),"")) | C28: =IF($A28="","",IFERROR(VLOOKUP($A28,TL_Table,3,FALSE),"")) | D28: 500 | E28: =IF($C28="",0,$C28^2/1029.4) | F28: =$E28*IF($D28="",0,$D28) | G28: =$G27+IF($D27="",0,$D27) | H28: =$H27+$F27
A29: DC 6-1/2 92# | B29: =IF($A29="","",IFERROR(VLOOKUP($A29,TL_Table,2,FALSE),"")) | C29: =IF($A29="","",IFERROR(VLOOKUP($A29,TL_Table,3,FALSE),"")) | D29: 300 | E29: =IF($C29="",0,$C29^2/1029.4) | F29: =$E29*IF($D29="",0,$D29) | G29: =$G28+IF($D28="",0,$D28) | H29: =$H28+$F28
B30: =IF($A30="","",IFERROR(VLOOKUP($A30,TL_Table,2,FALSE),"")) | C30: =IF($A30="","",IFERROR(VLOOKUP($A30,TL_Table,3,FALSE),"")) | E30: =IF($C30="",0,$C30^2/1029.4) | F30: =$E30*IF($D30="",0,$D30) | G30: =$G29+IF($D29="",0,$D29) | H30: =$H29+$F29
B31: =IF($A31="","",IFERROR(VLOOKUP($A31,TL_Table,2,FALSE),"")) | C31: =IF($A31="","",IFERROR(VLOOKUP($A31,TL_Table,3,FALSE),"")) | E31: =IF($C31="",0,$C31^2/1029.4) | F31: =$E31*IF($D31="",0,$D31) | G31: =$G30+IF($D30="",0,$D30) | H31: =$H30+$F30
B32: =IF($A32="","",IFERROR(VLOOKUP($A32,TL_Table,2,FALSE),"")) | C32: =IF($A32="","",IFERROR(VLOOKUP($A32,TL_Table,3,FALSE),"")) | E32: =IF($C32="",0,$C32^2/1029.4) | F32: =$E32*IF($D32="",0,$D32) | G32: =$G31+IF($D31="",0,$D31) | H32: =$H31+$F31
B33: =IF($A33="","",IFERROR(VLOOKUP($A33,TL_Table,2,FALSE),"")) | C33: =IF($A33="","",IFERROR(VLOOKUP($A33,TL_Table,3,FALSE),"")) | E33: =IF($C33="",0,$C33^2/1029.4) | F33: =$E33*IF($D33="",0,$D33) | G33: =$G32+IF($D32="",0,$D32) | H33: =$H32+$F32
B34: =IF($A34="","",IFERROR(VLOOKUP($A34,TL_Table,2,FALSE),"")) | C34: =IF($A34="","",IFERROR(VLOOKUP($A34,TL_Table,3,FALSE),"")) | E34: =IF($C34="",0,$C34^2/1029.4) | F34: =$E34*IF($D34="",0,$D34) | G34: =$G33+IF($D33="",0,$D33) | H34: =$H33+$F33
A36: Drill String Totals | F36: Capacity = ID^2/1029.4 [bbl/ft]; Strokes = Volume / Pump output
A37: Total string length | B37: =SUM($D$27:$D$34) | C37: ft | D37: =IFERROR($B$37*0.3048,NA()) | E37: m
A38: Length check vs bit MD | B38: =IF($B$37=$B$11,"OK - matches bit MD","CHECK: components <> bit MD")
A39: Drill string volume | B39: =SUM($F$27:$F$34) | C39: bbl | D39: =IFERROR($B$39*0.1589873,NA()) | E39: m3
A40: Strokes surface to bit | B40: =ROUNDUP(ROUND($B$39/$B$17,6),0)
A41: Time surface to bit | B41: =$B$40/$B$18 | F41: minutes at kill rate
A43: 3. Annulus Volume (bottom up)
A44: Section | B44: Hole/Csg ID (in) | C44: Pipe OD (in) | D44: Length (ft) | E44: Capacity (bbl/ft) | F44: Volume (bbl)
A45: DC x open hole | B45: 8.5 | C45: 6.5 | D45: 300 | E45: =IF(OR($B45="",$C45=""),0,($B45^2-$C45^2)/1029.4) | F45: =$E45*IF($D45="",0,$D45)
A46: DP x open hole | B46: 8.5 | C46: 5 | D46: 4300 | E46: =IF(OR($B46="",$C46=""),0,($B46^2-$C46^2)/1029.4) | F46: =$E46*IF($D46="",0,$D46)
A47: DP x casing | B47: 8.681 | C47: 5 | D47: 5900 | E47: =IF(OR($B47="",$C47=""),0,($B47^2-$C47^2)/1029.4) | F47: =$E47*IF($D47="",0,$D47)
E48: =IF(OR($B48="",$C48=""),0,($B48^2-$C48^2)/1029.4) | F48: =$E48*IF($D48="",0,$D48)
E49: =IF(OR($B49="",$C49=""),0,($B49^2-$C49^2)/1029.4) | F49: =$E49*IF($D49="",0,$D49)
E50: =IF(OR($B50="",$C50=""),0,($B50^2-$C50^2)/1029.4) | F50: =$E50*IF($D50="",0,$D50)
A52: Annulus Totals | F52: Annular capacity = (Dh^2 - Dp^2)/1029.4 [bbl/ft]
A53: Annulus volume | B53: =SUM($F$45:$F$50) | C53: bbl | D53: =IFERROR($B$53*0.1589873,NA()) | E53: m3
A54: Strokes bit to surface | B54: =ROUNDUP(ROUND($B$53/$B$17,6),0)
A55: Total circulation strokes | B55: =$B$40+$B$54
A56: Total circulation time | B56: =$B$55/$B$18 | F56: minutes at kill rate
A58: 4. Kick Data (Shut-In)
A60: Recorded on Shut-In
F61: Allow pressures to stabilise; watch for gas migration on SIDPP. On horizontal wells an influx lying in the lateral may show little or no SICP-SIDPP difference until it enters the build.
A62: Shut-in drill pipe pressure (SIDPP) | B62: 500 | C62: psi | D62: =IFERROR($B$62*6.894757,NA()) | E62: kPa
A63: Shut-in casing pressure (SICP) | B63: 700 | C63: psi | D63: =IFERROR($B$63*6.894757,NA()) | E63: kPa
A64: Pit gain | B64: 15 | C64: bbl | D64: =IFERROR($B$64*0.1589873,NA()) | E64: m3
A66: 5. Kill Calculations
A68: Kill Mud Weight (KMW) | F68: KMW = OMW + SIDPP / (0.052 x TVD)
F69: TVD, never MD. Round UP to the nearest 0.1 ppg for practical mixing.
A70: Kill mud weight (exact) | B70: =$B$10+$B$62/(0.052*$B$12) | C70: ppg | D70: =IFERROR($B$70*119.8264,NA()) | E70: kg/m3
A71: Kill mud weight (rounded up) | B71: =ROUNDUP(ROUND($B$70*10,6),0)/10 | C71: ppg | D71: =IFERROR($B$71*119.8264,NA()) | E71: kg/m3
A73: Initial & Final Circulating Pressure | F73: ICP = SCR + SIDPP; FCP = SCR x KMW / OMW
A74: Initial circulating pressure (ICP) | B74: =$B$16+$B$62 | C74: psi | D74: =IFERROR($B$74*6.894757,NA()) | E74: kPa
A75: Final circulating pressure (FCP) | B75: =$B$16*$B$71/$B$10 | C75: psi | D75: =IFERROR($B$75*6.894757,NA()) | E75: kPa
A76: Pressure drop per 100 strokes (vertical well) | B76: =ROUNDDOWN(ROUND(($B$74-$B$75)/$B$40*100,6),0) | C76: psi | D76: =IFERROR($B$76*6.894757,NA()) | E76: kPa | F76: Rounding rule: psi/step always rounds DOWN (161.9 -> 161). Linear ICP->FCP ramp is only valid for near-vertical wells - use the survey-driven schedule below for deviated/horizontal wells.
A78: Bottomhole Pressure (constant during kill) | F78: BHP = SIDPP + 0.052 x OMW x TVD
A79: Formation pressure | B79: =$B$62+0.052*$B$10*$B$12 | C79: psi | D79: =IFERROR($B$79*6.894757,NA()) | E79: kPa
A80: Formation pressure EMW | B80: =($B$62+0.052*$B$10*$B$12)/(0.052*$B$12) | C80: ppg | D80: =IFERROR($B$80*119.8264,NA()) | E80: kg/m3
A82: Influx Characterisation | F82: h_influx = Pit gain / Ann. capacity (at BHA); Grad_influx = 0.052 x OMW - (SICP - SIDPP) / h_influx
F83: Gas ~0.05-0.25 psi/ft, oil ~0.3-0.4, salt water ~0.4-0.5. Assumes influx around the BHA and a VERTICAL influx column - unreliable in a lateral, where the influx adds little vertical height.
A84: Influx height (along hole) | B84: =$B$64/$E$45 | C84: ft | D84: =IFERROR($B$84*0.3048,NA()) | E84: m
A85: Influx gradient | B85: =0.052*$B$10-($B$63-$B$62)/$B$84 | C85: psi/ft | D85: =IFERROR($B$85*22.62059,NA()) | E85: kPa/m
A86: Likely influx type | B86: =IF($B$85<0.25,"GAS",IF($B$85<0.4,"OIL / GAS-CUT","WATER"))
A88: MAASP After Kill | F88: MAASP_kill = (LOT_EMW - KMW) x 0.052 x Shoe TVD
F89: Rounding rule: maximized values round UP to whole psi.
A90: MAASP with kill mud | B90: =ROUNDUP(ROUND(($B$15-$B$71)*0.052*$B$14,6),0) | C90: psi | D90: =IFERROR($B$90*6.894757,NA()) | E90: kPa
A92: 6. Kill Schedule - Survey-Driven (valid for any trajectory)
A93: Front MD: pumped volume located in the string tables above. Front TVD: interpolated from the Directional Survey sheet. P = SIDPP - 0.052 x (KMW-OMW) x TVD(front) + SCR + (FCP-SCR) x s. With KMW rounded up, the final pressure ends slightly below FCP (slight overbalance - normal). The 'vertical well' column steps down by the ROUNDDOWN psi/100stk figure (never below FCP), the way the schedule is written on a manual kill sheet.
A94: % strokes to bit | B94: Strokes | C94: Front MD (ft) | D94: Front TVD (ft) | E94: DP pressure (psi) | F94: Vertical-well ramp (psi)
A95: 0 | B95: =ROUND($B$40*0.0,0) | C95: =INDEX($G$27:$G$34,MATCH((0.0*$B$39),$H$27:$H$34,1))+IF(INDEX($E$27:$E$34,MATCH((0.0*$B$39),$H$27:$H$34,1))=0,0,((0.0*$B$39)-INDEX($H$27:$H$34,MATCH((0.0*$B$39),$H$27:$H$34,1)))/INDEX($E$27:$E$34,MATCH((0.0*$B$39),$H$27:$H$34,1))) | D95: =INDEX('Directional Survey'!$J$7:$J$106,MATCH($C95,'Directional Survey'!$I$7:$I$106,1))+($C95-INDEX('Directional Survey'!$I$7:$I$106,MATCH($C95,'Directional Survey'!$I$7:$I$106,1)))*(IFERROR(INDEX('Directional Survey'!$J$7:$J$106,MATCH($C95,'Directional Survey'!$I$7:$I$106,1)+1),INDEX('Directional Survey'!$J$7:$J$106,MATCH($C95,'Directional Survey'!$I$7:$I$106,1)))-INDEX('Directional Survey'!$J$7:$J$106,MATCH($C95,'Directional Survey'!$I$7:$I$106,1)))/(IFERROR(INDEX('Directional Survey'!$I$7:$I$106,MATCH($C95,'Directional Survey'!$I$7:$I$106,1)+1),9.9E+99)-INDEX('Directional Survey'!$I$7:$I$106,MATCH($C95,'Directional Survey'!$I$7:$I$106,1))) | E95: =ROUND($B$62-0.052*($B$71-$B$10)*$D95+$B$16+($B$75-$B$16)*0.0,0) | F95: =MAX($B$75,$B$74-$B$76*$B95/100)
A96: 0.05 | B96: =ROUND($B$40*0.05,0) | C96: =INDEX($G$27:$G$34,MATCH((0.05*$B$39),$H$27:$H$34,1))+IF(INDEX($E$27:$E$34,MATCH((0.05*$B$39),$H$27:$H$34,1))=0,0,((0.05*$B$39)-INDEX($H$27:$H$34,MATCH((0.05*$B$39),$H$27:$H$34,1)))/INDEX($E$27:$E$34,MATCH((0.05*$B$39),$H$27:$H$34,1))) | D96: =INDEX('Directional Survey'!$J$7:$J$106,MATCH($C96,'Directional Survey'!$I$7:$I$106,1))+($C96-INDEX('Directional Survey'!$I$7:$I$106,MATCH($C96,'Directional Survey'!$I$7:$I$106,1)))*(IFERROR(INDEX('Directional Survey'!$J$7:$J$106,MATCH($C96,'Directional Survey'!$I$7:$I$106,1)+1),INDEX('Directional Survey'!$J$7:$J$106,MATCH($C96,'Directional Survey'!$I$7:$I$106,1)))-INDEX('Directional Survey'!$J$7:$J$106,MATCH($C96,'Directional Survey'!$I$7:$I$106,1)))/(IFERROR(INDEX('Directional Survey'!$I$7:$I$106,MATCH($C96,'Directional Survey'!$I$7:$I$106,1)+1),9.9E+99)-INDEX('Directional Survey'!$I$7:$I$106,MATCH($C96,'Directional Survey'!$I$7:$I$106,1))) | E96: =ROUND($B$62-0.052*($B$71-$B$10)*$D96+$B$16+($B$75-$B$16)*0.05,0) | F96: =MAX($B$75,$B$74-$B$76*$B96/100)
A97: 0.1 | B97: =ROUND($B$40*0.1,0) | C97: =INDEX($G$27:$G$34,MATCH((0.1*$B$39),$H$27:$H$34,1))+IF(INDEX($E$27:$E$34,MATCH((0.1*$B$39),$H$27:$H$34,1))=0,0,((0.1*$B$39)-INDEX($H$27:$H$34,MATCH((0.1*$B$39),$H$27:$H$34,1)))/INDEX($E$27:$E$34,MATCH((0.1*$B$39),$H$27:$H$34,1))) | D97: =INDEX('Directional Survey'!$J$7:$J$106,MATCH($C97,'Directional Survey'!$I$7:$I$106,1))+($C97-INDEX('Directional Survey'!$I$7:$I$106,MATCH($C97,'Directional Survey'!$I$7:$I$106,1)))*(IFERROR(INDEX('Directional Survey'!$J$7:$J$106,MATCH($C97,'Directional Survey'!$I$7:$I$106,1)+1),INDEX('Directional Survey'!$J$7:$J$106,MATCH($C97,'Directional Survey'!$I$7:$I$106,1)))-INDEX('Directional Survey'!$J$7:$J$106,MATCH($C97,'Directional Survey'!$I$7:$I$106,1)))/(IFERROR(INDEX('Directional Survey'!$I$7:$I$106,MATCH($C97,'Directional Survey'!$I$7:$I$106,1)+1),9.9E+99)-INDEX('Directional Survey'!$I$7:$I$106,MATCH($C97,'Directional Survey'!$I$7:$I$106,1))) | E97: =ROUND($B$62-0.052*($B$71-$B$10)*$D97+$B$16+($B$75-$B$16)*0.1,0) | F97: =MAX($B$75,$B$74-$B$76*$B97/100)
A98: 0.15 | B98: =ROUND($B$40*0.15,0) | C98: =INDEX($G$27:$G$34,MATCH((0.15*$B$39),$H$27:$H$34,1))+IF(INDEX($E$27:$E$34,MATCH((0.15*$B$39),$H$27:$H$34,1))=0,0,((0.15*$B$39)-INDEX($H$27:$H$34,MATCH((0.15*$B$39),$H$27:$H$34,1)))/INDEX($E$27:$E$34,MATCH((0.15*$B$39),$H$27:$H$34,1))) | D98: =INDEX('Directional Survey'!$J$7:$J$106,MATCH($C98,'Directional Survey'!$I$7:$I$106,1))+($C98-INDEX('Directional Survey'!$I$7:$I$106,MATCH($C98,'Directional Survey'!$I$7:$I$106,1)))*(IFERROR(INDEX('Directional Survey'!$J$7:$J$106,MATCH($C98,'Directional Survey'!$I$7:$I$106,1)+1),INDEX('Directional Survey'!$J$7:$J$106,MATCH($C98,'Directional Survey'!$I$7:$I$106,1)))-INDEX('Directional Survey'!$J$7:$J$106,MATCH($C98,'Directional Survey'!$I$7:$I$106,1)))/(IFERROR(INDEX('Directional Survey'!$I$7:$I$106,MATCH($C98,'Directional Survey'!$I$7:$I$106,1)+1),9.9E+99)-INDEX('Directional Survey'!$I$7:$I$106,MATCH($C98,'Directional Survey'!$I$7:$I$106,1))) | E98: =ROUND($B$62-0.052*($B$71-$B$10)*$D98+$B$16+($B$75-$B$16)*0.15,0) | F98: =MAX($B$75,$B$74-$B$76*$B98/100)
A99: 0.2 | B99: =ROUND($B$40*0.2,0) | C99: =INDEX($G$27:$G$34,MATCH((0.2*$B$39),$H$27:$H$34,1))+IF(INDEX($E$27:$E$34,MATCH((0.2*$B$39),$H$27:$H$34,1))=0,0,((0.2*$B$39)-INDEX($H$27:$H$34,MATCH((0.2*$B$39),$H$27:$H$34,1)))/INDEX($E$27:$E$34,MATCH((0.2*$B$39),$H$27:$H$34,1))) | D99: =INDEX('Directional Survey'!$J$7:$J$106,MATCH($C99,'Directional Survey'!$I$7:$I$106,1))+($C99-INDEX('Directional Survey'!$I$7:$I$106,MATCH($C99,'Directional Survey'!$I$7:$I$106,1)))*(IFERROR(INDEX('Directional Survey'!$J$7:$J$106,MATCH($C99,'Directional Survey'!$I$7:$I$106,1)+1),INDEX('Directional Survey'!$J$7:$J$106,MATCH($C99,'Directional Survey'!$I$7:$I$106,1)))-INDEX('Directional Survey'!$J$7:$J$106,MATCH($C99,'Directional Survey'!$I$7:$I$106,1)))/(IFERROR(INDEX('Directional Survey'!$I$7:$I$106,MATCH($C99,'Directional Survey'!$I$7:$I$106,1)+1),9.9E+99)-INDEX('Directional Survey'!$I$7:$I$106,MATCH($C99,'Directional Survey'!$I$7:$I$106,1))) | E99: =ROUND($B$62-0.052*($B$71-$B$10)*$D99+$B$16+($B$75-$B$16)*0.2,0) | F99: =MAX($B$75,$B$74-$B$76*$B99/100)
A100: 0.25 | B100: =ROUND($B$40*0.25,0) | C100: =INDEX($G$27:$G$34,MATCH((0.25*$B$39),$H$27:$H$34,1))+IF(INDEX($E$27:$E$34,MATCH((0.25*$B$39),$H$27:$H$34,1))=0,0,((0.25*$B$39)-INDEX($H$27:$H$34,MATCH((0.25*$B$39),$H$27:$H$34,1)))/INDEX($E$27:$E$34,MATCH((0.25*$B$39),$H$27:$H$34,1))) | D100: =INDEX('Directional Survey'!$J$7:$J$106,MATCH($C100,'Directional Survey'!$I$7:$I$106,1))+($C100-INDEX('Directional Survey'!$I$7:$I$106,MATCH($C100,'Directional Survey'!$I$7:$I$106,1)))*(IFERROR(INDEX('Directional Survey'!$J$7:$J$106,MATCH($C100,'Directional Survey'!$I$7:$I$106,1)+1),INDEX('Directional Survey'!$J$7:$J$106,MATCH($C100,'Directional Survey'!$I$7:$I$106,1)))-INDEX('Directional Survey'!$J$7:$J$106,MATCH($C100,'Directional Survey'!$I$7:$I$106,1)))/(IFERROR(INDEX('Directional Survey'!$I$7:$I$106,MATCH($C100,'Directional Survey'!$I$7:$I$106,1)+1),9.9E+99)-INDEX('Directional Survey'!$I$7:$I$106,MATCH($C100,'Directional Survey'!$I$7:$I$106,1))) | E100: =ROUND($B$62-0.052*($B$71-$B$10)*$D100+$B$16+($B$75-$B$16)*0.25,0) | F100: =MAX($B$75,$B$74-$B$76*$B100/100)
A101: 0.3 | B101: =ROUND($B$40*0.3,0) | C101: =INDEX($G$27:$G$34,MATCH((0.3*$B$39),$H$27:$H$34,1))+IF(INDEX($E$27:$E$34,MATCH((0.3*$B$39),$H$27:$H$34,1))=0,0,((0.3*$B$39)-INDEX($H$27:$H$34,MATCH((0.3*$B$39),$H$27:$H$34,1)))/INDEX($E$27:$E$34,MATCH((0.3*$B$39),$H$27:$H$34,1))) | D101: =INDEX('Directional Survey'!$J$7:$J$106,MATCH($C101,'Directional Survey'!$I$7:$I$106,1))+($C101-INDEX('Directional Survey'!$I$7:$I$106,MATCH($C101,'Directional Survey'!$I$7:$I$106,1)))*(IFERROR(INDEX('Directional Survey'!$J$7:$J$106,MATCH($C101,'Directional Survey'!$I$7:$I$106,1)+1),INDEX('Directional Survey'!$J$7:$J$106,MATCH($C101,'Directional Survey'!$I$7:$I$106,1)))-INDEX('Directional Survey'!$J$7:$J$106,MATCH($C101,'Directional Survey'!$I$7:$I$106,1)))/(IFERROR(INDEX('Directional Survey'!$I$7:$I$106,MATCH($C101,'Directional Survey'!$I$7:$I$106,1)+1),9.9E+99)-INDEX('Directional Survey'!$I$7:$I$106,MATCH($C101,'Directional Survey'!$I$7:$I$106,1))) | E101: =ROUND($B$62-0.052*($B$71-$B$10)*$D101+$B$16+($B$75-$B$16)*0.3,0) | F101: =MAX($B$75,$B$74-$B$76*$B101/100)
A102: 0.35 | B102: =ROUND($B$40*0.35,0) | C102: =INDEX($G$27:$G$34,MATCH((0.35*$B$39),$H$27:$H$34,1))+IF(INDEX($E$27:$E$34,MATCH((0.35*$B$39),$H$27:$H$34,1))=0,0,((0.35*$B$39)-INDEX($H$27:$H$34,MATCH((0.35*$B$39),$H$27:$H$34,1)))/INDEX($E$27:$E$34,MATCH((0.35*$B$39),$H$27:$H$34,1))) | D102: =INDEX('Directional Survey'!$J$7:$J$106,MATCH($C102,'Directional Survey'!$I$7:$I$106,1))+($C102-INDEX('Directional Survey'!$I$7:$I$106,MATCH($C102,'Directional Survey'!$I$7:$I$106,1)))*(IFERROR(INDEX('Directional Survey'!$J$7:$J$106,MATCH($C102,'Directional Survey'!$I$7:$I$106,1)+1),INDEX('Directional Survey'!$J$7:$J$106,MATCH($C102,'Directional Survey'!$I$7:$I$106,1)))-INDEX('Directional Survey'!$J$7:$J$106,MATCH($C102,'Directional Survey'!$I$7:$I$106,1)))/(IFERROR(INDEX('Directional Survey'!$I$7:$I$106,MATCH($C102,'Directional Survey'!$I$7:$I$106,1)+1),9.9E+99)-INDEX('Directional Survey'!$I$7:$I$106,MATCH($C102,'Directional Survey'!$I$7:$I$106,1))) | E102: =ROUND($B$62-0.052*($B$71-$B$10)*$D102+$B$16+($B$75-$B$16)*0.35,0) | F102: =MAX($B$75,$B$74-$B$76*$B102/100)
A103: 0.4 | B103: =ROUND($B$40*0.4,0) | C103: =INDEX($G$27:$G$34,MATCH((0.4*$B$39),$H$27:$H$34,1))+IF(INDEX($E$27:$E$34,MATCH((0.4*$B$39),$H$27:$H$34,1))=0,0,((0.4*$B$39)-INDEX($H$27:$H$34,MATCH((0.4*$B$39),$H$27:$H$34,1)))/INDEX($E$27:$E$34,MATCH((0.4*$B$39),$H$27:$H$34,1))) | D103: =INDEX('Directional Survey'!$J$7:$J$106,MATCH($C103,'Directional Survey'!$I$7:$I$106,1))+($C103-INDEX('Directional Survey'!$I$7:$I$106,MATCH($C103,'Directional Survey'!$I$7:$I$106,1)))*(IFERROR(INDEX('Directional Survey'!$J$7:$J$106,MATCH($C103,'Directional Survey'!$I$7:$I$106,1)+1),INDEX('Directional Survey'!$J$7:$J$106,MATCH($C103,'Directional Survey'!$I$7:$I$106,1)))-INDEX('Directional Survey'!$J$7:$J$106,MATCH($C103,'Directional Survey'!$I$7:$I$106,1)))/(IFERROR(INDEX('Directional Survey'!$I$7:$I$106,MATCH($C103,'Directional Survey'!$I$7:$I$106,1)+1),9.9E+99)-INDEX('Directional Survey'!$I$7:$I$106,MATCH($C103,'Directional Survey'!$I$7:$I$106,1))) | E103: =ROUND($B$62-0.052*($B$71-$B$10)*$D103+$B$16+($B$75-$B$16)*0.4,0) | F103: =MAX($B$75,$B$74-$B$76*$B103/100)
A104: 0.45 | B104: =ROUND($B$40*0.45,0) | C104: =INDEX($G$27:$G$34,MATCH((0.45*$B$39),$H$27:$H$34,1))+IF(INDEX($E$27:$E$34,MATCH((0.45*$B$39),$H$27:$H$34,1))=0,0,((0.45*$B$39)-INDEX($H$27:$H$34,MATCH((0.45*$B$39),$H$27:$H$34,1)))/INDEX($E$27:$E$34,MATCH((0.45*$B$39),$H$27:$H$34,1))) | D104: =INDEX('Directional Survey'!$J$7:$J$106,MATCH($C104,'Directional Survey'!$I$7:$I$106,1))+($C104-INDEX('Directional Survey'!$I$7:$I$106,MATCH($C104,'Directional Survey'!$I$7:$I$106,1)))*(IFERROR(INDEX('Directional Survey'!$J$7:$J$106,MATCH($C104,'Directional Survey'!$I$7:$I$106,1)+1),INDEX('Directional Survey'!$J$7:$J$106,MATCH($C104,'Directional Survey'!$I$7:$I$106,1)))-INDEX('Directional Survey'!$J$7:$J$106,MATCH($C104,'Directional Survey'!$I$7:$I$106,1)))/(IFERROR(INDEX('Directional Survey'!$I$7:$I$106,MATCH($C104,'Directional Survey'!$I$7:$I$106,1)+1),9.9E+99)-INDEX('Directional Survey'!$I$7:$I$106,MATCH($C104,'Directional Survey'!$I$7:$I$106,1))) | E104: =ROUND($B$62-0.052*($B$71-$B$10)*$D104+$B$16+($B$75-$B$16)*0.45,0) | F104: =MAX($B$75,$B$74-$B$76*$B104/100)
A105: 0.5 | B105: =ROUND($B$40*0.5,0) | C105: =INDEX($G$27:$G$34,MATCH((0.5*$B$39),$H$27:$H$34,1))+IF(INDEX($E$27:$E$34,MATCH((0.5*$B$39),$H$27:$H$34,1))=0,0,((0.5*$B$39)-INDEX($H$27:$H$34,MATCH((0.5*$B$39),$H$27:$H$34,1)))/INDEX($E$27:$E$34,MATCH((0.5*$B$39),$H$27:$H$34,1))) | D105: =INDEX('Directional Survey'!$J$7:$J$106,MATCH($C105,'Directional Survey'!$I$7:$I$106,1))+($C105-INDEX('Directional Survey'!$I$7:$I$106,MATCH($C105,'Directional Survey'!$I$7:$I$106,1)))*(IFERROR(INDEX('Directional Survey'!$J$7:$J$106,MATCH($C105,'Directional Survey'!$I$7:$I$106,1)+1),INDEX('Directional Survey'!$J$7:$J$106,MATCH($C105,'Directional Survey'!$I$7:$I$106,1)))-INDEX('Directional Survey'!$J$7:$J$106,MATCH($C105,'Directional Survey'!$I$7:$I$106,1)))/(IFERROR(INDEX('Directional Survey'!$I$7:$I$106,MATCH($C105,'Directional Survey'!$I$7:$I$106,1)+1),9.9E+99)-INDEX('Directional Survey'!$I$7:$I$106,MATCH($C105,'Directional Survey'!$I$7:$I$106,1))) | E105: =ROUND($B$62-0.052*($B$71-$B$10)*$D105+$B$16+($B$75-$B$16)*0.5,0) | F105: =MAX($B$75,$B$74-$B$76*$B105/100)
A106: 0.55 | B106: =ROUND($B$40*0.55,0) | C106: =INDEX($G$27:$G$34,MATCH((0.55*$B$39),$H$27:$H$34,1))+IF(INDEX($E$27:$E$34,MATCH((0.55*$B$39),$H$27:$H$34,1))=0,0,((0.55*$B$39)-INDEX($H$27:$H$34,MATCH((0.55*$B$39),$H$27:$H$34,1)))/INDEX($E$27:$E$34,MATCH((0.55*$B$39),$H$27:$H$34,1))) | D106: =INDEX('Directional Survey'!$J$7:$J$106,MATCH($C106,'Directional Survey'!$I$7:$I$106,1))+($C106-INDEX('Directional Survey'!$I$7:$I$106,MATCH($C106,'Directional Survey'!$I$7:$I$106,1)))*(IFERROR(INDEX('Directional Survey'!$J$7:$J$106,MATCH($C106,'Directional Survey'!$I$7:$I$106,1)+1),INDEX('Directional Survey'!$J$7:$J$106,MATCH($C106,'Directional Survey'!$I$7:$I$106,1)))-INDEX('Directional Survey'!$J$7:$J$106,MATCH($C106,'Directional Survey'!$I$7:$I$106,1)))/(IFERROR(INDEX('Directional Survey'!$I$7:$I$106,MATCH($C106,'Directional Survey'!$I$7:$I$106,1)+1),9.9E+99)-INDEX('Directional Survey'!$I$7:$I$106,MATCH($C106,'Directional Survey'!$I$7:$I$106,1))) | E106: =ROUND($B$62-0.052*($B$71-$B$10)*$D106+$B$16+($B$75-$B$16)*0.55,0) | F106: =MAX($B$75,$B$74-$B$76*$B106/100)
A107: 0.6 | B107: =ROUND($B$40*0.6,0) | C107: =INDEX($G$27:$G$34,MATCH((0.6*$B$39),$H$27:$H$34,1))+IF(INDEX($E$27:$E$34,MATCH((0.6*$B$39),$H$27:$H$34,1))=0,0,((0.6*$B$39)-INDEX($H$27:$H$34,MATCH((0.6*$B$39),$H$27:$H$34,1)))/INDEX($E$27:$E$34,MATCH((0.6*$B$39),$H$27:$H$34,1))) | D107: =INDEX('Directional Survey'!$J$7:$J$106,MATCH($C107,'Directional Survey'!$I$7:$I$106,1))+($C107-INDEX('Directional Survey'!$I$7:$I$106,MATCH($C107,'Directional Survey'!$I$7:$I$106,1)))*(IFERROR(INDEX('Directional Survey'!$J$7:$J$106,MATCH($C107,'Directional Survey'!$I$7:$I$106,1)+1),INDEX('Directional Survey'!$J$7:$J$106,MATCH($C107,'Directional Survey'!$I$7:$I$106,1)))-INDEX('Directional Survey'!$J$7:$J$106,MATCH($C107,'Directional Survey'!$I$7:$I$106,1)))/(IFERROR(INDEX('Directional Survey'!$I$7:$I$106,MATCH($C107,'Directional Survey'!$I$7:$I$106,1)+1),9.9E+99)-INDEX('Directional Survey'!$I$7:$I$106,MATCH($C107,'Directional Survey'!$I$7:$I$106,1))) | E107: =ROUND($B$62-0.052*($B$71-$B$10)*$D107+$B$16+($B$75-$B$16)*0.6,0) | F107: =MAX($B$75,$B$74-$B$76*$B107/100)
A108: 0.65 | B108: =ROUND($B$40*0.65,0) | C108: =INDEX($G$27:$G$34,MATCH((0.65*$B$39),$H$27:$H$34,1))+IF(INDEX($E$27:$E$34,MATCH((0.65*$B$39),$H$27:$H$34,1))=0,0,((0.65*$B$39)-INDEX($H$27:$H$34,MATCH((0.65*$B$39),$H$27:$H$34,1)))/INDEX($E$27:$E$34,MATCH((0.65*$B$39),$H$27:$H$34,1))) | D108: =INDEX('Directional Survey'!$J$7:$J$106,MATCH($C108,'Directional Survey'!$I$7:$I$106,1))+($C108-INDEX('Directional Survey'!$I$7:$I$106,MATCH($C108,'Directional Survey'!$I$7:$I$106,1)))*(IFERROR(INDEX('Directional Survey'!$J$7:$J$106,MATCH($C108,'Directional Survey'!$I$7:$I$106,1)+1),INDEX('Directional Survey'!$J$7:$J$106,MATCH($C108,'Directional Survey'!$I$7:$I$106,1)))-INDEX('Directional Survey'!$J$7:$J$106,MATCH($C108,'Directional Survey'!$I$7:$I$106,1)))/(IFERROR(INDEX('Directional Survey'!$I$7:$I$106,MATCH($C108,'Directional Survey'!$I$7:$I$106,1)+1),9.9E+99)-INDEX('Directional Survey'!$I$7:$I$106,MATCH($C108,'Directional Survey'!$I$7:$I$106,1))) | E108: =ROUND($B$62-0.052*($B$71-$B$10)*$D108+$B$16+($B$75-$B$16)*0.65,0) | F108: =MAX($B$75,$B$74-$B$76*$B108/100)
A109: 0.7 | B109: =ROUND($B$40*0.7,0) | C109: =INDEX($G$27:$G$34,MATCH((0.7*$B$39),$H$27:$H$34,1))+IF(INDEX($E$27:$E$34,MATCH((0.7*$B$39),$H$27:$H$34,1))=0,0,((0.7*$B$39)-INDEX($H$27:$H$34,MATCH((0.7*$B$39),$H$27:$H$34,1)))/INDEX($E$27:$E$34,MATCH((0.7*$B$39),$H$27:$H$34,1))) | D109: =INDEX('Directional Survey'!$J$7:$J$106,MATCH($C109,'Directional Survey'!$I$7:$I$106,1))+($C109-INDEX('Directional Survey'!$I$7:$I$106,MATCH($C109,'Directional Survey'!$I$7:$I$106,1)))*(IFERROR(INDEX('Directional Survey'!$J$7:$J$106,MATCH($C109,'Directional Survey'!$I$7:$I$106,1)+1),INDEX('Directional Survey'!$J$7:$J$106,MATCH($C109,'Directional Survey'!$I$7:$I$106,1)))-INDEX('Directional Survey'!$J$7:$J$106,MATCH($C109,'Directional Survey'!$I$7:$I$106,1)))/(IFERROR(INDEX('Directional Survey'!$I$7:$I$106,MATCH($C109,'Directional Survey'!$I$7:$I$106,1)+1),9.9E+99)-INDEX('Directional Survey'!$I$7:$I$106,MATCH($C109,'Directional Survey'!$I$7:$I$106,1))) | E109: =ROUND($B$62-0.052*($B$71-$B$10)*$D109+$B$16+($B$75-$B$16)*0.7,0) | F109: =MAX($B$75,$B$74-$B$76*$B109/100)
A110: 0.75 | B110: =ROUND($B$40*0.75,0) | C110: =INDEX($G$27:$G$34,MATCH((0.75*$B$39),$H$27:$H$34,1))+IF(INDEX($E$27:$E$34,MATCH((0.75*$B$39),$H$27:$H$34,1))=0,0,((0.75*$B$39)-INDEX($H$27:$H$34,MATCH((0.75*$B$39),$H$27:$H$34,1)))/INDEX($E$27:$E$34,MATCH((0.75*$B$39),$H$27:$H$34,1))) | D110: =INDEX('Directional Survey'!$J$7:$J$106,MATCH($C110,'Directional Survey'!$I$7:$I$106,1))+($C110-INDEX('Directional Survey'!$I$7:$I$106,MATCH($C110,'Directional Survey'!$I$7:$I$106,1)))*(IFERROR(INDEX('Directional Survey'!$J$7:$J$106,MATCH($C110,'Directional Survey'!$I$7:$I$106,1)+1),INDEX('Directional Survey'!$J$7:$J$106,MATCH($C110,'Directional Survey'!$I$7:$I$106,1)))-INDEX('Directional Survey'!$J$7:$J$106,MATCH($C110,'Directional Survey'!$I$7:$I$106,1)))/(IFERROR(INDEX('Directional Survey'!$I$7:$I$106,MATCH($C110,'Directional Survey'!$I$7:$I$106,1)+1),9.9E+99)-INDEX('Directional Survey'!$I$7:$I$106,MATCH($C110,'Directional Survey'!$I$7:$I$106,1))) | E110: =ROUND($B$62-0.052*($B$71-$B$10)*$D110+$B$16+($B$75-$B$16)*0.75,0) | F110: =MAX($B$75,$B$74-$B$76*$B110/100)
A111: 0.8 | B111: =ROUND($B$40*0.8,0) | C111: =INDEX($G$27:$G$34,MATCH((0.8*$B$39),$H$27:$H$34,1))+IF(INDEX($E$27:$E$34,MATCH((0.8*$B$39),$H$27:$H$34,1))=0,0,((0.8*$B$39)-INDEX($H$27:$H$34,MATCH((0.8*$B$39),$H$27:$H$34,1)))/INDEX($E$27:$E$34,MATCH((0.8*$B$39),$H$27:$H$34,1))) | D111: =INDEX('Directional Survey'!$J$7:$J$106,MATCH($C111,'Directional Survey'!$I$7:$I$106,1))+($C111-INDEX('Directional Survey'!$I$7:$I$106,MATCH($C111,'Directional Survey'!$I$7:$I$106,1)))*(IFERROR(INDEX('Directional Survey'!$J$7:$J$106,MATCH($C111,'Directional Survey'!$I$7:$I$106,1)+1),INDEX('Directional Survey'!$J$7:$J$106,MATCH($C111,'Directional Survey'!$I$7:$I$106,1)))-INDEX('Directional Survey'!$J$7:$J$106,MATCH($C111,'Directional Survey'!$I$7:$I$106,1)))/(IFERROR(INDEX('Directional Survey'!$I$7:$I$106,MATCH($C111,'Directional Survey'!$I$7:$I$106,1)+1),9.9E+99)-INDEX('Directional Survey'!$I$7:$I$106,MATCH($C111,'Directional Survey'!$I$7:$I$106,1))) | E111: =ROUND($B$62-0.052*($B$71-$B$10)*$D111+$B$16+($B$75-$B$16)*0.8,0) | F111: =MAX($B$75,$B$74-$B$76*$B111/100)
A112: 0.85 | B112: =ROUND($B$40*0.85,0) | C112: =INDEX($G$27:$G$34,MATCH((0.85*$B$39),$H$27:$H$34,1))+IF(INDEX($E$27:$E$34,MATCH((0.85*$B$39),$H$27:$H$34,1))=0,0,((0.85*$B$39)-INDEX($H$27:$H$34,MATCH((0.85*$B$39),$H$27:$H$34,1)))/INDEX($E$27:$E$34,MATCH((0.85*$B$39),$H$27:$H$34,1))) | D112: =INDEX('Directional Survey'!$J$7:$J$106,MATCH($C112,'Directional Survey'!$I$7:$I$106,1))+($C112-INDEX('Directional Survey'!$I$7:$I$106,MATCH($C112,'Directional Survey'!$I$7:$I$106,1)))*(IFERROR(INDEX('Directional Survey'!$J$7:$J$106,MATCH($C112,'Directional Survey'!$I$7:$I$106,1)+1),INDEX('Directional Survey'!$J$7:$J$106,MATCH($C112,'Directional Survey'!$I$7:$I$106,1)))-INDEX('Directional Survey'!$J$7:$J$106,MATCH($C112,'Directional Survey'!$I$7:$I$106,1)))/(IFERROR(INDEX('Directional Survey'!$I$7:$I$106,MATCH($C112,'Directional Survey'!$I$7:$I$106,1)+1),9.9E+99)-INDEX('Directional Survey'!$I$7:$I$106,MATCH($C112,'Directional Survey'!$I$7:$I$106,1))) | E112: =ROUND($B$62-0.052*($B$71-$B$10)*$D112+$B$16+($B$75-$B$16)*0.85,0) | F112: =MAX($B$75,$B$74-$B$76*$B112/100)
A113: 0.9 | B113: =ROUND($B$40*0.9,0) | C113: =INDEX($G$27:$G$34,MATCH((0.9*$B$39),$H$27:$H$34,1))+IF(INDEX($E$27:$E$34,MATCH((0.9*$B$39),$H$27:$H$34,1))=0,0,((0.9*$B$39)-INDEX($H$27:$H$34,MATCH((0.9*$B$39),$H$27:$H$34,1)))/INDEX($E$27:$E$34,MATCH((0.9*$B$39),$H$27:$H$34,1))) | D113: =INDEX('Directional Survey'!$J$7:$J$106,MATCH($C113,'Directional Survey'!$I$7:$I$106,1))+($C113-INDEX('Directional Survey'!$I$7:$I$106,MATCH($C113,'Directional Survey'!$I$7:$I$106,1)))*(IFERROR(INDEX('Directional Survey'!$J$7:$J$106,MATCH($C113,'Directional Survey'!$I$7:$I$106,1)+1),INDEX('Directional Survey'!$J$7:$J$106,MATCH($C113,'Directional Survey'!$I$7:$I$106,1)))-INDEX('Directional Survey'!$J$7:$J$106,MATCH($C113,'Directional Survey'!$I$7:$I$106,1)))/(IFERROR(INDEX('Directional Survey'!$I$7:$I$106,MATCH($C113,'Directional Survey'!$I$7:$I$106,1)+1),9.9E+99)-INDEX('Directional Survey'!$I$7:$I$106,MATCH($C113,'Directional Survey'!$I$7:$I$106,1))) | E113: =ROUND($B$62-0.052*($B$71-$B$10)*$D113+$B$16+($B$75-$B$16)*0.9,0) | F113: =MAX($B$75,$B$74-$B$76*$B113/100)
A114: 0.95 | B114: =ROUND($B$40*0.95,0) | C114: =INDEX($G$27:$G$34,MATCH((0.95*$B$39),$H$27:$H$34,1))+IF(INDEX($E$27:$E$34,MATCH((0.95*$B$39),$H$27:$H$34,1))=0,0,((0.95*$B$39)-INDEX($H$27:$H$34,MATCH((0.95*$B$39),$H$27:$H$34,1)))/INDEX($E$27:$E$34,MATCH((0.95*$B$39),$H$27:$H$34,1))) | D114: =INDEX('Directional Survey'!$J$7:$J$106,MATCH($C114,'Directional Survey'!$I$7:$I$106,1))+($C114-INDEX('Directional Survey'!$I$7:$I$106,MATCH($C114,'Directional Survey'!$I$7:$I$106,1)))*(IFERROR(INDEX('Directional Survey'!$J$7:$J$106,MATCH($C114,'Directional Survey'!$I$7:$I$106,1)+1),INDEX('Directional Survey'!$J$7:$J$106,MATCH($C114,'Directional Survey'!$I$7:$I$106,1)))-INDEX('Directional Survey'!$J$7:$J$106,MATCH($C114,'Directional Survey'!$I$7:$I$106,1)))/(IFERROR(INDEX('Directional Survey'!$I$7:$I$106,MATCH($C114,'Directional Survey'!$I$7:$I$106,1)+1),9.9E+99)-INDEX('Directional Survey'!$I$7:$I$106,MATCH($C114,'Directional Survey'!$I$7:$I$106,1))) | E114: =ROUND($B$62-0.052*($B$71-$B$10)*$D114+$B$16+($B$75-$B$16)*0.95,0) | F114: =MAX($B$75,$B$74-$B$76*$B114/100)
A115: 1 | B115: =ROUND($B$40*1.0,0) | C115: =INDEX($G$27:$G$34,MATCH((1.0*$B$39),$H$27:$H$34,1))+IF(INDEX($E$27:$E$34,MATCH((1.0*$B$39),$H$27:$H$34,1))=0,0,((1.0*$B$39)-INDEX($H$27:$H$34,MATCH((1.0*$B$39),$H$27:$H$34,1)))/INDEX($E$27:$E$34,MATCH((1.0*$B$39),$H$27:$H$34,1))) | D115: =INDEX('Directional Survey'!$J$7:$J$106,MATCH($C115,'Directional Survey'!$I$7:$I$106,1))+($C115-INDEX('Directional Survey'!$I$7:$I$106,MATCH($C115,'Directional Survey'!$I$7:$I$106,1)))*(IFERROR(INDEX('Directional Survey'!$J$7:$J$106,MATCH($C115,'Directional Survey'!$I$7:$I$106,1)+1),INDEX('Directional Survey'!$J$7:$J$106,MATCH($C115,'Directional Survey'!$I$7:$I$106,1)))-INDEX('Directional Survey'!$J$7:$J$106,MATCH($C115,'Directional Survey'!$I$7:$I$106,1)))/(IFERROR(INDEX('Directional Survey'!$I$7:$I$106,MATCH($C115,'Directional Survey'!$I$7:$I$106,1)+1),9.9E+99)-INDEX('Directional Survey'!$I$7:$I$106,MATCH($C115,'Directional Survey'!$I$7:$I$106,1))) | E115: =ROUND($B$62-0.052*($B$71-$B$10)*$D115+$B$16+($B$75-$B$16)*1.0,0) | F115: =MAX($B$75,$B$74-$B$76*$B115/100)

Sheet Kill Form
A1: WELL KILL SHEET - SURFACE BOP
A3: Well | B3: =WD_Well | D3: Date | E3: =WD_Date
A4: Rig | B4: =WD_Rig | D4: Engineer | E4: =WD_Engineer
A6: PRE-RECORDED DATA
A7: Current mud weight | B7: ='Kill Sheet'!$B$10 | C7: ppg
A8: MD / TVD at bit | B8: ='Kill Sheet'!$B$11 | C8: ft | E8: STROKES | F8: DP PSI
A9: Shoe MD / TVD | B9: ='Kill Sheet'!$B$13 | C9: ft | E9: ='Kill Sheet'!$B95 | F9: ='Kill Sheet'!$E95
A10: LOT EMW | B10: ='Kill Sheet'!$B$15 | C10: ppg | E10: ='Kill Sheet'!$B96 | F10: ='Kill Sheet'!$E96
A11: SCR pressure | B11: ='Kill Sheet'!$B$16 | C11: psi | E11: ='Kill Sheet'!$B97 | F11: ='Kill Sheet'!$E97
A12: Pump output | B12: ='Kill Sheet'!$B$17 | C12: bbl/stk | E12: ='Kill Sheet'!$B98 | F12: ='Kill Sheet'!$E98
A13: Kill rate | B13: ='Kill Sheet'!$B$18 | C13: spm | E13: ='Kill Sheet'!$B99 | F13: ='Kill Sheet'!$E99
A14: MAASP (initial) | B14: ='Kill Sheet'!$B$22 | C14: psi | E14: ='Kill Sheet'!$B100 | F14: ='Kill Sheet'!$E100
E15: ='Kill Sheet'!$B101 | F15: ='Kill Sheet'!$E101
A16: VOLUMES & STROKES | E16: ='Kill Sheet'!$B102 | F16: ='Kill Sheet'!$E102
A17: Drill string volume | B17: ='Kill Sheet'!$B$39 | C17: bbl | E17: ='Kill Sheet'!$B103 | F17: ='Kill Sheet'!$E103
A18: Strokes surface to bit | B18: ='Kill Sheet'!$B$40 | C18: stk | E18: ='Kill Sheet'!$B104 | F18: ='Kill Sheet'!$E104
A19: Annulus volume | B19: ='Kill Sheet'!$B$53 | C19: bbl | E19: ='Kill Sheet'!$B105 | F19: ='Kill Sheet'!$E105
A20: Strokes bit to surface | B20: ='Kill Sheet'!$B$54 | C20: stk | E20: ='Kill Sheet'!$B106 | F20: ='Kill Sheet'!$E106
A21: Total circulation | B21: ='Kill Sheet'!$B$55 | C21: stk | E21: ='Kill Sheet'!$B107 | F21: ='Kill Sheet'!$E107
E22: ='Kill Sheet'!$B108 | F22: ='Kill Sheet'!$E108
A23: KICK DATA | E23: ='Kill Sheet'!$B109 | F23: ='Kill Sheet'!$E109
A24: SIDPP | B24: ='Kill Sheet'!$B$62 | C24: psi | E24: ='Kill Sheet'!$B110 | F24: ='Kill Sheet'!$E110
A25: SICP | B25: ='Kill Sheet'!$B$63 | C25: psi | E25: ='Kill Sheet'!$B111 | F25: ='Kill Sheet'!$E111
A26: Pit gain | B26: ='Kill Sheet'!$B$64 | C26: bbl | E26: ='Kill Sheet'!$B112 | F26: ='Kill Sheet'!$E112
E27: ='Kill Sheet'!$B113 | F27: ='Kill Sheet'!$E113
A28: KILL DATA | E28: ='Kill Sheet'!$B114 | F28: ='Kill Sheet'!$E114
A29: Kill mud weight (rounded up) | B29: ='Kill Sheet'!$B$71 | C29: ppg | E29: ='Kill Sheet'!$B115 | F29: ='Kill Sheet'!$E115
A30: ICP | B30: ='Kill Sheet'!$B$74 | C30: psi | E30: Survey-driven schedule
A31: FCP | B31: ='Kill Sheet'!$B$75 | C31: psi
A32: psi per 100 strokes (rounded down) | B32: ='Kill Sheet'!$B$76 | C32: psi
A33: Formation pressure | B33: ='Kill Sheet'!$B$79 | C33: psi
A34: MAASP after kill | B34: ='Kill Sheet'!$B$90 | C34: psi
A37: Driller: ____________ | C37: Toolpusher: ____________ | E37: Company rep: ____________
A39: Generated from the live Kill Sheet - values update automatically. Verify against stabilised shut-in pressures before pumping.

Sheet Kill Sheet - Subsea
A1: Well Control Kill Sheet - Subsea BOP Supplement
A2: Choke line friction corrections, choke line displacement, riser margin and riser-disconnect hydrostatics (use with the main Kill Sheet)
A4: Parameter | B4: Value | C4: Unit | D4: SI Value | E4: SI Unit | F4: Notes / Equation
A6: Subsea Well Data
A8: Rig, Water Depth & Choke Line
F9: Yellow inputs are subsea-specific for THIS calc (the Well Data master defaults to a land / surface-BOP well). CLF should be MEASURED, not calculated, where possible - record it during slow-rate circulation up the choke line.
A10: Water depth | B10: 1500 | C10: ft | D10: =IFERROR($B$10*0.3048,NA()) | E10: m
A11: Air gap (RKB to sea level) | B11: 75 | C11: ft | D11: =IFERROR($B$11*0.3048,NA()) | E11: m
A12: Choke line length | B12: 1650 | C12: ft | D12: =IFERROR($B$12*0.3048,NA()) | E12: m | F12: Approx. water depth + air gap + stack height.
A13: Choke line ID | B13: 3 | C13: in | D13: =IFERROR($B$13*25.4,NA()) | E13: mm
A14: Choke line friction (CLF) at kill rate | B14: 250 | C14: psi | D14: =IFERROR($B$14*6.894757,NA()) | E14: kPa | F14: Measured at the kill rate circulating up the choke line.
A16: Linked Well Data
F17: Light blue = linked to the Well Data sheet; overwrite locally if this well differs.
A18: Current mud weight (OMW) | B18: =WD_OMW | C18: ppg | D18: =IFERROR($B$18*119.8264,NA()) | E18: kg/m3 | F18: Linked to Well Data sheet - overwrite locally if this well differs.
A19: Bit / TD true vertical depth (TVD) | B19: =WD_TVD | C19: ft | D19: =IFERROR($B$19*0.3048,NA()) | E19: m | F19: Linked to Well Data sheet - overwrite locally if this well differs.
A20: Casing shoe TVD | B20: =WD_ShoeTVD | C20: ft | D20: =IFERROR($B$20*0.3048,NA()) | E20: m | F20: Linked to Well Data sheet - overwrite locally if this well differs.
A21: LOT / FIT equivalent mud weight | B21: =WD_LOT | C21: ppg | D21: =IFERROR($B$21*119.8264,NA()) | E21: kg/m3 | F21: Linked to Well Data sheet - overwrite locally if this well differs.
A22: Slow circulating rate pressure (SCR) | B22: =WD_SCR | C22: psi | D22: =IFERROR($B$22*6.894757,NA()) | E22: kPa | F22: Linked to Well Data sheet - overwrite locally if this well differs.
A23: Pump output | B23: =WD_SPR | C23: bbl/stk | D23: =IFERROR($B$23*158.9873,NA()) | E23: L/stk | F23: Linked to Well Data sheet - overwrite locally if this well differs.
A25: Choke Line
A27: Choke Line Volume & Displacement | F27: Capacity = ID^2 / 1029.4 [bbl/ft]; Strokes = Volume / Pump output
F28: Small ID over a long length: the choke line holds only a few barrels but adds significant friction at kill rate.
A29: Choke line capacity | B29: =$B$13^2/1029.4 | C29: bbl/ft | D29: =IFERROR($B$29*0.5216119,NA()) | E29: m3/m
A30: Choke line volume | B30: =$B$29*$B$12 | C30: bbl | D30: =IFERROR($B$30*0.1589873,NA()) | E30: m3
A31: Strokes to displace choke line | B31: =ROUNDUP(ROUND($B$30/$B$23,6),0)
A33: CLF-Corrected Pressures
A35: Shut-In Pressures
F36: Allow pressures to stabilise; watch for gas migration on SIDPP.
A37: Shut-in drill pipe pressure (SIDPP) | B37: 500 | C37: psi | D37: =IFERROR($B$37*6.894757,NA()) | E37: kPa
A38: Shut-in casing pressure (SICP) | B38: 700 | C38: psi | D38: =IFERROR($B$38*6.894757,NA()) | E38: kPa
A40: MAASP - Static & Dynamic | F40: MAASP_static = (LOT_EMW - MW) x 0.052 x Shoe TVD; MAASP_dynamic = MAASP_static - CLF
F41: With a subsea stack the choke line friction acts on the ANNULUS side: while circulating up the choke line the shoe feels surface choke pressure + CLF, so the allowable surface reading drops by CLF. Rounding rule: maximized values round UP to whole psi.
A42: Static MAASP (well shut in) | B42: =ROUNDUP(ROUND(($B$21-$B$18)*0.052*$B$20,6),0) | C42: psi | D42: =IFERROR($B$42*6.894757,NA()) | E42: kPa
A43: Dynamic MAASP (circulating up choke line) | B43: =ROUNDUP(ROUND($B$42-$B$14,6),0) | C43: psi | D43: =IFERROR($B$43*6.894757,NA()) | E43: kPa
A45: Bringing the Pump to Kill Speed | F45: ICP = SCR + SIDPP (DP side unchanged); Choke pressure to hold = SICP - CLF
F46: The DP-side target (ICP) is unchanged by the subsea stack. But as the pump is brought up, CLF develops in the choke line on the annulus side and adds to bottomhole pressure. To keep BHP constant, open the choke so the surface CASING gauge falls to SICP - CLF while bringing the pump to kill speed (rather than holding SICP as on a surface stack).
A47: Initial circulating pressure (ICP) | B47: =$B$22+$B$37 | C47: psi | D47: =IFERROR($B$47*6.894757,NA()) | E47: kPa | F47: SCR should itself be measured circulating up the choke line.
A48: Choke pressure while bringing pump up | B48: =MAX(0,$B$38-$B$14) | C48: psi | D48: =IFERROR($B$48*6.894757,NA()) | E48: kPa
A50: Kill Mud & Gas at Surface
A52: Kill Mud Weight (KMW) | F52: KMW = OMW + SIDPP / (0.052 x TVD)
F53: TVD, never MD. Rounding rule: kill density always rounds UP to the nearest 0.1 ppg.
A54: Kill mud weight (exact) | B54: =$B$18+$B$37/(0.052*$B$19) | C54: ppg | D54: =IFERROR($B$54*119.8264,NA()) | E54: kg/m3
A55: Kill mud weight (rounded up) | B55: =ROUNDUP(ROUND($B$54*10,6),0)/10 | C55: ppg | D55: =IFERROR($B$55*119.8264,NA()) | E55: kg/m3
A56: Gas in the choke line | F56: Gas circulated up the narrow choke line expands very rapidly near surface - expect sudden unloading and fast choke response late in the circulation. Keep the choke line displaced to kill mud between circulations, or take returns up the kill line, and slow the pump if the choke cannot keep up.
A58: Riser Margin
A60: Riser Margin Mud Weight | F60: MW_rm = (0.052 x MW x TVD - SW x WD) / (0.052 x (TVD - WD - AG))
F61: Mud weight that keeps BHP unchanged if the riser is disconnected and seawater stands above the mudline. In deep water the required increase often exceeds the fracture gradient - full riser margin is frequently impractical.
A62: Seawater gradient (SW) | B62: =WD_SWGrad | C62: psi/ft | D62: =IFERROR($B$62*22.62059,NA()) | E62: kPa/m | F62: Linked to Well Data sheet - overwrite locally if this well differs.
A63: Riser margin mud weight (MW_rm) | B63: =(0.052*$B$18*$B$19-$B$62*$B$10)/(0.052*($B$19-$B$10-$B$11)) | C63: ppg | D63: =IFERROR($B$63*119.8264,NA()) | E63: kg/m3
A64: Margin over current MW | B64: =$B$63-$B$18 | C64: ppg | D64: =IFERROR($B$64*119.8264,NA()) | E64: kg/m3 | F64: Extra density needed for full riser margin.
A66: Shut-In With Riser Disconnected
A68: BHP After Disconnect | F68: BHP = SW x WD + 0.052 x MW x (TVD - WD - AG)
F69: Seawater column to the mudline, current mud below the BOP. Compares against formation pressure to show whether the well stays overbalanced on the mud alone.
A70: Reservoir / formation pressure | B70: =WD_ResP | C70: psi | D70: =IFERROR($B$70*6.894757,NA()) | E70: kPa | F70: Linked to Well Data sheet - overwrite locally if this well differs.
A71: BHP with seawater to mudline | B71: =$B$62*$B$10+0.052*$B$18*($B$19-$B$10-$B$11) | C71: psi | D71: =IFERROR($B$71*6.894757,NA()) | E71: kPa
A72: Status vs formation pressure | B72: =IF($B$71>=$B$70,"OK - overbalanced after disconnect","CHECK: underbalanced after disconnect - well can flow at the mudline")

Sheet Well Control
A1: Well Control
A2: Kick tolerance, MAASP, trip/swab/riser margins, gas behavior, kill weight and volumetric method
A4: Parameter | B4: Value | C4: Unit | D4: SI Value | E4: SI Unit | F4: Notes / Equation
A6: Kick Tolerance & MAASP
A8: MAASP (Maximum Allowable Annular Surface Pressure) | F8: MAASP [psi] = 0.052 x (FG - MW) x TVD_shoe
F9: FG = fracture gradient at shoe from leak-off test, expressed as EMW. Recalculate whenever mud weight changes.
A10: Fracture gradient at shoe (FG) | B10: 14.5 | C10: ppg | D10: =IFERROR($B$10*119.8264,NA()) | E10: kg/m3 | F10: From LOT/FIT, as equivalent mud weight.
A11: Current mud weight (MW) | B11: 12.5 | C11: ppg | D11: =IFERROR($B$11*119.8264,NA()) | E11: kg/m3
A12: Shoe TVD | B12: 5000 | C12: ft | D12: =IFERROR($B$12*0.3048,NA()) | E12: m
A13: MAASP | B13: =ROUNDUP(ROUND(0.052*($B$10-$B$11)*$B$12,6),0) | C13: psi | D13: =IFERROR($B$13*6.894757,NA()) | E13: kPa | F13: Rounding rule: maximized values round UP to whole psi (1000.1 -> 1001).
A15: Kick Tolerance (Volume Basis, Gas at Shoe) | F15: H_max = [P_frac - P_form + 0.052 x MW x (TVD - TVD_shoe)] / (0.052 x MW - G_gas); V_shoe = H_max x C_ann; KT [bbl] = V_shoe x P_frac / P_form
F16: Single gas bubble, no gas cut above it, Boyle expansion from bottom to shoe (isothermal, Z ignored). KT is the largest influx at bottomhole conditions that can be circulated out without breaking down the shoe.
A17: Fracture gradient at shoe (FG) | B17: 14.5 | C17: ppg | D17: =IFERROR($B$17*119.8264,NA()) | E17: kg/m3
A18: Mud weight (MW) | B18: 12.5 | C18: ppg | D18: =IFERROR($B$18*119.8264,NA()) | E18: kg/m3
A19: Shoe TVD | B19: 5000 | C19: ft | D19: =IFERROR($B$19*0.3048,NA()) | E19: m
A20: Well TVD | B20: 10000 | C20: ft | D20: =IFERROR($B$20*0.3048,NA()) | E20: m
A21: Design SIDPP (kick overpressure) | B21: 350 | C21: psi | D21: =IFERROR($B$21*6.894757,NA()) | E21: kPa | F21: Anticipated shut-in drill pipe pressure for the design kick.
A22: Gas gradient | B22: 0.1 | C22: psi/ft | D22: =IFERROR($B$22*22.62059,NA()) | E22: kPa/m | F22: 0.10-0.15 psi/ft typical for gas.
A23: Annular capacity at shoe/BHA | B23: 0.0459 | C23: bbl/ft | D23: =IFERROR($B$23*0.5216119,NA()) | E23: m3/m
A24: Fracture pressure at shoe | B24: =0.052*$B$17*$B$19 | C24: psi | D24: =IFERROR($B$24*6.894757,NA()) | E24: kPa
A25: Formation (kick) pressure | B25: =0.052*$B$18*$B$20+$B$21 | C25: psi | D25: =IFERROR($B$25*6.894757,NA()) | E25: kPa
A26: Max influx height at shoe | B26: =MAX(0,($B$24-$B$25+0.052*$B$18*($B$20-$B$19))/(0.052*$B$18-$B$22)) | C26: ft | D26: =IFERROR($B$26*0.3048,NA()) | E26: m
A27: Max influx volume at shoe | B27: =$B$26*$B$23 | C27: bbl | D27: =IFERROR($B$27*0.1589873,NA()) | E27: m3
A28: Kick tolerance (at bottomhole) | B28: =$B$27*$B$24/$B$25 | C28: bbl | D28: =IFERROR($B$28*0.1589873,NA()) | E28: m3 | F28: Compare with realistic kick detection volume; if smaller, set casing or raise MW policy.
A30: Margins
A32: Trip Margin / Swab Margin | F32: TM [ppg] = YP / (11.7 x (Dh - Dp))
F33: Overbalance added to cover swab pressures when pulling out (trip margin) or, equally, the swab reduction expected running in. Field approximation from yield point.
A34: Mud yield point (YP) | B34: 12 | F34: lb/100 ft2 from viscometer.
A35: Hole diameter (Dh) | B35: 8.5 | C35: in | D35: =IFERROR($B$35*25.4,NA()) | E35: mm
A36: Pipe outside diameter (Dp) | B36: 5 | C36: in | D36: =IFERROR($B$36*25.4,NA()) | E36: mm
A37: Well TVD | B37: 10000 | C37: ft | D37: =IFERROR($B$37*0.3048,NA()) | E37: m
A38: Trip / swab margin | B38: =$B$34/(11.7*($B$35-$B$36)) | C38: ppg | D38: =IFERROR($B$38*119.8264,NA()) | E38: kg/m3
A39: Equivalent overbalance | B39: =0.052*$B$38*$B$37 | C39: psi | D39: =IFERROR($B$39*6.894757,NA()) | E39: kPa
A41: Riser Margin (Floating Rigs) | F41: MW_req = (MW x TVD - MW_sw x WD) / (TVD - WD - AG); RM = MW_req - MW
F42: Mud weight increment so that, after riser disconnect, seawater above the mudline still balances bottomhole pressure. AG = air gap (RKB to sea level). Often impractical in deep water.
A43: Current mud weight (MW) | B43: 12.5 | C43: ppg | D43: =IFERROR($B$43*119.8264,NA()) | E43: kg/m3
A44: Well TVD (from RKB) | B44: 10000 | C44: ft | D44: =IFERROR($B$44*0.3048,NA()) | E44: m
A45: Water depth (WD) | B45: 3000 | C45: ft | D45: =IFERROR($B$45*0.3048,NA()) | E45: m
A46: Air gap (AG) | B46: 75 | C46: ft | D46: =IFERROR($B$46*0.3048,NA()) | E46: m
A47: Seawater density | B47: 8.55 | C47: ppg | D47: =IFERROR($B$47*119.8264,NA()) | E47: kg/m3
A48: Required mud weight after disconnect | B48: =($B$43*$B$44-$B$47*$B$45)/($B$44-$B$45-$B$46) | C48: ppg | D48: =IFERROR($B$48*119.8264,NA()) | E48: kg/m3
A49: Riser margin | B49: =$B$48-$B$43 | C49: ppg | D49: =IFERROR($B$49*119.8264,NA()) | E49: kg/m3
A51: Gas Behavior
A53: Gas Migration Rate from Casing Pressure Rise | F53: V_mig [ft/hr] = (dP/dt) / (0.052 x MW)
F54: Shut-in well: migrating gas carries its pressure up; casing pressure rise rate converts to migration speed through the mud gradient.
A55: Casing pressure rise rate | B55: 150 | C55: psi/hr | D55: =IFERROR($B$55*6.894757,NA()) | E55: kPa/hr
A56: Mud weight (MW) | B56: 12.5 | C56: ppg | D56: =IFERROR($B$56*119.8264,NA()) | E56: kg/m3
A57: Gas migration rate | B57: =$B$55/(0.052*$B$56) | C57: ft/hr | D57: =IFERROR($B$57*0.3048,NA()) | E57: m/hr
A59: Gas Expansion (Boyle's Law) | F59: P1 x V1 = P2 x V2 -> V2 = P1 x V1 / P2
F60: Isothermal ideal gas (Z and temperature ignored). Use absolute pressures for accuracy; at wellbore pressures the gauge/absolute difference is usually negligible.
A61: Initial pressure (P1) | B61: 5200 | C61: psi | D61: =IFERROR($B$61*6.894757,NA()) | E61: kPa
A62: Initial gas volume (V1) | B62: 10 | C62: bbl | D62: =IFERROR($B$62*0.1589873,NA()) | E62: m3
A63: Final pressure (P2) | B63: 500 | C63: psi | D63: =IFERROR($B$63*6.894757,NA()) | E63: kPa
A64: Expanded gas volume (V2) | B64: =$B$61*$B$62/$B$63 | C64: bbl | D64: =IFERROR($B$64*0.1589873,NA()) | E64: m3
A66: Gas-Cut Mud: Bottomhole Pressure Reduction | F66: dBHP [psi] ~ 0.052 x TVD x (MW - MW_cut) / 2
F67: Annular-average approximation: gas expands mostly near surface, so the density cut measured at the flowline acts over roughly half the column on average. Actual reduction is usually even smaller - treat as an upper-bound screening number, not a reason to raise mud weight by itself.
A68: Uncut mud weight (MW) | B68: 12.5 | C68: ppg | D68: =IFERROR($B$68*119.8264,NA()) | E68: kg/m3
A69: Gas-cut mud weight at flowline | B69: 10 | C69: ppg | D69: =IFERROR($B$69*119.8264,NA()) | E69: kg/m3
A70: Well TVD | B70: 10000 | C70: ft | D70: =IFERROR($B$70*0.3048,NA()) | E70: m
A71: Reduction if cut acted over full column | B71: =0.052*$B$70*($B$68-$B$69) | C71: psi | D71: =IFERROR($B$71*6.894757,NA()) | E71: kPa | F71: Unrealistic worst case shown for comparison.
A72: Approx. BHP reduction (annular average) | B72: =$B$71/2 | C72: psi | D72: =IFERROR($B$72*6.894757,NA()) | E72: kPa
A74: Kill Calculations
A76: Kill Mud Weight, ICP, FCP & Barite | F76: KMW = MW + SIDPP/(0.052 x TVD); ICP = SCRP + SIDPP; FCP = SCRP x KMW/MW; Sacks = 1470 x (KMW - MW)/(35 - KMW) x V/100
F77: Driller's/Wait-and-Weight standard kill-sheet values. Barite: SG 4.20 (35 ppg), 100-lb sacks.
A78: Current mud weight (MW) | B78: 12.5 | C78: ppg | D78: =IFERROR($B$78*119.8264,NA()) | E78: kg/m3
A79: Shut-in drill pipe pressure (SIDPP) | B79: 350 | C79: psi | D79: =IFERROR($B$79*6.894757,NA()) | E79: kPa
A80: Well TVD | B80: 10000 | C80: ft | D80: =IFERROR($B$80*0.3048,NA()) | E80: m
A81: Slow circulating rate pressure (SCRP) | B81: 800 | C81: psi | D81: =IFERROR($B$81*6.894757,NA()) | E81: kPa
A82: Active mud system volume | B82: 1000 | C82: bbl | D82: =IFERROR($B$82*0.1589873,NA()) | E82: m3
A83: Kill mud weight (exact) | B83: =$B$78+$B$79/(0.052*$B$80) | C83: ppg | D83: =IFERROR($B$83*119.8264,NA()) | E83: kg/m3
A84: Kill mud weight (KMW, rounded up) | B84: =ROUNDUP(ROUND($B$83*10,6),0)/10 | C84: ppg | D84: =IFERROR($B$84*119.8264,NA()) | E84: kg/m3 | F84: Rounding rule: kill weight fluid density rounds UP to the nearest 0.1 ppg.
A85: Initial circulating pressure (ICP) | B85: =$B$81+$B$79 | C85: psi | D85: =IFERROR($B$85*6.894757,NA()) | E85: kPa
A86: Final circulating pressure (FCP) | B86: =$B$81*$B$84/$B$78 | C86: psi | D86: =IFERROR($B$86*6.894757,NA()) | E86: kPa
A87: Barite required | B87: =1470*($B$84-$B$78)/(35-$B$84)*$B$82/100 | F87: 100-lb sacks to weight the whole active system to KMW.
A89: Volumetric Method
A91: Volumetric Method: Bleed Increments | F91: P per bbl [psi/bbl] = 0.052 x MW / C_ann; bbl per step = P_working / (psi/bbl)
F92: Gas migrating with pipe off bottom or no circulation possible: hold BHP constant by bleeding mud in measured steps as casing pressure rises by the chosen working pressure.
A93: Mud weight (MW) | B93: 12.5 | C93: ppg | D93: =IFERROR($B$93*119.8264,NA()) | E93: kg/m3
A94: Annular capacity at gas | B94: 0.0459 | C94: bbl/ft | D94: =IFERROR($B$94*0.5216119,NA()) | E94: m3/m
A95: Working pressure per step | B95: 100 | C95: psi | D95: =IFERROR($B$95*6.894757,NA()) | E95: kPa | F95: Also allow a safety margin (typically 50-100 psi) before the first bleed.
A96: Hydrostatic pressure per barrel | B96: =0.052*$B$93/$B$94 | C96: psi/bbl | D96: =IFERROR($B$96*43.36638,NA()) | E96: kPa/m3
A97: Mud to bleed per step | B97: =$B$95/$B$96 | C97: bbl | D97: =IFERROR($B$97*0.1589873,NA()) | E97: m3 | F97: Bleed mud only (never gas) at constant casing pressure, then wait; repeat as gas migrates.
A99: Lubricate & Bleed | F99: P gained per bbl lubricated = 0.052 x MW_lube / C_csg; P to bleed per cycle = bbl x psi/bbl
F100: Gas at surface under the BOP: pump (lubricate) mud in, allow it to fall through the gas, then bleed gas pressure equal to the hydrostatic added. Capacity here is usually casing (no pipe) below the BOP.
A101: Lubricating mud weight | B101: 13.2 | C101: ppg | D101: =IFERROR($B$101*119.8264,NA()) | E101: kg/m3
A102: Casing capacity at gas | B102: 0.0732 | C102: bbl/ft | D102: =IFERROR($B$102*0.5216119,NA()) | E102: m3/m
A103: Mud lubricated per cycle | B103: 5 | C103: bbl | D103: =IFERROR($B$103*0.1589873,NA()) | E103: m3
A104: Hydrostatic gained per barrel | B104: =0.052*$B$101/$B$102 | C104: psi/bbl | D104: =IFERROR($B$104*43.36638,NA()) | E104: kPa/m3
A105: Pressure to bleed per cycle | B105: =$B$103*$B$104 | C105: psi | D105: =IFERROR($B$105*6.894757,NA()) | E105: kPa | F105: Bleed dry gas only; stop if mud reaches the choke.

Sheet Hydraulics
A1: Drilling Hydraulics
A2: Annular velocity, cuttings transport, Bingham and power-law rheology, annular losses, ECD, surge and swab
A4: Parameter | B4: Value | C4: Unit | D4: SI Value | E4: SI Unit | F4: Notes / Equation
A6: Velocities & Cuttings Transport
A8: Annular Velocity | F8: AV [ft/min] = 24.5 x Q / (Dh^2 - Dp^2)
F9: Q in gpm, diameters in inches. Rule of thumb: keep AV above ~100-120 ft/min in vertical wells.
A10: Flow rate (Q) | B10: 600 | C10: gpm | D10: =IFERROR($B$10*3.785412,NA()) | E10: L/min
A11: Hole diameter (Dh) | B11: 8.5 | C11: in | D11: =IFERROR($B$11*25.4,NA()) | E11: mm
A12: Pipe outside diameter (Dp) | B12: 5 | C12: in | D12: =IFERROR($B$12*25.4,NA()) | E12: mm
A13: Annular velocity | B13: =24.5*$B$10/($B$11^2-$B$12^2) | C13: ft/min | D13: =IFERROR($B$13*0.3048,NA()) | E13: m/min
A15: Pipe (Internal) Velocity | F15: V_pipe [ft/min] = 24.5 x Q / ID^2
A16: Flow rate (Q) | B16: 600 | C16: gpm | D16: =IFERROR($B$16*3.785412,NA()) | E16: L/min
A17: Pipe inside diameter (ID) | B17: 4.276 | C17: in | D17: =IFERROR($B$17*25.4,NA()) | E17: mm
A18: Pipe velocity | B18: =24.5*$B$16/$B$17^2 | C18: ft/min | D18: =IFERROR($B$18*0.3048,NA()) | E18: m/min
A20: Cuttings Slip Velocity & Transport Ratio | F20: V_slip [ft/min] = 92.6 x SQRT( Dc x (MW_c - MW) / MW ); TR = (AV - V_slip) / AV x 100
F21: Turbulent (Newtonian) slip form, drag coefficient ~1.5; cuttings SG 2.6 = 21.7 ppg. Ignores mud rheology support, so it is conservative in viscous muds. TR > 50% is generally adequate hole cleaning in near-vertical hole.
A22: Cutting diameter (Dc) | B22: 0.25 | C22: in | D22: =IFERROR($B$22*25.4,NA()) | E22: mm
A23: Cuttings density | B23: 21.7 | C23: ppg | D23: =IFERROR($B$23*119.8264,NA()) | E23: kg/m3 | F23: SG 2.6 shale/sand.
A24: Mud weight (MW) | B24: 12.5 | C24: ppg | D24: =IFERROR($B$24*119.8264,NA()) | E24: kg/m3
A25: Flow rate (Q) | B25: 600 | C25: gpm | D25: =IFERROR($B$25*3.785412,NA()) | E25: L/min
A26: Hole diameter (Dh) | B26: 8.5 | C26: in | D26: =IFERROR($B$26*25.4,NA()) | E26: mm
A27: Pipe outside diameter (Dp) | B27: 5 | C27: in | D27: =IFERROR($B$27*25.4,NA()) | E27: mm
A28: Annular velocity | B28: =24.5*$B$25/($B$26^2-$B$27^2) | C28: ft/min | D28: =IFERROR($B$28*0.3048,NA()) | E28: m/min
A29: Cuttings slip velocity | B29: =92.6*SQRT($B$22*($B$23-$B$24)/$B$24) | C29: ft/min | D29: =IFERROR($B$29*0.3048,NA()) | E29: m/min
A30: Net cuttings rise velocity | B30: =$B$28-$B$29 | C30: ft/min | D30: =IFERROR($B$30*0.3048,NA()) | E30: m/min
A31: Transport ratio | B31: =($B$28-$B$29)/$B$28*100 | C31: %
A33: Rheology from Viscometer Readings
A35: Bingham Plastic: PV & YP | F35: PV [cP] = theta600 - theta300; YP [lb/100ft2] = theta300 - PV
F36: Standard 600/300 rpm Fann dial readings.
A37: Dial reading at 600 rpm (theta600) | B37: 65 | F37: Fann dial degrees.
A38: Dial reading at 300 rpm (theta300) | B38: 40 | F38: Fann dial degrees.
A39: Plastic viscosity (PV) | B39: =$B$37-$B$38 | F39: cP.
A40: Yield point (YP) | B40: =$B$38-$B$39 | F40: lb/100 ft2.
A42: Power Law: n & K | F42: n = 3.32 x LOG(theta600 / theta300); K = 510 x theta300 / 511^n
F43: K in eq. centipoise (dyne-s^n/100 cm2). LOG is base 10.
A44: Dial reading at 600 rpm (theta600) | B44: 65
A45: Dial reading at 300 rpm (theta300) | B45: 40
A46: Flow behavior index (n) | B46: =3.32*LOG($B$44/$B$45)
A47: Consistency index (K) | B47: =510*$B$45/511^$B$46 | F47: eq. cP.
A49: Annular Pressure Loss & ECD
A51: Annular Pressure Loss & ECD (Bingham, Laminar) | F51: APL [psi] = L x PV x AV / (60000 x (Dh - Dp)^2) + L x YP / (200 x (Dh - Dp)); ECD = MW + APL / (0.052 x TVD)
F52: Simple field form, laminar annular flow, uniform geometry. Sum section by section for tapered strings; underestimates in turbulent flow.
A53: Annulus length (L) | B53: 10000 | C53: ft | D53: =IFERROR($B$53*0.3048,NA()) | E53: m
A54: Plastic viscosity (PV) | B54: 25 | F54: cP.
A55: Yield point (YP) | B55: 15 | F55: lb/100 ft2.
A56: Flow rate (Q) | B56: 600 | C56: gpm | D56: =IFERROR($B$56*3.785412,NA()) | E56: L/min
A57: Hole diameter (Dh) | B57: 8.5 | C57: in | D57: =IFERROR($B$57*25.4,NA()) | E57: mm
A58: Pipe outside diameter (Dp) | B58: 5 | C58: in | D58: =IFERROR($B$58*25.4,NA()) | E58: mm
A59: Mud weight (MW) | B59: 12.5 | C59: ppg | D59: =IFERROR($B$59*119.8264,NA()) | E59: kg/m3
A60: True vertical depth (TVD) | B60: 10000 | C60: ft | D60: =IFERROR($B$60*0.3048,NA()) | E60: m
A61: Annular velocity | B61: =24.5*$B$56/($B$57^2-$B$58^2) | C61: ft/min | D61: =IFERROR($B$61*0.3048,NA()) | E61: m/min
A62: Annular pressure loss (APL) | B62: =$B$53*$B$54*$B$61/(60000*($B$57-$B$58)^2)+$B$53*$B$55/(200*($B$57-$B$58)) | C62: psi | D62: =IFERROR($B$62*6.894757,NA()) | E62: kPa
A63: Equivalent circulating density (ECD) | B63: =$B$59+$B$62/(0.052*$B$60) | C63: ppg | D63: =IFERROR($B$63*119.8264,NA()) | E63: kg/m3
A65: Surge & Swab
A67: Surge & Swab Pressure (Burkhardt-Style, Simplified) | F67: Ve = Vp x (0.45 + Dp^2/(Dh^2 - Dp^2)); Ps [psi] = L x PV x Ve / (60000 x (Dh - Dp)^2) + L x YP / (200 x (Dh - Dp)); EMW = MW +/- Ps / (0.052 x TVD)
F68: Clinging constant 0.45; closed-end (or float-equipped) pipe, laminar flow. Vp is the average pipe running speed - peak speed can be 1.5-2x average, so apply to the fastest stand. Surge adds to BHP (running in), swab subtracts (pulling out).
A69: Pipe running speed (Vp) | B69: 90 | C69: ft/min | D69: =IFERROR($B$69*0.3048,NA()) | E69: m/min | F69: Stand length / seconds per stand x 60.
A70: Hole diameter (Dh) | B70: 8.5 | C70: in | D70: =IFERROR($B$70*25.4,NA()) | E70: mm
A71: Pipe outside diameter (Dp) | B71: 5 | C71: in | D71: =IFERROR($B$71*25.4,NA()) | E71: mm
A72: String length in hole (L) | B72: 10000 | C72: ft | D72: =IFERROR($B$72*0.3048,NA()) | E72: m
A73: Plastic viscosity (PV) | B73: 25 | F73: cP.
A74: Yield point (YP) | B74: 15 | F74: lb/100 ft2.
A75: Mud weight (MW) | B75: 12.5 | C75: ppg | D75: =IFERROR($B$75*119.8264,NA()) | E75: kg/m3
A76: True vertical depth (TVD) | B76: 10000 | C76: ft | D76: =IFERROR($B$76*0.3048,NA()) | E76: m
A77: Effective annular velocity (Ve) | B77: =$B$69*(0.45+$B$71^2/($B$70^2-$B$71^2)) | C77: ft/min | D77: =IFERROR($B$77*0.3048,NA()) | E77: m/min
A78: Surge / swab pressure (Ps) | B78: =$B$72*$B$73*$B$77/(60000*($B$70-$B$71)^2)+$B$72*$B$74/(200*($B$70-$B$71)) | C78: psi | D78: =IFERROR($B$78*6.894757,NA()) | E78: kPa
A79: Equivalent MW while surging | B79: =$B$75+$B$78/(0.052*$B$76) | C79: ppg | D79: =IFERROR($B$79*119.8264,NA()) | E79: kg/m3 | F79: Keep below fracture gradient EMW at the shoe.
A80: Equivalent MW while swabbing | B80: =$B$75-$B$78/(0.052*$B$76) | C80: ppg | D80: =IFERROR($B$80*119.8264,NA()) | E80: kg/m3 | F80: Keep above pore pressure EMW - otherwise slow the trip.

Sheet Bit Hydraulics
A1: Bit Hydraulics
A2: Total flow area, nozzle velocity, bit pressure drop, hydraulic horsepower, HSI and jet impact force
A4: Parameter | B4: Value | C4: Unit | D4: SI Value | E4: SI Unit | F4: Notes / Equation
A6: Nozzles & Flow Area
A8: Total Flow Area (TFA) | F8: TFA [in2] = PI()/4 x sum( (d/32)^2 ) for each nozzle, d in 1/32 in
F9: Three-nozzle bit shown; enter 0 for blanked nozzles and extend the sum for more nozzles.
A10: Nozzle 1 size | B10: 13 | F10: 1/32 in.
A11: Nozzle 2 size | B11: 13 | F11: 1/32 in.
A12: Nozzle 3 size | B12: 14 | F12: 1/32 in.
A13: Total flow area (TFA) | B13: =PI()/4*(($B$10/32)^2+($B$11/32)^2+($B$12/32)^2) | C13: in2 | D13: =IFERROR($B$13*6.4516,NA()) | E13: cm2
A15: Nozzle (Jet) Velocity | F15: Vn [ft/s] = 0.32086 x Q / TFA
F16: Uses TFA computed above. Typical target 350-450 ft/s for adequate bottomhole cleaning.
A17: Flow rate (Q) | B17: 450 | C17: gpm | D17: =IFERROR($B$17*3.785412,NA()) | E17: L/min
A18: Nozzle velocity (Vn) | B18: =0.32086*$B$17/$B$13 | C18: ft/s | D18: =IFERROR($B$18*0.3048,NA()) | E18: m/s
A20: Bit Pressure Drop & Horsepower
A22: Pressure Drop Across Bit | F22: dPb [psi] = Q^2 x MW / (12042 x TFA^2)
F23: Nozzle discharge coefficient 0.95 built into the constant. Uses Q and TFA from above.
A24: Mud weight (MW) | B24: 12.5 | C24: ppg | D24: =IFERROR($B$24*119.8264,NA()) | E24: kg/m3
A25: Surface (standpipe) pressure | B25: 3200 | C25: psi | D25: =IFERROR($B$25*6.894757,NA()) | E25: kPa
A26: Bit pressure drop (dPb) | B26: =$B$17^2*$B$24/(12042*$B$13^2) | C26: psi | D26: =IFERROR($B$26*6.894757,NA()) | E26: kPa
A27: Percent of surface pressure at bit | B27: =$B$26/$B$25*100 | C27: %
A29: Hydraulic Horsepower & HSI | F29: HHP = P x Q / 1714; HSI = HHP_bit / (PI()/4 x D_bit^2)
F30: HSI 2.5-5+ hp/in2 is a common target for effective PDC/roller-cone cleaning.
A31: Bit diameter | B31: 8.5 | C31: in | D31: =IFERROR($B$31*25.4,NA()) | E31: mm
A32: System hydraulic horsepower | B32: =$B$25*$B$17/1714 | C32: hp | D32: =IFERROR($B$32*0.7456999,NA()) | E32: kW
A33: Bit hydraulic horsepower | B33: =$B$26*$B$17/1714 | C33: hp | D33: =IFERROR($B$33*0.7456999,NA()) | E33: kW
A34: Hydraulic horsepower per in2 (HSI) | B34: =$B$33/(PI()/4*$B$31^2) | C34: hp/in2 | D34: =IFERROR($B$34*0.1155886,NA()) | E34: kW/cm2
A36: Jet Impact Force
A38: Hydraulic Impact Force | F38: IF [lbf] = 0.01823 x Cd x Q x SQRT( MW x dPb )
F39: Uses Q, MW and dPb from above. Impact per unit bit area is a useful comparison between bit runs.
A40: Nozzle discharge coefficient (Cd) | B40: 0.95
A41: Jet impact force (IF) | B41: =0.01823*$B$40*$B$17*SQRT($B$24*$B$26) | C41: lbf | D41: =IFERROR($B$41*0.004448222,NA()) | E41: kN
A42: Impact force per in2 of bit area | B42: =$B$41/(PI()/4*$B$31^2) | F42: lbf/in2 of bit face.
A44: Optimization Guidance
A46: Rules of Thumb for Bit Hydraulics Optimization
F47: Compare the 'percent of surface pressure at bit' output above against these targets.
A48: Maximum bit hydraulic horsepower: | F48: achieved when dPb is about 65% of surface pressure (friction exponent u ~ 1.86).
A49: Maximum jet impact force: | F49: achieved when dPb is about 48% of surface pressure.
A50: Practical window: | F50: most operators size nozzles for 50-65% of surface pressure at the bit, subject to minimum annular velocity for hole cleaning and maximum pump pressure/liner rating.
A51: Nozzle selection: | F51: adjust nozzle sizes (TFA) rather than flow rate first; flow rate is usually set by hole cleaning and motor/MWD requirements.

Sheet Drill String & Tension
A1: Drill String Weight, Tension & Vibration
A2: Buoyancy, hook load, margin of overpull, collar length for WOB, stretch, slip crush, critical RPM, ton-miles
A4: Parameter | B4: Value | C4: Unit | D4: SI Value | E4: SI Unit | F4: Notes / Equation
A6: Buoyancy & String Weight
A8: Buoyancy Factor | F8: BF = (65.5 - MW) / 65.5
F9: 65.5 ppg = density of steel. Multiply air weights by BF to get buoyed weight in mud.
A10: Mud weight (MW) | B10: 12.5 | C10: ppg | D10: =IFERROR($B$10*119.8264,NA()) | E10: kg/m3
A11: Buoyancy factor (BF) | B11: =(65.5-$B$10)/65.5
A13: Buoyed String Weight (Hook Load) | F13: W_buoyed = (L_dp x W_dp + L_dc x W_dc) x BF
F14: Air weights per foot include tool joints (use 'approximate weight' from pipe tables). Add HWDP as a third term if run.
A15: Drill pipe length | B15: 9400 | C15: ft | D15: =IFERROR($B$15*0.3048,NA()) | E15: m
A16: Drill pipe weight (incl. tool joints) | B16: 20.89 | C16: lb/ft | D16: =IFERROR($B$16*1.488164,NA()) | E16: kg/m
A17: Drill collar length | B17: 600 | C17: ft | D17: =IFERROR($B$17*0.3048,NA()) | E17: m
A18: Drill collar weight | B18: 92 | C18: lb/ft | D18: =IFERROR($B$18*1.488164,NA()) | E18: kg/m | F18: 6-1/2 in x 2-13/16 in collars.
A19: Mud weight (MW) | B19: 12.5 | C19: ppg | D19: =IFERROR($B$19*119.8264,NA()) | E19: kg/m3
A20: Buoyancy factor (BF) | B20: =(65.5-$B$19)/65.5
A21: Buoyed string weight | B21: =($B$15*$B$16+$B$17*$B$18)*$B$20 | C21: lbf | D21: =IFERROR($B$21*0.004448222,NA()) | E21: kN
A23: Tension, Overpull & Slips
A25: Maximum Allowable Pull & Margin of Overpull | F25: Max pull = T_yield x DF; MOP = Max pull - buoyed hook load; SF = T_yield / hook load
F26: T_yield = pipe body tensile yield for the weakest (usually top) joint and wear class. DF of 0.90 on new pipe is common; use premium-class ratings for worn pipe. Hook load defaults to the buoyed string weight computed above.
A27: Pipe body tensile yield | B27: 553830 | C27: lbf | D27: =IFERROR($B$27*0.004448222,NA()) | E27: kN | F27: 5 in 19.5 lb/ft G-105, new.
A28: Tension design factor (DF) | B28: 0.9
A29: Hook load (buoyed) | B29: 203400 | C29: lbf | D29: =IFERROR($B$29*0.004448222,NA()) | E29: kN
A30: Maximum allowable pull | B30: =$B$27*$B$28 | C30: lbf | D30: =IFERROR($B$30*0.004448222,NA()) | E30: kN
A31: Margin of overpull (MOP) | B31: =$B$30-$B$29 | C31: lbf | D31: =IFERROR($B$31*0.004448222,NA()) | E31: kN | F31: Keep at least 50,000-100,000 lbf for stuck-pipe contingency.
A32: Safety factor in tension | B32: =$B$27/$B$29
A34: Drill Collar Length for Desired WOB | F34: L_dc [ft] = WOB x SF / (W_dc x BF x COS(angle))
F35: Keeps the neutral point inside the collars (drill pipe never in compression). SF 1.10-1.20 places the neutral point 10-20% below the top of the collars.
A36: Desired weight on bit (WOB) | B36: 45000 | C36: lbf | D36: =IFERROR($B$36*0.004448222,NA()) | E36: kN
A37: Safety factor (SF) | B37: 1.15
A38: Drill collar weight | B38: 92 | C38: lb/ft | D38: =IFERROR($B$38*1.488164,NA()) | E38: kg/m
A39: Mud weight (MW) | B39: 12.5 | C39: ppg | D39: =IFERROR($B$39*119.8264,NA()) | E39: kg/m3
A40: Hole inclination | B40: 10 | C40: deg
A41: Drill collar length required | B41: =$B$36*$B$37/($B$38*(65.5-$B$39)/65.5*COS(RADIANS($B$40))) | C41: ft | D41: =IFERROR($B$41*0.3048,NA()) | E41: m
A43: Slip Crush Ratio | F43: SH/SA = SQRT( 1 + D x K/(2 x Ls) + (D x K/(2 x Ls))^2 ); Max static load = T_yield / (SH/SA)
F44: Reinhold-Spiri (API RP 7G) hoop-to-axial stress ratio. K = lateral load factor (~4.0 for 9 deg 27.5 min taper, friction 0.08); Ls = slip contact length. Hook loads above the max static load risk crushing the pipe in the slips.
A45: Pipe outside diameter (D) | B45: 5 | C45: in | D45: =IFERROR($B$45*25.4,NA()) | E45: mm
A46: Lateral load factor (K) | B46: 4
A47: Slip contact length (Ls) | B47: 16 | C47: in | D47: =IFERROR($B$47*25.4,NA()) | E47: mm
A48: Pipe body tensile yield | B48: 553830 | C48: lbf | D48: =IFERROR($B$48*0.004448222,NA()) | E48: kN
A49: Slip crush ratio (SH/SA) | B49: =SQRT(1+$B$45*$B$46/(2*$B$47)+($B$45*$B$46/(2*$B$47))^2)
A50: Max static hook load in slips | B50: =$B$48/$B$49 | C50: lbf | D50: =IFERROR($B$50*0.004448222,NA()) | E50: kN
A52: Stretch
A54: Drill Pipe Stretch Under Pull | F54: e [in] = P x L x 12 / (A x E), A = PI()/4 x (OD^2 - ID^2), E = 29.6e6 psi
F55: Elastic stretch of the free (unstuck) length under an applied pull P. Also used inverted to find stuck point: L_free = e x A x E / (12 x P).
A56: Applied pull (P) | B56: 50000 | C56: lbf | D56: =IFERROR($B$56*0.004448222,NA()) | E56: kN | F56: Differential pull above the string's own hanging weight.
A57: Free pipe length (L) | B57: 10000 | C57: ft | D57: =IFERROR($B$57*0.3048,NA()) | E57: m
A58: Pipe outside diameter (OD) | B58: 5 | C58: in | D58: =IFERROR($B$58*25.4,NA()) | E58: mm
A59: Pipe inside diameter (ID) | B59: 4.276 | C59: in | D59: =IFERROR($B$59*25.4,NA()) | E59: mm
A60: Pipe wall cross-section area (A) | B60: =PI()/4*($B$58^2-$B$59^2) | C60: in2 | D60: =IFERROR($B$60*6.4516,NA()) | E60: cm2
A61: Stretch | B61: =$B$56*$B$57*12/($B$60*29600000) | C61: in | D61: =IFERROR($B$61*25.4,NA()) | E61: mm
A63: Stretch Due to Own Weight (Free-Hanging) | F63: e [in] = 12 x w x L^2 x BF / (2 x A x E)
F64: Average tension over the string is half the hanging weight, hence the factor 2. w = air weight per foot; buoyancy applied through BF.
A65: Pipe weight in air | B65: 19.5 | C65: lb/ft | D65: =IFERROR($B$65*1.488164,NA()) | E65: kg/m
A66: String length (L) | B66: 10000 | C66: ft | D66: =IFERROR($B$66*0.3048,NA()) | E66: m
A67: Mud weight (MW) | B67: 12.5 | C67: ppg | D67: =IFERROR($B$67*119.8264,NA()) | E67: kg/m3
A68: Pipe wall cross-section area (A) | B68: 5.275 | C68: in2 | D68: =IFERROR($B$68*6.4516,NA()) | E68: cm2
A69: Stretch due to own weight | B69: =12*$B$65*$B$66^2*(65.5-$B$67)/65.5/(2*$B$68*29600000) | C69: in | D69: =IFERROR($B$69*25.4,NA()) | E69: mm
A71: Vibration & Ton-Miles
A73: Critical Rotary Speed (Transverse, One Joint) | F73: RPM_crit = 33055 x SQRT(OD^2 + ID^2) / L^2 (L = joint length in ft)
F74: Lubinski-style field formula for the first transverse (lateral) mode of one joint between tool joints; equivalent to 4.76e6 x SQRT(OD^2+ID^2)/L^2 with L in inches. Avoid running within about +/-15% of the critical speed; axial and higher modes also exist, so treat as a screening value only.
A75: Pipe outside diameter (OD) | B75: 5 | C75: in | D75: =IFERROR($B$75*25.4,NA()) | E75: mm
A76: Pipe inside diameter (ID) | B76: 4.276 | C76: in | D76: =IFERROR($B$76*25.4,NA()) | E76: mm
A77: Joint length (L) | B77: 31 | C77: ft | D77: =IFERROR($B$77*0.3048,NA()) | E77: m | F77: Range 2 joint ~31 ft.
A78: Critical rotary speed | B78: =33055*SQRT($B$75^2+$B$76^2)/$B$77^2 | C78: RPM
A80: Ton-Miles for a Round Trip | F80: T_rt = W_p x D x (L_s + D) / 10560000 + D x (M + C/2) / 2640000
F81: Standard drilling-line service formula. W_p = buoyed drill pipe weight per foot, D = depth, L_s = stand length, M = traveling block+hook weight, C = buoyed excess collar (and HWDP) weight over the same length of drill pipe. Drilling/coring/short trips are counted as multiples of round-trip ton-miles per the standard schedule.
A82: Drill pipe weight (incl. tool joints) | B82: 20.89 | C82: lb/ft | D82: =IFERROR($B$82*1.488164,NA()) | E82: kg/m
A83: Mud weight (MW) | B83: 12.5 | C83: ppg | D83: =IFERROR($B$83*119.8264,NA()) | E83: kg/m3
A84: Trip depth (D) | B84: 10000 | C84: ft | D84: =IFERROR($B$84*0.3048,NA()) | E84: m
A85: Stand length (Ls) | B85: 93 | C85: ft | D85: =IFERROR($B$85*0.3048,NA()) | E85: m
A86: Traveling block + hook weight (M) | B86: 100000 | C86: lbf | D86: =IFERROR($B$86*0.004448222,NA()) | E86: kN
A87: Drill collar length | B87: 600 | C87: ft | D87: =IFERROR($B$87*0.3048,NA()) | E87: m
A88: Drill collar weight | B88: 92 | C88: lb/ft | D88: =IFERROR($B$88*1.488164,NA()) | E88: kg/m
A89: Buoyancy factor (BF) | B89: =(65.5-$B$83)/65.5
A90: Buoyed drill pipe weight | B90: =$B$82*$B$89 | C90: lb/ft | D90: =IFERROR($B$90*1.488164,NA()) | E90: kg/m
A91: Buoyed excess collar weight (C) | B91: =($B$88-$B$82)*$B$87*$B$89 | C91: lbf | D91: =IFERROR($B$91*0.004448222,NA()) | E91: kN
A92: Round-trip ton-miles | B92: =$B$90*$B$84*($B$85+$B$84)/10560000+$B$84*($B$86+$B$91/2)/2640000 | D92: =IFERROR($B$92*1.459972,NA()) | E92: tonne-km | F92: US ton-miles (2000 lb x 5280 ft).

Sheet Directional Drilling
A1: Directional Drilling
A2: Dogleg severity, minimum curvature surveys, closure, radius of curvature, build geometry, slide vs rotate
A4: Parameter | B4: Value | C4: Unit | D4: SI Value | E4: SI Unit | F4: Notes / Equation
A6: Surveys & Dogleg
A8: Dogleg Severity Between Two Surveys | F8: DL [deg] = ACOS( COS(I1) x COS(I2) + SIN(I1) x SIN(I2) x COS(A2 - A1) ); DLS = DL x 100 / CL
F9: I = inclination, A = azimuth, CL = course length (MD between surveys). Typical limits: 3-5 deg/100 ft for drill pipe fatigue, less for casing running.
A10: Inclination at survey 1 (I1) | B10: 20 | C10: deg
A11: Azimuth at survey 1 (A1) | B11: 45 | C11: deg
A12: Inclination at survey 2 (I2) | B12: 22 | C12: deg
A13: Azimuth at survey 2 (A2) | B13: 48 | C13: deg
A14: Course length (CL) | B14: 100 | C14: ft | D14: =IFERROR($B$14*0.3048,NA()) | E14: m
A15: Dogleg angle (DL) | B15: =DEGREES(ACOS(COS(RADIANS($B$10))*COS(RADIANS($B$12))+SIN(RADIANS($B$10))*SIN(RADIANS($B$12))*COS(RADIANS($B$13-$B$11)))) | C15: deg
A16: Dogleg severity (DLS) | B16: =$B$15*100/$B$14 | C16: deg/100ft | D16: =IFERROR($B$16*0.984252,NA()) | E16: deg/30m
A18: Minimum Curvature Between Two Surveys | F18: RF = 2/DL x TAN(DL/2) (DL in radians); dTVD = CL/2 x (COS I1 + COS I2) x RF; dN = CL/2 x (SIN I1 x COS A1 + SIN I2 x COS A2) x RF; dE = CL/2 x (SIN I1 x SIN A1 + SIN I2 x SIN A2) x RF
F19: Industry-standard survey calculation. RF = 1 when the dogleg is zero (straight course).
A20: Inclination at survey 1 (I1) | B20: 20 | C20: deg
A21: Azimuth at survey 1 (A1) | B21: 45 | C21: deg
A22: Inclination at survey 2 (I2) | B22: 22 | C22: deg
A23: Azimuth at survey 2 (A2) | B23: 48 | C23: deg
A24: Course length (CL) | B24: 100 | C24: ft | D24: =IFERROR($B$24*0.3048,NA()) | E24: m
A25: Dogleg angle (DL) | B25: =DEGREES(ACOS(COS(RADIANS($B$20))*COS(RADIANS($B$22))+SIN(RADIANS($B$20))*SIN(RADIANS($B$22))*COS(RADIANS($B$23-$B$21)))) | C25: deg
A26: Ratio factor (RF) | B26: =IF($B$25=0,1,2/RADIANS($B$25)*TAN(RADIANS($B$25)/2))
A27: Delta TVD | B27: =$B$24/2*(COS(RADIANS($B$20))+COS(RADIANS($B$22)))*$B$26 | C27: ft | D27: =IFERROR($B$27*0.3048,NA()) | E27: m
A28: Delta North | B28: =$B$24/2*(SIN(RADIANS($B$20))*COS(RADIANS($B$21))+SIN(RADIANS($B$22))*COS(RADIANS($B$23)))*$B$26 | C28: ft | D28: =IFERROR($B$28*0.3048,NA()) | E28: m
A29: Delta East | B29: =$B$24/2*(SIN(RADIANS($B$20))*SIN(RADIANS($B$21))+SIN(RADIANS($B$22))*SIN(RADIANS($B$23)))*$B$26 | C29: ft | D29: =IFERROR($B$29*0.3048,NA()) | E29: m
A31: Closure & Vertical Section | F31: Closure = SQRT(N^2 + E^2); Closure azimuth = ATAN2(N, E); VS = closure x COS(VS azimuth - closure azimuth)
F32: N and E are cumulative coordinates from the wellhead. Vertical section is the closure projected onto the plan (target) direction.
A33: Cumulative North (+N/-S) | B33: 1450 | C33: ft | D33: =IFERROR($B$33*0.3048,NA()) | E33: m
A34: Cumulative East (+E/-W) | B34: 1620 | C34: ft | D34: =IFERROR($B$34*0.3048,NA()) | E34: m
A35: Vertical section plane azimuth | B35: 45 | C35: deg
A36: Closure distance | B36: =SQRT($B$33^2+$B$34^2) | C36: ft | D36: =IFERROR($B$36*0.3048,NA()) | E36: m
A37: Closure azimuth | B37: =MOD(DEGREES(ATAN2($B$33,$B$34)),360) | C37: deg
A38: Vertical section (VS) | B38: =$B$36*COS(RADIANS($B$35-$B$37)) | C38: ft | D38: =IFERROR($B$38*0.3048,NA()) | E38: m
A40: Build Planning
A42: Radius of Curvature & Build Section Length | F42: R [ft] = 18000 / (PI() x BUR); MD_build = (I_end - I_start) x 100 / BUR
F43: BUR in deg/100 ft. R is the radius of the build arc in the vertical plane.
A44: Build-up rate (BUR) | B44: 3 | C44: deg/100ft | D44: =IFERROR($B$44*0.984252,NA()) | E44: deg/30m
A45: Starting inclination | B45: 0 | C45: deg
A46: Ending inclination | B46: 35 | C46: deg
A47: Radius of curvature (R) | B47: =18000/(PI()*$B$44) | C47: ft | D47: =IFERROR($B$47*0.3048,NA()) | E47: m
A48: Measured depth of build section | B48: =($B$46-$B$45)*100/$B$44 | C48: ft | D48: =IFERROR($B$48*0.3048,NA()) | E48: m
A50: TVD & Displacement Through a Build from KOP | F50: TVD_eob = TVD_kop + R x SIN(I); HD_eob = R x (1 - COS(I))
F51: Vertical hole above the kick-off point, constant build to inclination I.
A52: Kick-off point TVD | B52: 2000 | C52: ft | D52: =IFERROR($B$52*0.3048,NA()) | E52: m
A53: Build-up rate (BUR) | B53: 3 | C53: deg/100ft | D53: =IFERROR($B$53*0.984252,NA()) | E53: deg/30m
A54: End-of-build inclination (I) | B54: 35 | C54: deg
A55: Radius of curvature (R) | B55: =18000/(PI()*$B$53) | C55: ft | D55: =IFERROR($B$55*0.3048,NA()) | E55: m
A56: TVD at end of build | B56: =$B$52+$B$55*SIN(RADIANS($B$54)) | C56: ft | D56: =IFERROR($B$56*0.3048,NA()) | E56: m
A57: Horizontal displacement at end of build | B57: =$B$55*(1-COS(RADIANS($B$54))) | C57: ft | D57: =IFERROR($B$57*0.3048,NA()) | E57: m
A59: Build & Hold: TVD and Displacement at TD | F59: MD_tan = TD_md - KOP_md - MD_build; TVD_td = KOP + R x SIN(I) + MD_tan x COS(I); HD_td = R x (1 - COS(I)) + MD_tan x SIN(I)
F60: Vertical to KOP, constant build to hold angle I, straight tangent to TD.
A61: Kick-off point MD (= TVD, vertical above) | B61: 2000 | C61: ft | D61: =IFERROR($B$61*0.3048,NA()) | E61: m
A62: Build-up rate (BUR) | B62: 3 | C62: deg/100ft | D62: =IFERROR($B$62*0.984252,NA()) | E62: deg/30m
A63: Hold inclination (I) | B63: 35 | C63: deg
A64: Total depth (TD) measured depth | B64: 10000 | C64: ft | D64: =IFERROR($B$64*0.3048,NA()) | E64: m
A65: Radius of curvature (R) | B65: =18000/(PI()*$B$62) | C65: ft | D65: =IFERROR($B$65*0.3048,NA()) | E65: m
A66: Tangent section length | B66: =$B$64-$B$61-$B$63*100/$B$62 | C66: ft | D66: =IFERROR($B$66*0.3048,NA()) | E66: m
A67: TVD at TD | B67: =$B$61+$B$65*SIN(RADIANS($B$63))+$B$66*COS(RADIANS($B$63)) | C67: ft | D67: =IFERROR($B$67*0.3048,NA()) | E67: m
A68: Horizontal displacement at TD | B68: =$B$65*(1-COS(RADIANS($B$63)))+$B$66*SIN(RADIANS($B$63)) | C68: ft | D68: =IFERROR($B$68*0.3048,NA()) | E68: m
A70: Slide vs Rotate Footage for Required Build | F70: Slide fraction = (BUR_req - BUR_rot) / (DLS_motor - BUR_rot); Slide ft per stand = fraction x L_stand
F71: DLS_motor = motor yield while sliding (from bend setting and formation); BUR_rot = build/drop tendency while rotating (negative if dropping). Plan the slide at the start of each stand and confirm with surveys.
A72: Required build rate | B72: 3 | C72: deg/100ft | D72: =IFERROR($B$72*0.984252,NA()) | E72: deg/30m
A73: Rotating build tendency | B73: 0.3 | C73: deg/100ft | D73: =IFERROR($B$73*0.984252,NA()) | E73: deg/30m
A74: Motor yield while sliding | B74: 8 | C74: deg/100ft | D74: =IFERROR($B$74*0.984252,NA()) | E74: deg/30m
A75: Stand length | B75: 93 | C75: ft | D75: =IFERROR($B$75*0.3048,NA()) | E75: m
A76: Slide fraction | B76: =($B$72-$B$73)/($B$74-$B$73)
A77: Slide footage per stand | B77: =$B$76*$B$75 | C77: ft | D77: =IFERROR($B$77*0.3048,NA()) | E77: m
A78: Rotate footage per stand | B78: =$B$75-$B$77 | C78: ft | D78: =IFERROR($B$78*0.3048,NA()) | E78: m

Sheet Directional Survey
A1: Directional Survey - Minimum Curvature
A2: Paste MD / Inc / Azi stations; TVD, N/E, VS and DLS compute per row. Charts and the Kill Sheet schedule update automatically.
A3: Vertical section direction | B3: 90 | C3: deg | D3: TVD at TD | E3: =LOOKUP(9.99E+307,D7:D106) | F3: ft | G3: Max DLS | H3: =MAX(H8:H106) | I3: deg/100ft
A4: Parameter | B4: Value | C4: Unit | D4: SI Value | E4: SI Unit | F4: Notes / Equation
A5: Survey Stations - enter MD / Inc / Azi (yellow). Row 1 is the tie-in (TVD/NS/EW also inputs there). MD must strictly increase; no blank rows between stations; last station must reach bit/TD measured depth.
A6: MD (ft) | B6: Inc (deg) | C6: Azi (deg) | D6: TVD (ft) | E6: VS (ft) | F6: N/S (ft) | G6: E/W (ft) | H6: DLS (deg/100ft) | I6: MDh* | J6: TVDh* | K6: DL* | L6: RF* | M6: VS_c* | N6: TVD_c* | O6: EW_c* | P6: NS_c*
A7: 0 | B7: 0 | C7: 0 | D7: 0 | E7: =F7*COS(RADIANS($B$3))+G7*SIN(RADIANS($B$3)) | F7: 0 | G7: 0 | I7: =IF(A7="",9.9E+99,A7) | J7: =IF(D7="",0,D7) | M7: =IF($A7="",NA(),E7) | N7: =IF($A7="",NA(),D7) | O7: =IF($A7="",NA(),G7) | P7: =IF($A7="",NA(),F7)
A8: 1000 | B8: 0 | C8: 0 | D8: =IF(K8="","",D7+(A8-A7)/2*(COS(RADIANS(B7))+COS(RADIANS(B8)))*L8) | E8: =IF(D8="","",F8*COS(RADIANS($B$3))+G8*SIN(RADIANS($B$3))) | F8: =IF(K8="","",ROUND(F7+(A8-A7)/2*(SIN(RADIANS(B7))*COS(RADIANS(C7))+SIN(RADIANS(B8))*COS(RADIANS(C8)))*L8,4)) | G8: =IF(K8="","",ROUND(G7+(A8-A7)/2*(SIN(RADIANS(B7))*SIN(RADIANS(C7))+SIN(RADIANS(B8))*SIN(RADIANS(C8)))*L8,4)) | H8: =IF(K8="","",IF(A8=A7,0,K8*100/(A8-A7))) | I8: =IF(A8="",9.9E+99,A8) | J8: =IF(D8="",0,D8) | K8: =IF(OR(A8="",A7=""),"",DEGREES(ACOS(MIN(1,MAX(-1,COS(RADIANS(B7))*COS(RADIANS(B8))+SIN(RADIANS(B7))*SIN(RADIANS(B8))*COS(RADIANS(C8-C7))))))) | L8: =IF(K8="","",IF(K8=0,1,2/RADIANS(K8)*TAN(RADIANS(K8)/2))) | M8: =IF($A8="",NA(),E8) | N8: =IF($A8="",NA(),D8) | O8: =IF($A8="",NA(),G8) | P8: =IF($A8="",NA(),F8)
A9: 2000 | B9: 0 | C9: 0 | D9: =IF(K9="","",D8+(A9-A8)/2*(COS(RADIANS(B8))+COS(RADIANS(B9)))*L9) | E9: =IF(D9="","",F9*COS(RADIANS($B$3))+G9*SIN(RADIANS($B$3))) | F9: =IF(K9="","",ROUND(F8+(A9-A8)/2*(SIN(RADIANS(B8))*COS(RADIANS(C8))+SIN(RADIANS(B9))*COS(RADIANS(C9)))*L9,4)) | G9: =IF(K9="","",ROUND(G8+(A9-A8)/2*(SIN(RADIANS(B8))*SIN(RADIANS(C8))+SIN(RADIANS(B9))*SIN(RADIANS(C9)))*L9,4)) | H9: =IF(K9="","",IF(A9=A8,0,K9*100/(A9-A8))) | I9: =IF(A9="",9.9E+99,A9) | J9: =IF(D9="",0,D9) | K9: =IF(OR(A9="",A8=""),"",DEGREES(ACOS(MIN(1,MAX(-1,COS(RADIANS(B8))*COS(RADIANS(B9))+SIN(RADIANS(B8))*SIN(RADIANS(B9))*COS(RADIANS(C9-C8))))))) | L9: =IF(K9="","",IF(K9=0,1,2/RADIANS(K9)*TAN(RADIANS(K9)/2))) | M9: =IF($A9="",NA(),E9) | N9: =IF($A9="",NA(),D9) | O9: =IF($A9="",NA(),G9) | P9: =IF($A9="",NA(),F9)
A10: 3000 | B10: 0 | C10: 0 | D10: =IF(K10="","",D9+(A10-A9)/2*(COS(RADIANS(B9))+COS(RADIANS(B10)))*L10) | E10: =IF(D10="","",F10*COS(RADIANS($B$3))+G10*SIN(RADIANS($B$3))) | F10: =IF(K10="","",ROUND(F9+(A10-A9)/2*(SIN(RADIANS(B9))*COS(RADIANS(C9))+SIN(RADIANS(B10))*COS(RADIANS(C10)))*L10,4)) | G10: =IF(K10="","",ROUND(G9+(A10-A9)/2*(SIN(RADIANS(B9))*SIN(RADIANS(C9))+SIN(RADIANS(B10))*SIN(RADIANS(C10)))*L10,4)) | H10: =IF(K10="","",IF(A10=A9,0,K10*100/(A10-A9))) | I10: =IF(A10="",9.9E+99,A10) | J10: =IF(D10="",0,D10) | K10: =IF(OR(A10="",A9=""),"",DEGREES(ACOS(MIN(1,MAX(-1,COS(RADIANS(B9))*COS(RADIANS(B10))+SIN(RADIANS(B9))*SIN(RADIANS(B10))*COS(RADIANS(C10-C9))))))) | L10: =IF(K10="","",IF(K10=0,1,2/RADIANS(K10)*TAN(RADIANS(K10)/2))) | M10: =IF($A10="",NA(),E10) | N10: =IF($A10="",NA(),D10) | O10: =IF($A10="",NA(),G10) | P10: =IF($A10="",NA(),F10)
A11: 4000 | B11: 0 | C11: 0 | D11: =IF(K11="","",D10+(A11-A10)/2*(COS(RADIANS(B10))+COS(RADIANS(B11)))*L11) | E11: =IF(D11="","",F11*COS(RADIANS($B$3))+G11*SIN(RADIANS($B$3))) | F11: =IF(K11="","",ROUND(F10+(A11-A10)/2*(SIN(RADIANS(B10))*COS(RADIANS(C10))+SIN(RADIANS(B11))*COS(RADIANS(C11)))*L11,4)) | G11: =IF(K11="","",ROUND(G10+(A11-A10)/2*(SIN(RADIANS(B10))*SIN(RADIANS(C10))+SIN(RADIANS(B11))*SIN(RADIANS(C11)))*L11,4)) | H11: =IF(K11="","",IF(A11=A10,0,K11*100/(A11-A10))) | I11: =IF(A11="",9.9E+99,A11) | J11: =IF(D11="",0,D11) | K11: =IF(OR(A11="",A10=""),"",DEGREES(ACOS(MIN(1,MAX(-1,COS(RADIANS(B10))*COS(RADIANS(B11))+SIN(RADIANS(B10))*SIN(RADIANS(B11))*COS(RADIANS(C11-C10))))))) | L11: =IF(K11="","",IF(K11=0,1,2/RADIANS(K11)*TAN(RADIANS(K11)/2))) | M11: =IF($A11="",NA(),E11) | N11: =IF($A11="",NA(),D11) | O11: =IF($A11="",NA(),G11) | P11: =IF($A11="",NA(),F11)
A12: 4500 | B12: 0 | C12: 0 | D12: =IF(K12="","",D11+(A12-A11)/2*(COS(RADIANS(B11))+COS(RADIANS(B12)))*L12) | E12: =IF(D12="","",F12*COS(RADIANS($B$3))+G12*SIN(RADIANS($B$3))) | F12: =IF(K12="","",ROUND(F11+(A12-A11)/2*(SIN(RADIANS(B11))*COS(RADIANS(C11))+SIN(RADIANS(B12))*COS(RADIANS(C12)))*L12,4)) | G12: =IF(K12="","",ROUND(G11+(A12-A11)/2*(SIN(RADIANS(B11))*SIN(RADIANS(C11))+SIN(RADIANS(B12))*SIN(RADIANS(C12)))*L12,4)) | H12: =IF(K12="","",IF(A12=A11,0,K12*100/(A12-A11))) | I12: =IF(A12="",9.9E+99,A12) | J12: =IF(D12="",0,D12) | K12: =IF(OR(A12="",A11=""),"",DEGREES(ACOS(MIN(1,MAX(-1,COS(RADIANS(B11))*COS(RADIANS(B12))+SIN(RADIANS(B11))*SIN(RADIANS(B12))*COS(RADIANS(C12-C11))))))) | L12: =IF(K12="","",IF(K12=0,1,2/RADIANS(K12)*TAN(RADIANS(K12)/2))) | M12: =IF($A12="",NA(),E12) | N12: =IF($A12="",NA(),D12) | O12: =IF($A12="",NA(),G12) | P12: =IF($A12="",NA(),F12)
A13: 5000 | B13: 0 | C13: 0 | D13: =IF(K13="","",D12+(A13-A12)/2*(COS(RADIANS(B12))+COS(RADIANS(B13)))*L13) | E13: =IF(D13="","",F13*COS(RADIANS($B$3))+G13*SIN(RADIANS($B$3))) | F13: =IF(K13="","",ROUND(F12+(A13-A12)/2*(SIN(RADIANS(B12))*COS(RADIANS(C12))+SIN(RADIANS(B13))*COS(RADIANS(C13)))*L13,4)) | G13: =IF(K13="","",ROUND(G12+(A13-A12)/2*(SIN(RADIANS(B12))*SIN(RADIANS(C12))+SIN(RADIANS(B13))*SIN(RADIANS(C13)))*L13,4)) | H13: =IF(K13="","",IF(A13=A12,0,K13*100/(A13-A12))) | I13: =IF(A13="",9.9E+99,A13) | J13: =IF(D13="",0,D13) | K13: =IF(OR(A13="",A12=""),"",DEGREES(ACOS(MIN(1,MAX(-1,COS(RADIANS(B12))*COS(RADIANS(B13))+SIN(RADIANS(B12))*SIN(RADIANS(B13))*COS(RADIANS(C13-C12))))))) | L13: =IF(K13="","",IF(K13=0,1,2/RADIANS(K13)*TAN(RADIANS(K13)/2))) | M13: =IF($A13="",NA(),E13) | N13: =IF($A13="",NA(),D13) | O13: =IF($A13="",NA(),G13) | P13: =IF($A13="",NA(),F13)
A14: 5100 | B14: 10 | C14: 90 | D14: =IF(K14="","",D13+(A14-A13)/2*(COS(RADIANS(B13))+COS(RADIANS(B14)))*L14) | E14: =IF(D14="","",F14*COS(RADIANS($B$3))+G14*SIN(RADIANS($B$3))) | F14: =IF(K14="","",ROUND(F13+(A14-A13)/2*(SIN(RADIANS(B13))*COS(RADIANS(C13))+SIN(RADIANS(B14))*COS(RADIANS(C14)))*L14,4)) | G14: =IF(K14="","",ROUND(G13+(A14-A13)/2*(SIN(RADIANS(B13))*SIN(RADIANS(C13))+SIN(RADIANS(B14))*SIN(RADIANS(C14)))*L14,4)) | H14: =IF(K14="","",IF(A14=A13,0,K14*100/(A14-A13))) | I14: =IF(A14="",9.9E+99,A14) | J14: =IF(D14="",0,D14) | K14: =IF(OR(A14="",A13=""),"",DEGREES(ACOS(MIN(1,MAX(-1,COS(RADIANS(B13))*COS(RADIANS(B14))+SIN(RADIANS(B13))*SIN(RADIANS(B14))*COS(RADIANS(C14-C13))))))) | L14: =IF(K14="","",IF(K14=0,1,2/RADIANS(K14)*TAN(RADIANS(K14)/2))) | M14: =IF($A14="",NA(),E14) | N14: =IF($A14="",NA(),D14) | O14: =IF($A14="",NA(),G14) | P14: =IF($A14="",NA(),F14)
A15: 5200 | B15: 20 | C15: 90 | D15: =IF(K15="","",D14+(A15-A14)/2*(COS(RADIANS(B14))+COS(RADIANS(B15)))*L15) | E15: =IF(D15="","",F15*COS(RADIANS($B$3))+G15*SIN(RADIANS($B$3))) | F15: =IF(K15="","",ROUND(F14+(A15-A14)/2*(SIN(RADIANS(B14))*COS(RADIANS(C14))+SIN(RADIANS(B15))*COS(RADIANS(C15)))*L15,4)) | G15: =IF(K15="","",ROUND(G14+(A15-A14)/2*(SIN(RADIANS(B14))*SIN(RADIANS(C14))+SIN(RADIANS(B15))*SIN(RADIANS(C15)))*L15,4)) | H15: =IF(K15="","",IF(A15=A14,0,K15*100/(A15-A14))) | I15: =IF(A15="",9.9E+99,A15) | J15: =IF(D15="",0,D15) | K15: =IF(OR(A15="",A14=""),"",DEGREES(ACOS(MIN(1,MAX(-1,COS(RADIANS(B14))*COS(RADIANS(B15))+SIN(RADIANS(B14))*SIN(RADIANS(B15))*COS(RADIANS(C15-C14))))))) | L15: =IF(K15="","",IF(K15=0,1,2/RADIANS(K15)*TAN(RADIANS(K15)/2))) | M15: =IF($A15="",NA(),E15) | N15: =IF($A15="",NA(),D15) | O15: =IF($A15="",NA(),G15) | P15: =IF($A15="",NA(),F15)
A16: 5300 | B16: 30 | C16: 90 | D16: =IF(K16="","",D15+(A16-A15)/2*(COS(RADIANS(B15))+COS(RADIANS(B16)))*L16) | E16: =IF(D16="","",F16*COS(RADIANS($B$3))+G16*SIN(RADIANS($B$3))) | F16: =IF(K16="","",ROUND(F15+(A16-A15)/2*(SIN(RADIANS(B15))*COS(RADIANS(C15))+SIN(RADIANS(B16))*COS(RADIANS(C16)))*L16,4)) | G16: =IF(K16="","",ROUND(G15+(A16-A15)/2*(SIN(RADIANS(B15))*SIN(RADIANS(C15))+SIN(RADIANS(B16))*SIN(RADIANS(C16)))*L16,4)) | H16: =IF(K16="","",IF(A16=A15,0,K16*100/(A16-A15))) | I16: =IF(A16="",9.9E+99,A16) | J16: =IF(D16="",0,D16) | K16: =IF(OR(A16="",A15=""),"",DEGREES(ACOS(MIN(1,MAX(-1,COS(RADIANS(B15))*COS(RADIANS(B16))+SIN(RADIANS(B15))*SIN(RADIANS(B16))*COS(RADIANS(C16-C15))))))) | L16: =IF(K16="","",IF(K16=0,1,2/RADIANS(K16)*TAN(RADIANS(K16)/2))) | M16: =IF($A16="",NA(),E16) | N16: =IF($A16="",NA(),D16) | O16: =IF($A16="",NA(),G16) | P16: =IF($A16="",NA(),F16)
A17: 5400 | B17: 40 | C17: 90 | D17: =IF(K17="","",D16+(A17-A16)/2*(COS(RADIANS(B16))+COS(RADIANS(B17)))*L17) | E17: =IF(D17="","",F17*COS(RADIANS($B$3))+G17*SIN(RADIANS($B$3))) | F17: =IF(K17="","",ROUND(F16+(A17-A16)/2*(SIN(RADIANS(B16))*COS(RADIANS(C16))+SIN(RADIANS(B17))*COS(RADIANS(C17)))*L17,4)) | G17: =IF(K17="","",ROUND(G16+(A17-A16)/2*(SIN(RADIANS(B16))*SIN(RADIANS(C16))+SIN(RADIANS(B17))*SIN(RADIANS(C17)))*L17,4)) | H17: =IF(K17="","",IF(A17=A16,0,K17*100/(A17-A16))) | I17: =IF(A17="",9.9E+99,A17) | J17: =IF(D17="",0,D17) | K17: =IF(OR(A17="",A16=""),"",DEGREES(ACOS(MIN(1,MAX(-1,COS(RADIANS(B16))*COS(RADIANS(B17))+SIN(RADIANS(B16))*SIN(RADIANS(B17))*COS(RADIANS(C17-C16))))))) | L17: =IF(K17="","",IF(K17=0,1,2/RADIANS(K17)*TAN(RADIANS(K17)/2))) | M17: =IF($A17="",NA(),E17) | N17: =IF($A17="",NA(),D17) | O17: =IF($A17="",NA(),G17) | P17: =IF($A17="",NA(),F17)
A18: 5500 | B18: 50 | C18: 90 | D18: =IF(K18="","",D17+(A18-A17)/2*(COS(RADIANS(B17))+COS(RADIANS(B18)))*L18) | E18: =IF(D18="","",F18*COS(RADIANS($B$3))+G18*SIN(RADIANS($B$3))) | F18: =IF(K18="","",ROUND(F17+(A18-A17)/2*(SIN(RADIANS(B17))*COS(RADIANS(C17))+SIN(RADIANS(B18))*COS(RADIANS(C18)))*L18,4)) | G18: =IF(K18="","",ROUND(G17+(A18-A17)/2*(SIN(RADIANS(B17))*SIN(RADIANS(C17))+SIN(RADIANS(B18))*SIN(RADIANS(C18)))*L18,4)) | H18: =IF(K18="","",IF(A18=A17,0,K18*100/(A18-A17))) | I18: =IF(A18="",9.9E+99,A18) | J18: =IF(D18="",0,D18) | K18: =IF(OR(A18="",A17=""),"",DEGREES(ACOS(MIN(1,MAX(-1,COS(RADIANS(B17))*COS(RADIANS(B18))+SIN(RADIANS(B17))*SIN(RADIANS(B18))*COS(RADIANS(C18-C17))))))) | L18: =IF(K18="","",IF(K18=0,1,2/RADIANS(K18)*TAN(RADIANS(K18)/2))) | M18: =IF($A18="",NA(),E18) | N18: =IF($A18="",NA(),D18) | O18: =IF($A18="",NA(),G18) | P18: =IF($A18="",NA(),F18)
A19: 5600 | B19: 60 | C19: 90 | D19: =IF(K19="","",D18+(A19-A18)/2*(COS(RADIANS(B18))+COS(RADIANS(B19)))*L19) | E19: =IF(D19="","",F19*COS(RADIANS($B$3))+G19*SIN(RADIANS($B$3))) | F19: =IF(K19="","",ROUND(F18+(A19-A18)/2*(SIN(RADIANS(B18))*COS(RADIANS(C18))+SIN(RADIANS(B19))*COS(RADIANS(C19)))*L19,4)) | G19: =IF(K19="","",ROUND(G18+(A19-A18)/2*(SIN(RADIANS(B18))*SIN(RADIANS(C18))+SIN(RADIANS(B19))*SIN(RADIANS(C19)))*L19,4)) | H19: =IF(K19="","",IF(A19=A18,0,K19*100/(A19-A18))) | I19: =IF(A19="",9.9E+99,A19) | J19: =IF(D19="",0,D19) | K19: =IF(OR(A19="",A18=""),"",DEGREES(ACOS(MIN(1,MAX(-1,COS(RADIANS(B18))*COS(RADIANS(B19))+SIN(RADIANS(B18))*SIN(RADIANS(B19))*COS(RADIANS(C19-C18))))))) | L19: =IF(K19="","",IF(K19=0,1,2/RADIANS(K19)*TAN(RADIANS(K19)/2))) | M19: =IF($A19="",NA(),E19) | N19: =IF($A19="",NA(),D19) | O19: =IF($A19="",NA(),G19) | P19: =IF($A19="",NA(),F19)
... A32: 10500 | B32: 90 | C32: 90 | D32: =IF(K32="","",D31+(A32-A31)/2*(COS(RADIANS(B31))+COS(RADIANS(B32)))*L32) | E32: =IF(D32="","",F32*COS(RADIANS($B$3))+G32*SIN(RADIANS($B$3))) | F32: =IF(K32="","",ROUND(F31+(A32-A31)/2*(SIN(RADIANS(B31))*COS(RADIANS(C31))+SIN(RADIANS(B32))*COS(RADIANS(C32)))*L32,4)) | G32: =IF(K32="","",ROUND(G31+(A32-A31)/2*(SIN(RADIANS(B31))*SIN(RADIANS(C31))+SIN(RADIANS(B32))*SIN(RADIANS(C32)))*L32,4)) | H32: =IF(K32="","",IF(A32=A31,0,K32*100/(A32-A31))) | I32: =IF(A32="",9.9E+99,A32) | J32: =IF(D32="",0,D32) | K32: =IF(OR(A32="",A31=""),"",DEGREES(ACOS(MIN(1,MAX(-1,COS(RADIANS(B31))*COS(RADIANS(B32))+SIN(RADIANS(B31))*SIN(RADIANS(B32))*COS(RADIANS(C32-C31))))))) | L32: =IF(K32="","",IF(K32=0,1,2/RADIANS(K32)*TAN(RADIANS(K32)/2))) | M32: =IF($A32="",NA(),E32) | N32: =IF($A32="",NA(),D32) | O32: =IF($A32="",NA(),G32) | P32: =IF($A32="",NA(),F32)
D33: =IF(K33="","",D32+(A33-A32)/2*(COS(RADIANS(B32))+COS(RADIANS(B33)))*L33) | E33: =IF(D33="","",F33*COS(RADIANS($B$3))+G33*SIN(RADIANS($B$3))) | F33: =IF(K33="","",ROUND(F32+(A33-A32)/2*(SIN(RADIANS(B32))*COS(RADIANS(C32))+SIN(RADIANS(B33))*COS(RADIANS(C33)))*L33,4)) | G33: =IF(K33="","",ROUND(G32+(A33-A32)/2*(SIN(RADIANS(B32))*SIN(RADIANS(C32))+SIN(RADIANS(B33))*SIN(RADIANS(C33)))*L33,4)) | H33: =IF(K33="","",IF(A33=A32,0,K33*100/(A33-A32))) | I33: =IF(A33="",9.9E+99,A33) | J33: =IF(D33="",0,D33) | K33: =IF(OR(A33="",A32=""),"",DEGREES(ACOS(MIN(1,MAX(-1,COS(RADIANS(B32))*COS(RADIANS(B33))+SIN(RADIANS(B32))*SIN(RADIANS(B33))*COS(RADIANS(C33-C32))))))) | L33: =IF(K33="","",IF(K33=0,1,2/RADIANS(K33)*TAN(RADIANS(K33)/2))) | M33: =IF($A33="",NA(),E33) | N33: =IF($A33="",NA(),D33) | O33: =IF($A33="",NA(),G33) | P33: =IF($A33="",NA(),F33)
D34: =IF(K34="","",D33+(A34-A33)/2*(COS(RADIANS(B33))+COS(RADIANS(B34)))*L34) | E34: =IF(D34="","",F34*COS(RADIANS($B$3))+G34*SIN(RADIANS($B$3))) | F34: =IF(K34="","",ROUND(F33+(A34-A33)/2*(SIN(RADIANS(B33))*COS(RADIANS(C33))+SIN(RADIANS(B34))*COS(RADIANS(C34)))*L34,4)) | G34: =IF(K34="","",ROUND(G33+(A34-A33)/2*(SIN(RADIANS(B33))*SIN(RADIANS(C33))+SIN(RADIANS(B34))*SIN(RADIANS(C34)))*L34,4)) | H34: =IF(K34="","",IF(A34=A33,0,K34*100/(A34-A33))) | I34: =IF(A34="",9.9E+99,A34) | J34: =IF(D34="",0,D34) | K34: =IF(OR(A34="",A33=""),"",DEGREES(ACOS(MIN(1,MAX(-1,COS(RADIANS(B33))*COS(RADIANS(B34))+SIN(RADIANS(B33))*SIN(RADIANS(B34))*COS(RADIANS(C34-C33))))))) | L34: =IF(K34="","",IF(K34=0,1,2/RADIANS(K34)*TAN(RADIANS(K34)/2))) | M34: =IF($A34="",NA(),E34) | N34: =IF($A34="",NA(),D34) | O34: =IF($A34="",NA(),G34) | P34: =IF($A34="",NA(),F34)
D35: =IF(K35="","",D34+(A35-A34)/2*(COS(RADIANS(B34))+COS(RADIANS(B35)))*L35) | E35: =IF(D35="","",F35*COS(RADIANS($B$3))+G35*SIN(RADIANS($B$3))) | F35: =IF(K35="","",ROUND(F34+(A35-A34)/2*(SIN(RADIANS(B34))*COS(RADIANS(C34))+SIN(RADIANS(B35))*COS(RADIANS(C35)))*L35,4)) | G35: =IF(K35="","",ROUND(G34+(A35-A34)/2*(SIN(RADIANS(B34))*SIN(RADIANS(C34))+SIN(RADIANS(B35))*SIN(RADIANS(C35)))*L35,4)) | H35: =IF(K35="","",IF(A35=A34,0,K35*100/(A35-A34))) | I35: =IF(A35="",9.9E+99,A35) | J35: =IF(D35="",0,D35) | K35: =IF(OR(A35="",A34=""),"",DEGREES(ACOS(MIN(1,MAX(-1,COS(RADIANS(B34))*COS(RADIANS(B35))+SIN(RADIANS(B34))*SIN(RADIANS(B35))*COS(RADIANS(C35-C34))))))) | L35: =IF(K35="","",IF(K35=0,1,2/RADIANS(K35)*TAN(RADIANS(K35)/2))) | M35: =IF($A35="",NA(),E35) | N35: =IF($A35="",NA(),D35) | O35: =IF($A35="",NA(),G35) | P35: =IF($A35="",NA(),F35)
D36: =IF(K36="","",D35+(A36-A35)/2*(COS(RADIANS(B35))+COS(RADIANS(B36)))*L36) | E36: =IF(D36="","",F36*COS(RADIANS($B$3))+G36*SIN(RADIANS($B$3))) | F36: =IF(K36="","",ROUND(F35+(A36-A35)/2*(SIN(RADIANS(B35))*COS(RADIANS(C35))+SIN(RADIANS(B36))*COS(RADIANS(C36)))*L36,4)) | G36: =IF(K36="","",ROUND(G35+(A36-A35)/2*(SIN(RADIANS(B35))*SIN(RADIANS(C35))+SIN(RADIANS(B36))*SIN(RADIANS(C36)))*L36,4)) | H36: =IF(K36="","",IF(A36=A35,0,K36*100/(A36-A35))) | I36: =IF(A36="",9.9E+99,A36) | J36: =IF(D36="",0,D36) | K36: =IF(OR(A36="",A35=""),"",DEGREES(ACOS(MIN(1,MAX(-1,COS(RADIANS(B35))*COS(RADIANS(B36))+SIN(RADIANS(B35))*SIN(RADIANS(B36))*COS(RADIANS(C36-C35))))))) | L36: =IF(K36="","",IF(K36=0,1,2/RADIANS(K36)*TAN(RADIANS(K36)/2))) | M36: =IF($A36="",NA(),E36) | N36: =IF($A36="",NA(),D36) | O36: =IF($A36="",NA(),G36) | P36: =IF($A36="",NA(),F36)
D37: =IF(K37="","",D36+(A37-A36)/2*(COS(RADIANS(B36))+COS(RADIANS(B37)))*L37) | E37: =IF(D37="","",F37*COS(RADIANS($B$3))+G37*SIN(RADIANS($B$3))) | F37: =IF(K37="","",ROUND(F36+(A37-A36)/2*(SIN(RADIANS(B36))*COS(RADIANS(C36))+SIN(RADIANS(B37))*COS(RADIANS(C37)))*L37,4)) | G37: =IF(K37="","",ROUND(G36+(A37-A36)/2*(SIN(RADIANS(B36))*SIN(RADIANS(C36))+SIN(RADIANS(B37))*SIN(RADIANS(C37)))*L37,4)) | H37: =IF(K37="","",IF(A37=A36,0,K37*100/(A37-A36))) | I37: =IF(A37="",9.9E+99,A37) | J37: =IF(D37="",0,D37) | K37: =IF(OR(A37="",A36=""),"",DEGREES(ACOS(MIN(1,MAX(-1,COS(RADIANS(B36))*COS(RADIANS(B37))+SIN(RADIANS(B36))*SIN(RADIANS(B37))*COS(RADIANS(C37-C36))))))) | L37: =IF(K37="","",IF(K37=0,1,2/RADIANS(K37)*TAN(RADIANS(K37)/2))) | M37: =IF($A37="",NA(),E37) | N37: =IF($A37="",NA(),D37) | O37: =IF($A37="",NA(),G37) | P37: =IF($A37="",NA(),F37)
D38: =IF(K38="","",D37+(A38-A37)/2*(COS(RADIANS(B37))+COS(RADIANS(B38)))*L38) | E38: =IF(D38="","",F38*COS(RADIANS($B$3))+G38*SIN(RADIANS($B$3))) | F38: =IF(K38="","",ROUND(F37+(A38-A37)/2*(SIN(RADIANS(B37))*COS(RADIANS(C37))+SIN(RADIANS(B38))*COS(RADIANS(C38)))*L38,4)) | G38: =IF(K38="","",ROUND(G37+(A38-A37)/2*(SIN(RADIANS(B37))*SIN(RADIANS(C37))+SIN(RADIANS(B38))*SIN(RADIANS(C38)))*L38,4)) | H38: =IF(K38="","",IF(A38=A37,0,K38*100/(A38-A37))) | I38: =IF(A38="",9.9E+99,A38) | J38: =IF(D38="",0,D38) | K38: =IF(OR(A38="",A37=""),"",DEGREES(ACOS(MIN(1,MAX(-1,COS(RADIANS(B37))*COS(RADIANS(B38))+SIN(RADIANS(B37))*SIN(RADIANS(B38))*COS(RADIANS(C38-C37))))))) | L38: =IF(K38="","",IF(K38=0,1,2/RADIANS(K38)*TAN(RADIANS(K38)/2))) | M38: =IF($A38="",NA(),E38) | N38: =IF($A38="",NA(),D38) | O38: =IF($A38="",NA(),G38) | P38: =IF($A38="",NA(),F38)
D39: =IF(K39="","",D38+(A39-A38)/2*(COS(RADIANS(B38))+COS(RADIANS(B39)))*L39) | E39: =IF(D39="","",F39*COS(RADIANS($B$3))+G39*SIN(RADIANS($B$3))) | F39: =IF(K39="","",ROUND(F38+(A39-A38)/2*(SIN(RADIANS(B38))*COS(RADIANS(C38))+SIN(RADIANS(B39))*COS(RADIANS(C39)))*L39,4)) | G39: =IF(K39="","",ROUND(G38+(A39-A38)/2*(SIN(RADIANS(B38))*SIN(RADIANS(C38))+SIN(RADIANS(B39))*SIN(RADIANS(C39)))*L39,4)) | H39: =IF(K39="","",IF(A39=A38,0,K39*100/(A39-A38))) | I39: =IF(A39="",9.9E+99,A39) | J39: =IF(D39="",0,D39) | K39: =IF(OR(A39="",A38=""),"",DEGREES(ACOS(MIN(1,MAX(-1,COS(RADIANS(B38))*COS(RADIANS(B39))+SIN(RADIANS(B38))*SIN(RADIANS(B39))*COS(RADIANS(C39-C38))))))) | L39: =IF(K39="","",IF(K39=0,1,2/RADIANS(K39)*TAN(RADIANS(K39)/2))) | M39: =IF($A39="",NA(),E39) | N39: =IF($A39="",NA(),D39) | O39: =IF($A39="",NA(),G39) | P39: =IF($A39="",NA(),F39)
D40: =IF(K40="","",D39+(A40-A39)/2*(COS(RADIANS(B39))+COS(RADIANS(B40)))*L40) | E40: =IF(D40="","",F40*COS(RADIANS($B$3))+G40*SIN(RADIANS($B$3))) | F40: =IF(K40="","",ROUND(F39+(A40-A39)/2*(SIN(RADIANS(B39))*COS(RADIANS(C39))+SIN(RADIANS(B40))*COS(RADIANS(C40)))*L40,4)) | G40: =IF(K40="","",ROUND(G39+(A40-A39)/2*(SIN(RADIANS(B39))*SIN(RADIANS(C39))+SIN(RADIANS(B40))*SIN(RADIANS(C40)))*L40,4)) | H40: =IF(K40="","",IF(A40=A39,0,K40*100/(A40-A39))) | I40: =IF(A40="",9.9E+99,A40) | J40: =IF(D40="",0,D40) | K40: =IF(OR(A40="",A39=""),"",DEGREES(ACOS(MIN(1,MAX(-1,COS(RADIANS(B39))*COS(RADIANS(B40))+SIN(RADIANS(B39))*SIN(RADIANS(B40))*COS(RADIANS(C40-C39))))))) | L40: =IF(K40="","",IF(K40=0,1,2/RADIANS(K40)*TAN(RADIANS(K40)/2))) | M40: =IF($A40="",NA(),E40) | N40: =IF($A40="",NA(),D40) | O40: =IF($A40="",NA(),G40) | P40: =IF($A40="",NA(),F40)
D41: =IF(K41="","",D40+(A41-A40)/2*(COS(RADIANS(B40))+COS(RADIANS(B41)))*L41) | E41: =IF(D41="","",F41*COS(RADIANS($B$3))+G41*SIN(RADIANS($B$3))) | F41: =IF(K41="","",ROUND(F40+(A41-A40)/2*(SIN(RADIANS(B40))*COS(RADIANS(C40))+SIN(RADIANS(B41))*COS(RADIANS(C41)))*L41,4)) | G41: =IF(K41="","",ROUND(G40+(A41-A40)/2*(SIN(RADIANS(B40))*SIN(RADIANS(C40))+SIN(RADIANS(B41))*SIN(RADIANS(C41)))*L41,4)) | H41: =IF(K41="","",IF(A41=A40,0,K41*100/(A41-A40))) | I41: =IF(A41="",9.9E+99,A41) | J41: =IF(D41="",0,D41) | K41: =IF(OR(A41="",A40=""),"",DEGREES(ACOS(MIN(1,MAX(-1,COS(RADIANS(B40))*COS(RADIANS(B41))+SIN(RADIANS(B40))*SIN(RADIANS(B41))*COS(RADIANS(C41-C40))))))) | L41: =IF(K41="","",IF(K41=0,1,2/RADIANS(K41)*TAN(RADIANS(K41)/2))) | M41: =IF($A41="",NA(),E41) | N41: =IF($A41="",NA(),D41) | O41: =IF($A41="",NA(),G41) | P41: =IF($A41="",NA(),F41)
D42: =IF(K42="","",D41+(A42-A41)/2*(COS(RADIANS(B41))+COS(RADIANS(B42)))*L42) | E42: =IF(D42="","",F42*COS(RADIANS($B$3))+G42*SIN(RADIANS($B$3))) | F42: =IF(K42="","",ROUND(F41+(A42-A41)/2*(SIN(RADIANS(B41))*COS(RADIANS(C41))+SIN(RADIANS(B42))*COS(RADIANS(C42)))*L42,4)) | G42: =IF(K42="","",ROUND(G41+(A42-A41)/2*(SIN(RADIANS(B41))*SIN(RADIANS(C41))+SIN(RADIANS(B42))*SIN(RADIANS(C42)))*L42,4)) | H42: =IF(K42="","",IF(A42=A41,0,K42*100/(A42-A41))) | I42: =IF(A42="",9.9E+99,A42) | J42: =IF(D42="",0,D42) | K42: =IF(OR(A42="",A41=""),"",DEGREES(ACOS(MIN(1,MAX(-1,COS(RADIANS(B41))*COS(RADIANS(B42))+SIN(RADIANS(B41))*SIN(RADIANS(B42))*COS(RADIANS(C42-C41))))))) | L42: =IF(K42="","",IF(K42=0,1,2/RADIANS(K42)*TAN(RADIANS(K42)/2))) | M42: =IF($A42="",NA(),E42) | N42: =IF($A42="",NA(),D42) | O42: =IF($A42="",NA(),G42) | P42: =IF($A42="",NA(),F42)
D43: =IF(K43="","",D42+(A43-A42)/2*(COS(RADIANS(B42))+COS(RADIANS(B43)))*L43) | E43: =IF(D43="","",F43*COS(RADIANS($B$3))+G43*SIN(RADIANS($B$3))) | F43: =IF(K43="","",ROUND(F42+(A43-A42)/2*(SIN(RADIANS(B42))*COS(RADIANS(C42))+SIN(RADIANS(B43))*COS(RADIANS(C43)))*L43,4)) | G43: =IF(K43="","",ROUND(G42+(A43-A42)/2*(SIN(RADIANS(B42))*SIN(RADIANS(C42))+SIN(RADIANS(B43))*SIN(RADIANS(C43)))*L43,4)) | H43: =IF(K43="","",IF(A43=A42,0,K43*100/(A43-A42))) | I43: =IF(A43="",9.9E+99,A43) | J43: =IF(D43="",0,D43) | K43: =IF(OR(A43="",A42=""),"",DEGREES(ACOS(MIN(1,MAX(-1,COS(RADIANS(B42))*COS(RADIANS(B43))+SIN(RADIANS(B42))*SIN(RADIANS(B43))*COS(RADIANS(C43-C42))))))) | L43: =IF(K43="","",IF(K43=0,1,2/RADIANS(K43)*TAN(RADIANS(K43)/2))) | M43: =IF($A43="",NA(),E43) | N43: =IF($A43="",NA(),D43) | O43: =IF($A43="",NA(),G43) | P43: =IF($A43="",NA(),F43)
D44: =IF(K44="","",D43+(A44-A43)/2*(COS(RADIANS(B43))+COS(RADIANS(B44)))*L44) | E44: =IF(D44="","",F44*COS(RADIANS($B$3))+G44*SIN(RADIANS($B$3))) | F44: =IF(K44="","",ROUND(F43+(A44-A43)/2*(SIN(RADIANS(B43))*COS(RADIANS(C43))+SIN(RADIANS(B44))*COS(RADIANS(C44)))*L44,4)) | G44: =IF(K44="","",ROUND(G43+(A44-A43)/2*(SIN(RADIANS(B43))*SIN(RADIANS(C43))+SIN(RADIANS(B44))*SIN(RADIANS(C44)))*L44,4)) | H44: =IF(K44="","",IF(A44=A43,0,K44*100/(A44-A43))) | I44: =IF(A44="",9.9E+99,A44) | J44: =IF(D44="",0,D44) | K44: =IF(OR(A44="",A43=""),"",DEGREES(ACOS(MIN(1,MAX(-1,COS(RADIANS(B43))*COS(RADIANS(B44))+SIN(RADIANS(B43))*SIN(RADIANS(B44))*COS(RADIANS(C44-C43))))))) | L44: =IF(K44="","",IF(K44=0,1,2/RADIANS(K44)*TAN(RADIANS(K44)/2))) | M44: =IF($A44="",NA(),E44) | N44: =IF($A44="",NA(),D44) | O44: =IF($A44="",NA(),G44) | P44: =IF($A44="",NA(),F44)
... D106: =IF(K106="","",D105+(A106-A105)/2*(COS(RADIANS(B105))+COS(RADIANS(B106)))*L106) | E106: =IF(D106="","",F106*COS(RADIANS($B$3))+G106*SIN(RADIANS($B$3))) | F106: =IF(K106="","",ROUND(F105+(A106-A105)/2*(SIN(RADIANS(B105))*COS(RADIANS(C105))+SIN(RADIANS(B106))*COS(RADIANS(C106)))*L106,4)) | G106: =IF(K106="","",ROUND(G105+(A106-A105)/2*(SIN(RADIANS(B105))*SIN(RADIANS(C105))+SIN(RADIANS(B106))*SIN(RADIANS(C106)))*L106,4)) | H106: =IF(K106="","",IF(A106=A105,0,K106*100/(A106-A105))) | I106: =IF(A106="",9.9E+99,A106) | J106: =IF(D106="",0,D106) | K106: =IF(OR(A106="",A105=""),"",DEGREES(ACOS(MIN(1,MAX(-1,COS(RADIANS(B105))*COS(RADIANS(B106))+SIN(RADIANS(B105))*SIN(RADIANS(B106))*COS(RADIANS(C106-C105))))))) | L106: =IF(K106="","",IF(K106=0,1,2/RADIANS(K106)*TAN(RADIANS(K106)/2))) | M106: =IF($A106="",NA(),E106) | N106: =IF($A106="",NA(),D106) | O106: =IF($A106="",NA(),G106) | P106: =IF($A106="",NA(),F106)
A107: * helper columns used by charts and the Kill Sheet - do not edit. VS_c/TVD_c/EW_c/NS_c show #N/A on unused rows by design (chart gaps).
A109: TVD Interpolator (same logic the Kill Sheet uses)
A110: Measured depth | B110: 8000 | C110: ft
A111: TVD at that MD | B111: =INDEX('Directional Survey'!$J$7:$J$106,MATCH($B$110,'Directional Survey'!$I$7:$I$106,1))+($B$110-INDEX('Directional Survey'!$I$7:$I$106,MATCH($B$110,'Directional Survey'!$I$7:$I$106,1)))*(IFERROR(INDEX('Directional Survey'!$J$7:$J$106,MATCH($B$110,'Directional Survey'!$I$7:$I$106,1)+1),INDEX('Directional Survey'!$J$7:$J$106,MATCH($B$110,'Directional Survey'!$I$7:$I$106,1)))-INDEX('Directional Survey'!$J$7:$J$106,MATCH($B$110,'Directional Survey'!$I$7:$I$106,1)))/(IFERROR(INDEX('Directional Survey'!$I$7:$I$106,MATCH($B$110,'Directional Survey'!$I$7:$I$106,1)+1),9.9E+99)-INDEX('Directional Survey'!$I$7:$I$106,MATCH($B$110,'Directional Survey'!$I$7:$I$106,1))) | C111: ft

Sheet Torque & Drag
A1: Torque & Drag - Soft-String (Johancsik)
A2: Pick-up / slack-off / rotating tension and torque along the survey, hookloads, buckling screen, tension & torque plots
A4: Parameter | B4: Value | C4: Unit | D4: SI Value | E4: SI Unit | F4: Notes / Equation
A6: Inputs (light blue = linked to Well Data)
A8: String & Friction
F9: Calibrate friction factors to measured hookloads when available. Soft-string model: DP-dominated strings; stiff BHAs read high.
A10: Mud weight | B10: =WD_OMW | C10: ppg | D10: =IFERROR($B$10*119.8264,NA()) | E10: kg/m3 | F10: Linked to Well Data sheet - overwrite locally if this well differs.
A11: Bit / TD measured depth | B11: =WD_MD | C11: ft | D11: =IFERROR($B$11*0.3048,NA()) | E11: m | F11: Linked to Well Data sheet - overwrite locally if this well differs.
A12: Casing shoe MD | B12: =WD_ShoeMD | C12: ft | D12: =IFERROR($B$12*0.3048,NA()) | E12: m | F12: Linked to Well Data sheet - overwrite locally if this well differs.
A13: Open hole diameter | B13: =WD_HoleDiam | C13: in | D13: =IFERROR($B$13*25.4,NA()) | E13: mm | F13: Linked to Well Data sheet - overwrite locally if this well differs.
A14: Casing ID | B14: =WD_CsgID | C14: in | D14: =IFERROR($B$14*25.4,NA()) | E14: mm | F14: Linked to Well Data sheet - overwrite locally if this well differs.
A15: Drill pipe adjusted weight | B15: =WD_DPWt | C15: lb/ft | D15: =IFERROR($B$15*1.488164,NA()) | E15: kg/m | F15: Linked to Well Data sheet - overwrite locally if this well differs.
A16: BHA weight per foot | B16: =WD_BHAWt | C16: lb/ft | D16: =IFERROR($B$16*1.488164,NA()) | E16: kg/m | F16: Linked to Well Data sheet - overwrite locally if this well differs.
A17: BHA length | B17: =WD_BHALen | C17: ft | D17: =IFERROR($B$17*0.3048,NA()) | E17: m | F17: Linked to Well Data sheet - overwrite locally if this well differs.
A18: Friction factor - cased | B18: =WD_MuCased | F18: Linked to Well Data sheet - overwrite locally if this well differs.
A19: Friction factor - open hole | B19: =WD_MuOpen | F19: Linked to Well Data sheet - overwrite locally if this well differs.
A20: Weight on bit (slack-off / rotating case) | B20: =WD_WOB | C20: klbf | D20: =IFERROR($B$20*4.448222,NA()) | E20: kN | F20: Linked to Well Data sheet - overwrite locally if this well differs.
A21: Bit torque (rotating case) | B21: =WD_BitTq | C21: ft-lbf | D21: =IFERROR($B$21*1.355818,NA()) | E21: N-m | F21: Linked to Well Data sheet - overwrite locally if this well differs.
A22: Tool joint OD (torque radius) | B22: =WD_TJOD | C22: in | D22: =IFERROR($B$22*25.4,NA()) | E22: mm | F22: Linked to Well Data sheet - overwrite locally if this well differs.
A23: Block + top drive weight | B23: =WD_BlockWt | C23: klbf | D23: =IFERROR($B$23*4.448222,NA()) | E23: kN | F23: Linked to Well Data sheet - overwrite locally if this well differs.
A24: Drill pipe body OD (buckling) | B24: 5 | C24: in | D24: =IFERROR($B$24*25.4,NA()) | E24: mm
A25: Drill pipe body ID (buckling) | B25: 4.276 | C25: in | D25: =IFERROR($B$25*25.4,NA()) | E25: mm
A26: Steel modulus (E) | B26: 30000000 | C26: psi | D26: =IFERROR($B$26*6.894757,NA()) | E26: kPa | F26: Api RP 7G commonly 29.6-30 x 10^6 psi.
A27: Buoyancy factor | B27: =(65.5-$B$10)/65.5
A28: DP moment of inertia (I) | B28: =PI()/64*($B$24^4-$B$25^4) | F28: in^4
A30: Station Table (marches bottom-up from the bit; rows mirror the survey)
A31: Tension in lbf at each survey node. Pick-up boundary: 0 at bit (off-bottom); slack-off & rotating boundary: -WOB. Torque boundary: bit torque. Buckling screen on the slack-off case.
A32: MD (ft) | B32: Inc (deg) | C32: dMD (ft) | D32: th avg (deg) | E32: dInc (rad) | F32: dAzi (rad) | G32: w_b (lb/ft) | H32: T pick-up (lbf) | I32: T slack-off (lbf) | J32: T rotating (lbf) | K32: Torque (ft-lbf) | L32: F_sin limit (lbf) | M32: Buckling flag | N32: MD_c* | O32: PU_c* | P32: SO_c* | Q32: ROT_c* | R32: TQ_c*
A33: =IF('Directional Survey'!A7="","",'Directional Survey'!A7) | B33: =IF($A33="","",'Directional Survey'!B7) | C33: =IF(OR($A33="",'Directional Survey'!A8=""),"",'Directional Survey'!A8-$A33) | D33: =IF($C33="","",($B33+'Directional Survey'!B8)/2) | E33: =IF($C33="","",RADIANS('Directional Survey'!B8-$B33)) | F33: =IF($C33="","",RADIANS('Directional Survey'!C8-'Directional Survey'!C7)) | G33: =IF($C33="","",$B$27*IF(($A33+$A33+$C33)/2>$B$11-$B$17,$B$16,$B$15)) | H33: =IF($A33="","",IF($C33="",0,$H34+$G33*$C33*COS(RADIANS($D33))+IF(($A33+$C33/2)<=$B$12,$B$18,$B$19)*SQRT(($H34*$F33*SIN(RADIANS($D33)))^2+($H34*$E33+$G33*$C33*SIN(RADIANS($D33)))^2))) | I33: =IF($A33="","",IF($C33="",-$B$20*1000,$I34+$G33*$C33*COS(RADIANS($D33))-IF(($A33+$C33/2)<=$B$12,$B$18,$B$19)*SQRT(($I34*$F33*SIN(RADIANS($D33)))^2+($I34*$E33+$G33*$C33*SIN(RADIANS($D33)))^2))) | J33: =IF($A33="","",IF($C33="",-$B$20*1000,$J34+$G33*$C33*COS(RADIANS($D33)))) | K33: =IF($A33="","",IF($C33="",$B$21,$K34+IF(($A33+$C33/2)<=$B$12,$B$18,$B$19)*SQRT(($J34*$F33*SIN(RADIANS($D33)))^2+($J34*$E33+$G33*$C33*SIN(RADIANS($D33)))^2)*$B$22/24)) | L33: =IF($C33="","",2*SQRT($B$26*$B$28*($G33/12)*SIN(RADIANS(MAX($D33,3)))/(IF($A33<=$B$12,$B$14,$B$13)-$B$24)/2)) | M33: =IF($C33="","",IF($I33<-1.41*$L33,"HELICAL BUCKLING - CHECK",IF($I33<-$L33,"SINUSOIDAL - MARGINAL",""))) | N33: =IF($A33="",NA(),$A33) | O33: =IF($A33="",NA(),$H33/1000) | P33: =IF($A33="",NA(),$I33/1000) | Q33: =IF($A33="",NA(),$J33/1000) | R33: =IF($A33="",NA(),$K33/1000)
A34: =IF('Directional Survey'!A8="","",'Directional Survey'!A8) | B34: =IF($A34="","",'Directional Survey'!B8) | C34: =IF(OR($A34="",'Directional Survey'!A9=""),"",'Directional Survey'!A9-$A34) | D34: =IF($C34="","",($B34+'Directional Survey'!B9)/2) | E34: =IF($C34="","",RADIANS('Directional Survey'!B9-$B34)) | F34: =IF($C34="","",RADIANS('Directional Survey'!C9-'Directional Survey'!C8)) | G34: =IF($C34="","",$B$27*IF(($A34+$A34+$C34)/2>$B$11-$B$17,$B$16,$B$15)) | H34: =IF($A34="","",IF($C34="",0,$H35+$G34*$C34*COS(RADIANS($D34))+IF(($A34+$C34/2)<=$B$12,$B$18,$B$19)*SQRT(($H35*$F34*SIN(RADIANS($D34)))^2+($H35*$E34+$G34*$C34*SIN(RADIANS($D34)))^2))) | I34: =IF($A34="","",IF($C34="",-$B$20*1000,$I35+$G34*$C34*COS(RADIANS($D34))-IF(($A34+$C34/2)<=$B$12,$B$18,$B$19)*SQRT(($I35*$F34*SIN(RADIANS($D34)))^2+($I35*$E34+$G34*$C34*SIN(RADIANS($D34)))^2))) | J34: =IF($A34="","",IF($C34="",-$B$20*1000,$J35+$G34*$C34*COS(RADIANS($D34)))) | K34: =IF($A34="","",IF($C34="",$B$21,$K35+IF(($A34+$C34/2)<=$B$12,$B$18,$B$19)*SQRT(($J35*$F34*SIN(RADIANS($D34)))^2+($J35*$E34+$G34*$C34*SIN(RADIANS($D34)))^2)*$B$22/24)) | L34: =IF($C34="","",2*SQRT($B$26*$B$28*($G34/12)*SIN(RADIANS(MAX($D34,3)))/(IF($A34<=$B$12,$B$14,$B$13)-$B$24)/2)) | M34: =IF($C34="","",IF($I34<-1.41*$L34,"HELICAL BUCKLING - CHECK",IF($I34<-$L34,"SINUSOIDAL - MARGINAL",""))) | N34: =IF($A34="",NA(),$A34) | O34: =IF($A34="",NA(),$H34/1000) | P34: =IF($A34="",NA(),$I34/1000) | Q34: =IF($A34="",NA(),$J34/1000) | R34: =IF($A34="",NA(),$K34/1000)
A35: =IF('Directional Survey'!A9="","",'Directional Survey'!A9) | B35: =IF($A35="","",'Directional Survey'!B9) | C35: =IF(OR($A35="",'Directional Survey'!A10=""),"",'Directional Survey'!A10-$A35) | D35: =IF($C35="","",($B35+'Directional Survey'!B10)/2) | E35: =IF($C35="","",RADIANS('Directional Survey'!B10-$B35)) | F35: =IF($C35="","",RADIANS('Directional Survey'!C10-'Directional Survey'!C9)) | G35: =IF($C35="","",$B$27*IF(($A35+$A35+$C35)/2>$B$11-$B$17,$B$16,$B$15)) | H35: =IF($A35="","",IF($C35="",0,$H36+$G35*$C35*COS(RADIANS($D35))+IF(($A35+$C35/2)<=$B$12,$B$18,$B$19)*SQRT(($H36*$F35*SIN(RADIANS($D35)))^2+($H36*$E35+$G35*$C35*SIN(RADIANS($D35)))^2))) | I35: =IF($A35="","",IF($C35="",-$B$20*1000,$I36+$G35*$C35*COS(RADIANS($D35))-IF(($A35+$C35/2)<=$B$12,$B$18,$B$19)*SQRT(($I36*$F35*SIN(RADIANS($D35)))^2+($I36*$E35+$G35*$C35*SIN(RADIANS($D35)))^2))) | J35: =IF($A35="","",IF($C35="",-$B$20*1000,$J36+$G35*$C35*COS(RADIANS($D35)))) | K35: =IF($A35="","",IF($C35="",$B$21,$K36+IF(($A35+$C35/2)<=$B$12,$B$18,$B$19)*SQRT(($J36*$F35*SIN(RADIANS($D35)))^2+($J36*$E35+$G35*$C35*SIN(RADIANS($D35)))^2)*$B$22/24)) | L35: =IF($C35="","",2*SQRT($B$26*$B$28*($G35/12)*SIN(RADIANS(MAX($D35,3)))/(IF($A35<=$B$12,$B$14,$B$13)-$B$24)/2)) | M35: =IF($C35="","",IF($I35<-1.41*$L35,"HELICAL BUCKLING - CHECK",IF($I35<-$L35,"SINUSOIDAL - MARGINAL",""))) | N35: =IF($A35="",NA(),$A35) | O35: =IF($A35="",NA(),$H35/1000) | P35: =IF($A35="",NA(),$I35/1000) | Q35: =IF($A35="",NA(),$J35/1000) | R35: =IF($A35="",NA(),$K35/1000)
A36: =IF('Directional Survey'!A10="","",'Directional Survey'!A10) | B36: =IF($A36="","",'Directional Survey'!B10) | C36: =IF(OR($A36="",'Directional Survey'!A11=""),"",'Directional Survey'!A11-$A36) | D36: =IF($C36="","",($B36+'Directional Survey'!B11)/2) | E36: =IF($C36="","",RADIANS('Directional Survey'!B11-$B36)) | F36: =IF($C36="","",RADIANS('Directional Survey'!C11-'Directional Survey'!C10)) | G36: =IF($C36="","",$B$27*IF(($A36+$A36+$C36)/2>$B$11-$B$17,$B$16,$B$15)) | H36: =IF($A36="","",IF($C36="",0,$H37+$G36*$C36*COS(RADIANS($D36))+IF(($A36+$C36/2)<=$B$12,$B$18,$B$19)*SQRT(($H37*$F36*SIN(RADIANS($D36)))^2+($H37*$E36+$G36*$C36*SIN(RADIANS($D36)))^2))) | I36: =IF($A36="","",IF($C36="",-$B$20*1000,$I37+$G36*$C36*COS(RADIANS($D36))-IF(($A36+$C36/2)<=$B$12,$B$18,$B$19)*SQRT(($I37*$F36*SIN(RADIANS($D36)))^2+($I37*$E36+$G36*$C36*SIN(RADIANS($D36)))^2))) | J36: =IF($A36="","",IF($C36="",-$B$20*1000,$J37+$G36*$C36*COS(RADIANS($D36)))) | K36: =IF($A36="","",IF($C36="",$B$21,$K37+IF(($A36+$C36/2)<=$B$12,$B$18,$B$19)*SQRT(($J37*$F36*SIN(RADIANS($D36)))^2+($J37*$E36+$G36*$C36*SIN(RADIANS($D36)))^2)*$B$22/24)) | L36: =IF($C36="","",2*SQRT($B$26*$B$28*($G36/12)*SIN(RADIANS(MAX($D36,3)))/(IF($A36<=$B$12,$B$14,$B$13)-$B$24)/2)) | M36: =IF($C36="","",IF($I36<-1.41*$L36,"HELICAL BUCKLING - CHECK",IF($I36<-$L36,"SINUSOIDAL - MARGINAL",""))) | N36: =IF($A36="",NA(),$A36) | O36: =IF($A36="",NA(),$H36/1000) | P36: =IF($A36="",NA(),$I36/1000) | Q36: =IF($A36="",NA(),$J36/1000) | R36: =IF($A36="",NA(),$K36/1000)
A37: =IF('Directional Survey'!A11="","",'Directional Survey'!A11) | B37: =IF($A37="","",'Directional Survey'!B11) | C37: =IF(OR($A37="",'Directional Survey'!A12=""),"",'Directional Survey'!A12-$A37) | D37: =IF($C37="","",($B37+'Directional Survey'!B12)/2) | E37: =IF($C37="","",RADIANS('Directional Survey'!B12-$B37)) | F37: =IF($C37="","",RADIANS('Directional Survey'!C12-'Directional Survey'!C11)) | G37: =IF($C37="","",$B$27*IF(($A37+$A37+$C37)/2>$B$11-$B$17,$B$16,$B$15)) | H37: =IF($A37="","",IF($C37="",0,$H38+$G37*$C37*COS(RADIANS($D37))+IF(($A37+$C37/2)<=$B$12,$B$18,$B$19)*SQRT(($H38*$F37*SIN(RADIANS($D37)))^2+($H38*$E37+$G37*$C37*SIN(RADIANS($D37)))^2))) | I37: =IF($A37="","",IF($C37="",-$B$20*1000,$I38+$G37*$C37*COS(RADIANS($D37))-IF(($A37+$C37/2)<=$B$12,$B$18,$B$19)*SQRT(($I38*$F37*SIN(RADIANS($D37)))^2+($I38*$E37+$G37*$C37*SIN(RADIANS($D37)))^2))) | J37: =IF($A37="","",IF($C37="",-$B$20*1000,$J38+$G37*$C37*COS(RADIANS($D37)))) | K37: =IF($A37="","",IF($C37="",$B$21,$K38+IF(($A37+$C37/2)<=$B$12,$B$18,$B$19)*SQRT(($J38*$F37*SIN(RADIANS($D37)))^2+($J38*$E37+$G37*$C37*SIN(RADIANS($D37)))^2)*$B$22/24)) | L37: =IF($C37="","",2*SQRT($B$26*$B$28*($G37/12)*SIN(RADIANS(MAX($D37,3)))/(IF($A37<=$B$12,$B$14,$B$13)-$B$24)/2)) | M37: =IF($C37="","",IF($I37<-1.41*$L37,"HELICAL BUCKLING - CHECK",IF($I37<-$L37,"SINUSOIDAL - MARGINAL",""))) | N37: =IF($A37="",NA(),$A37) | O37: =IF($A37="",NA(),$H37/1000) | P37: =IF($A37="",NA(),$I37/1000) | Q37: =IF($A37="",NA(),$J37/1000) | R37: =IF($A37="",NA(),$K37/1000)
A38: =IF('Directional Survey'!A12="","",'Directional Survey'!A12) | B38: =IF($A38="","",'Directional Survey'!B12) | C38: =IF(OR($A38="",'Directional Survey'!A13=""),"",'Directional Survey'!A13-$A38) | D38: =IF($C38="","",($B38+'Directional Survey'!B13)/2) | E38: =IF($C38="","",RADIANS('Directional Survey'!B13-$B38)) | F38: =IF($C38="","",RADIANS('Directional Survey'!C13-'Directional Survey'!C12)) | G38: =IF($C38="","",$B$27*IF(($A38+$A38+$C38)/2>$B$11-$B$17,$B$16,$B$15)) | H38: =IF($A38="","",IF($C38="",0,$H39+$G38*$C38*COS(RADIANS($D38))+IF(($A38+$C38/2)<=$B$12,$B$18,$B$19)*SQRT(($H39*$F38*SIN(RADIANS($D38)))^2+($H39*$E38+$G38*$C38*SIN(RADIANS($D38)))^2))) | I38: =IF($A38="","",IF($C38="",-$B$20*1000,$I39+$G38*$C38*COS(RADIANS($D38))-IF(($A38+$C38/2)<=$B$12,$B$18,$B$19)*SQRT(($I39*$F38*SIN(RADIANS($D38)))^2+($I39*$E38+$G38*$C38*SIN(RADIANS($D38)))^2))) | J38: =IF($A38="","",IF($C38="",-$B$20*1000,$J39+$G38*$C38*COS(RADIANS($D38)))) | K38: =IF($A38="","",IF($C38="",$B$21,$K39+IF(($A38+$C38/2)<=$B$12,$B$18,$B$19)*SQRT(($J39*$F38*SIN(RADIANS($D38)))^2+($J39*$E38+$G38*$C38*SIN(RADIANS($D38)))^2)*$B$22/24)) | L38: =IF($C38="","",2*SQRT($B$26*$B$28*($G38/12)*SIN(RADIANS(MAX($D38,3)))/(IF($A38<=$B$12,$B$14,$B$13)-$B$24)/2)) | M38: =IF($C38="","",IF($I38<-1.41*$L38,"HELICAL BUCKLING - CHECK",IF($I38<-$L38,"SINUSOIDAL - MARGINAL",""))) | N38: =IF($A38="",NA(),$A38) | O38: =IF($A38="",NA(),$H38/1000) | P38: =IF($A38="",NA(),$I38/1000) | Q38: =IF($A38="",NA(),$J38/1000) | R38: =IF($A38="",NA(),$K38/1000)
A39: =IF('Directional Survey'!A13="","",'Directional Survey'!A13) | B39: =IF($A39="","",'Directional Survey'!B13) | C39: =IF(OR($A39="",'Directional Survey'!A14=""),"",'Directional Survey'!A14-$A39) | D39: =IF($C39="","",($B39+'Directional Survey'!B14)/2) | E39: =IF($C39="","",RADIANS('Directional Survey'!B14-$B39)) | F39: =IF($C39="","",RADIANS('Directional Survey'!C14-'Directional Survey'!C13)) | G39: =IF($C39="","",$B$27*IF(($A39+$A39+$C39)/2>$B$11-$B$17,$B$16,$B$15)) | H39: =IF($A39="","",IF($C39="",0,$H40+$G39*$C39*COS(RADIANS($D39))+IF(($A39+$C39/2)<=$B$12,$B$18,$B$19)*SQRT(($H40*$F39*SIN(RADIANS($D39)))^2+($H40*$E39+$G39*$C39*SIN(RADIANS($D39)))^2))) | I39: =IF($A39="","",IF($C39="",-$B$20*1000,$I40+$G39*$C39*COS(RADIANS($D39))-IF(($A39+$C39/2)<=$B$12,$B$18,$B$19)*SQRT(($I40*$F39*SIN(RADIANS($D39)))^2+($I40*$E39+$G39*$C39*SIN(RADIANS($D39)))^2))) | J39: =IF($A39="","",IF($C39="",-$B$20*1000,$J40+$G39*$C39*COS(RADIANS($D39)))) | K39: =IF($A39="","",IF($C39="",$B$21,$K40+IF(($A39+$C39/2)<=$B$12,$B$18,$B$19)*SQRT(($J40*$F39*SIN(RADIANS($D39)))^2+($J40*$E39+$G39*$C39*SIN(RADIANS($D39)))^2)*$B$22/24)) | L39: =IF($C39="","",2*SQRT($B$26*$B$28*($G39/12)*SIN(RADIANS(MAX($D39,3)))/(IF($A39<=$B$12,$B$14,$B$13)-$B$24)/2)) | M39: =IF($C39="","",IF($I39<-1.41*$L39,"HELICAL BUCKLING - CHECK",IF($I39<-$L39,"SINUSOIDAL - MARGINAL",""))) | N39: =IF($A39="",NA(),$A39) | O39: =IF($A39="",NA(),$H39/1000) | P39: =IF($A39="",NA(),$I39/1000) | Q39: =IF($A39="",NA(),$J39/1000) | R39: =IF($A39="",NA(),$K39/1000)
A40: =IF('Directional Survey'!A14="","",'Directional Survey'!A14) | B40: =IF($A40="","",'Directional Survey'!B14) | C40: =IF(OR($A40="",'Directional Survey'!A15=""),"",'Directional Survey'!A15-$A40) | D40: =IF($C40="","",($B40+'Directional Survey'!B15)/2) | E40: =IF($C40="","",RADIANS('Directional Survey'!B15-$B40)) | F40: =IF($C40="","",RADIANS('Directional Survey'!C15-'Directional Survey'!C14)) | G40: =IF($C40="","",$B$27*IF(($A40+$A40+$C40)/2>$B$11-$B$17,$B$16,$B$15)) | H40: =IF($A40="","",IF($C40="",0,$H41+$G40*$C40*COS(RADIANS($D40))+IF(($A40+$C40/2)<=$B$12,$B$18,$B$19)*SQRT(($H41*$F40*SIN(RADIANS($D40)))^2+($H41*$E40+$G40*$C40*SIN(RADIANS($D40)))^2))) | I40: =IF($A40="","",IF($C40="",-$B$20*1000,$I41+$G40*$C40*COS(RADIANS($D40))-IF(($A40+$C40/2)<=$B$12,$B$18,$B$19)*SQRT(($I41*$F40*SIN(RADIANS($D40)))^2+($I41*$E40+$G40*$C40*SIN(RADIANS($D40)))^2))) | J40: =IF($A40="","",IF($C40="",-$B$20*1000,$J41+$G40*$C40*COS(RADIANS($D40)))) | K40: =IF($A40="","",IF($C40="",$B$21,$K41+IF(($A40+$C40/2)<=$B$12,$B$18,$B$19)*SQRT(($J41*$F40*SIN(RADIANS($D40)))^2+($J41*$E40+$G40*$C40*SIN(RADIANS($D40)))^2)*$B$22/24)) | L40: =IF($C40="","",2*SQRT($B$26*$B$28*($G40/12)*SIN(RADIANS(MAX($D40,3)))/(IF($A40<=$B$12,$B$14,$B$13)-$B$24)/2)) | M40: =IF($C40="","",IF($I40<-1.41*$L40,"HELICAL BUCKLING - CHECK",IF($I40<-$L40,"SINUSOIDAL - MARGINAL",""))) | N40: =IF($A40="",NA(),$A40) | O40: =IF($A40="",NA(),$H40/1000) | P40: =IF($A40="",NA(),$I40/1000) | Q40: =IF($A40="",NA(),$J40/1000) | R40: =IF($A40="",NA(),$K40/1000)
A41: =IF('Directional Survey'!A15="","",'Directional Survey'!A15) | B41: =IF($A41="","",'Directional Survey'!B15) | C41: =IF(OR($A41="",'Directional Survey'!A16=""),"",'Directional Survey'!A16-$A41) | D41: =IF($C41="","",($B41+'Directional Survey'!B16)/2) | E41: =IF($C41="","",RADIANS('Directional Survey'!B16-$B41)) | F41: =IF($C41="","",RADIANS('Directional Survey'!C16-'Directional Survey'!C15)) | G41: =IF($C41="","",$B$27*IF(($A41+$A41+$C41)/2>$B$11-$B$17,$B$16,$B$15)) | H41: =IF($A41="","",IF($C41="",0,$H42+$G41*$C41*COS(RADIANS($D41))+IF(($A41+$C41/2)<=$B$12,$B$18,$B$19)*SQRT(($H42*$F41*SIN(RADIANS($D41)))^2+($H42*$E41+$G41*$C41*SIN(RADIANS($D41)))^2))) | I41: =IF($A41="","",IF($C41="",-$B$20*1000,$I42+$G41*$C41*COS(RADIANS($D41))-IF(($A41+$C41/2)<=$B$12,$B$18,$B$19)*SQRT(($I42*$F41*SIN(RADIANS($D41)))^2+($I42*$E41+$G41*$C41*SIN(RADIANS($D41)))^2))) | J41: =IF($A41="","",IF($C41="",-$B$20*1000,$J42+$G41*$C41*COS(RADIANS($D41)))) | K41: =IF($A41="","",IF($C41="",$B$21,$K42+IF(($A41+$C41/2)<=$B$12,$B$18,$B$19)*SQRT(($J42*$F41*SIN(RADIANS($D41)))^2+($J42*$E41+$G41*$C41*SIN(RADIANS($D41)))^2)*$B$22/24)) | L41: =IF($C41="","",2*SQRT($B$26*$B$28*($G41/12)*SIN(RADIANS(MAX($D41,3)))/(IF($A41<=$B$12,$B$14,$B$13)-$B$24)/2)) | M41: =IF($C41="","",IF($I41<-1.41*$L41,"HELICAL BUCKLING - CHECK",IF($I41<-$L41,"SINUSOIDAL - MARGINAL",""))) | N41: =IF($A41="",NA(),$A41) | O41: =IF($A41="",NA(),$H41/1000) | P41: =IF($A41="",NA(),$I41/1000) | Q41: =IF($A41="",NA(),$J41/1000) | R41: =IF($A41="",NA(),$K41/1000)
A42: =IF('Directional Survey'!A16="","",'Directional Survey'!A16) | B42: =IF($A42="","",'Directional Survey'!B16) | C42: =IF(OR($A42="",'Directional Survey'!A17=""),"",'Directional Survey'!A17-$A42) | D42: =IF($C42="","",($B42+'Directional Survey'!B17)/2) | E42: =IF($C42="","",RADIANS('Directional Survey'!B17-$B42)) | F42: =IF($C42="","",RADIANS('Directional Survey'!C17-'Directional Survey'!C16)) | G42: =IF($C42="","",$B$27*IF(($A42+$A42+$C42)/2>$B$11-$B$17,$B$16,$B$15)) | H42: =IF($A42="","",IF($C42="",0,$H43+$G42*$C42*COS(RADIANS($D42))+IF(($A42+$C42/2)<=$B$12,$B$18,$B$19)*SQRT(($H43*$F42*SIN(RADIANS($D42)))^2+($H43*$E42+$G42*$C42*SIN(RADIANS($D42)))^2))) | I42: =IF($A42="","",IF($C42="",-$B$20*1000,$I43+$G42*$C42*COS(RADIANS($D42))-IF(($A42+$C42/2)<=$B$12,$B$18,$B$19)*SQRT(($I43*$F42*SIN(RADIANS($D42)))^2+($I43*$E42+$G42*$C42*SIN(RADIANS($D42)))^2))) | J42: =IF($A42="","",IF($C42="",-$B$20*1000,$J43+$G42*$C42*COS(RADIANS($D42)))) | K42: =IF($A42="","",IF($C42="",$B$21,$K43+IF(($A42+$C42/2)<=$B$12,$B$18,$B$19)*SQRT(($J43*$F42*SIN(RADIANS($D42)))^2+($J43*$E42+$G42*$C42*SIN(RADIANS($D42)))^2)*$B$22/24)) | L42: =IF($C42="","",2*SQRT($B$26*$B$28*($G42/12)*SIN(RADIANS(MAX($D42,3)))/(IF($A42<=$B$12,$B$14,$B$13)-$B$24)/2)) | M42: =IF($C42="","",IF($I42<-1.41*$L42,"HELICAL BUCKLING - CHECK",IF($I42<-$L42,"SINUSOIDAL - MARGINAL",""))) | N42: =IF($A42="",NA(),$A42) | O42: =IF($A42="",NA(),$H42/1000) | P42: =IF($A42="",NA(),$I42/1000) | Q42: =IF($A42="",NA(),$J42/1000) | R42: =IF($A42="",NA(),$K42/1000)
A43: =IF('Directional Survey'!A17="","",'Directional Survey'!A17) | B43: =IF($A43="","",'Directional Survey'!B17) | C43: =IF(OR($A43="",'Directional Survey'!A18=""),"",'Directional Survey'!A18-$A43) | D43: =IF($C43="","",($B43+'Directional Survey'!B18)/2) | E43: =IF($C43="","",RADIANS('Directional Survey'!B18-$B43)) | F43: =IF($C43="","",RADIANS('Directional Survey'!C18-'Directional Survey'!C17)) | G43: =IF($C43="","",$B$27*IF(($A43+$A43+$C43)/2>$B$11-$B$17,$B$16,$B$15)) | H43: =IF($A43="","",IF($C43="",0,$H44+$G43*$C43*COS(RADIANS($D43))+IF(($A43+$C43/2)<=$B$12,$B$18,$B$19)*SQRT(($H44*$F43*SIN(RADIANS($D43)))^2+($H44*$E43+$G43*$C43*SIN(RADIANS($D43)))^2))) | I43: =IF($A43="","",IF($C43="",-$B$20*1000,$I44+$G43*$C43*COS(RADIANS($D43))-IF(($A43+$C43/2)<=$B$12,$B$18,$B$19)*SQRT(($I44*$F43*SIN(RADIANS($D43)))^2+($I44*$E43+$G43*$C43*SIN(RADIANS($D43)))^2))) | J43: =IF($A43="","",IF($C43="",-$B$20*1000,$J44+$G43*$C43*COS(RADIANS($D43)))) | K43: =IF($A43="","",IF($C43="",$B$21,$K44+IF(($A43+$C43/2)<=$B$12,$B$18,$B$19)*SQRT(($J44*$F43*SIN(RADIANS($D43)))^2+($J44*$E43+$G43*$C43*SIN(RADIANS($D43)))^2)*$B$22/24)) | L43: =IF($C43="","",2*SQRT($B$26*$B$28*($G43/12)*SIN(RADIANS(MAX($D43,3)))/(IF($A43<=$B$12,$B$14,$B$13)-$B$24)/2)) | M43: =IF($C43="","",IF($I43<-1.41*$L43,"HELICAL BUCKLING - CHECK",IF($I43<-$L43,"SINUSOIDAL - MARGINAL",""))) | N43: =IF($A43="",NA(),$A43) | O43: =IF($A43="",NA(),$H43/1000) | P43: =IF($A43="",NA(),$I43/1000) | Q43: =IF($A43="",NA(),$J43/1000) | R43: =IF($A43="",NA(),$K43/1000)
A44: =IF('Directional Survey'!A18="","",'Directional Survey'!A18) | B44: =IF($A44="","",'Directional Survey'!B18) | C44: =IF(OR($A44="",'Directional Survey'!A19=""),"",'Directional Survey'!A19-$A44) | D44: =IF($C44="","",($B44+'Directional Survey'!B19)/2) | E44: =IF($C44="","",RADIANS('Directional Survey'!B19-$B44)) | F44: =IF($C44="","",RADIANS('Directional Survey'!C19-'Directional Survey'!C18)) | G44: =IF($C44="","",$B$27*IF(($A44+$A44+$C44)/2>$B$11-$B$17,$B$16,$B$15)) | H44: =IF($A44="","",IF($C44="",0,$H45+$G44*$C44*COS(RADIANS($D44))+IF(($A44+$C44/2)<=$B$12,$B$18,$B$19)*SQRT(($H45*$F44*SIN(RADIANS($D44)))^2+($H45*$E44+$G44*$C44*SIN(RADIANS($D44)))^2))) | I44: =IF($A44="","",IF($C44="",-$B$20*1000,$I45+$G44*$C44*COS(RADIANS($D44))-IF(($A44+$C44/2)<=$B$12,$B$18,$B$19)*SQRT(($I45*$F44*SIN(RADIANS($D44)))^2+($I45*$E44+$G44*$C44*SIN(RADIANS($D44)))^2))) | J44: =IF($A44="","",IF($C44="",-$B$20*1000,$J45+$G44*$C44*COS(RADIANS($D44)))) | K44: =IF($A44="","",IF($C44="",$B$21,$K45+IF(($A44+$C44/2)<=$B$12,$B$18,$B$19)*SQRT(($J45*$F44*SIN(RADIANS($D44)))^2+($J45*$E44+$G44*$C44*SIN(RADIANS($D44)))^2)*$B$22/24)) | L44: =IF($C44="","",2*SQRT($B$26*$B$28*($G44/12)*SIN(RADIANS(MAX($D44,3)))/(IF($A44<=$B$12,$B$14,$B$13)-$B$24)/2)) | M44: =IF($C44="","",IF($I44<-1.41*$L44,"HELICAL BUCKLING - CHECK",IF($I44<-$L44,"SINUSOIDAL - MARGINAL",""))) | N44: =IF($A44="",NA(),$A44) | O44: =IF($A44="",NA(),$H44/1000) | P44: =IF($A44="",NA(),$I44/1000) | Q44: =IF($A44="",NA(),$J44/1000) | R44: =IF($A44="",NA(),$K44/1000)
... A131: =IF('Directional Survey'!A105="","",'Directional Survey'!A105) | B131: =IF($A131="","",'Directional Survey'!B105) | C131: =IF(OR($A131="",'Directional Survey'!A106=""),"",'Directional Survey'!A106-$A131) | D131: =IF($C131="","",($B131+'Directional Survey'!B106)/2) | E131: =IF($C131="","",RADIANS('Directional Survey'!B106-$B131)) | F131: =IF($C131="","",RADIANS('Directional Survey'!C106-'Directional Survey'!C105)) | G131: =IF($C131="","",$B$27*IF(($A131+$A131+$C131)/2>$B$11-$B$17,$B$16,$B$15)) | H131: =IF($A131="","",IF($C131="",0,$H132+$G131*$C131*COS(RADIANS($D131))+IF(($A131+$C131/2)<=$B$12,$B$18,$B$19)*SQRT(($H132*$F131*SIN(RADIANS($D131)))^2+($H132*$E131+$G131*$C131*SIN(RADIANS($D131)))^2))) | I131: =IF($A131="","",IF($C131="",-$B$20*1000,$I132+$G131*$C131*COS(RADIANS($D131))-IF(($A131+$C131/2)<=$B$12,$B$18,$B$19)*SQRT(($I132*$F131*SIN(RADIANS($D131)))^2+($I132*$E131+$G131*$C131*SIN(RADIANS($D131)))^2))) | J131: =IF($A131="","",IF($C131="",-$B$20*1000,$J132+$G131*$C131*COS(RADIANS($D131)))) | K131: =IF($A131="","",IF($C131="",$B$21,$K132+IF(($A131+$C131/2)<=$B$12,$B$18,$B$19)*SQRT(($J132*$F131*SIN(RADIANS($D131)))^2+($J132*$E131+$G131*$C131*SIN(RADIANS($D131)))^2)*$B$22/24)) | L131: =IF($C131="","",2*SQRT($B$26*$B$28*($G131/12)*SIN(RADIANS(MAX($D131,3)))/(IF($A131<=$B$12,$B$14,$B$13)-$B$24)/2)) | M131: =IF($C131="","",IF($I131<-1.41*$L131,"HELICAL BUCKLING - CHECK",IF($I131<-$L131,"SINUSOIDAL - MARGINAL",""))) | N131: =IF($A131="",NA(),$A131) | O131: =IF($A131="",NA(),$H131/1000) | P131: =IF($A131="",NA(),$I131/1000) | Q131: =IF($A131="",NA(),$J131/1000) | R131: =IF($A131="",NA(),$K131/1000)
A132: =IF('Directional Survey'!A106="","",'Directional Survey'!A106) | B132: =IF($A132="","",'Directional Survey'!B106) | C132: ="" | G132: =IF($C132="","",$B$27*IF(($A132+$A132+$C132)/2>$B$11-$B$17,$B$16,$B$15)) | H132: =IF($A132="","",IF($C132="",0,$H133+$G132*$C132*COS(RADIANS($D132))+IF(($A132+$C132/2)<=$B$12,$B$18,$B$19)*SQRT(($H133*$F132*SIN(RADIANS($D132)))^2+($H133*$E132+$G132*$C132*SIN(RADIANS($D132)))^2))) | I132: =IF($A132="","",IF($C132="",-$B$20*1000,$I133+$G132*$C132*COS(RADIANS($D132))-IF(($A132+$C132/2)<=$B$12,$B$18,$B$19)*SQRT(($I133*$F132*SIN(RADIANS($D132)))^2+($I133*$E132+$G132*$C132*SIN(RADIANS($D132)))^2))) | J132: =IF($A132="","",IF($C132="",-$B$20*1000,$J133+$G132*$C132*COS(RADIANS($D132)))) | K132: =IF($A132="","",IF($C132="",$B$21,$K133+IF(($A132+$C132/2)<=$B$12,$B$18,$B$19)*SQRT(($J133*$F132*SIN(RADIANS($D132)))^2+($J133*$E132+$G132*$C132*SIN(RADIANS($D132)))^2)*$B$22/24)) | L132: =IF($C132="","",2*SQRT($B$26*$B$28*($G132/12)*SIN(RADIANS(MAX($D132,3)))/(IF($A132<=$B$12,$B$14,$B$13)-$B$24)/2)) | M132: =IF($C132="","",IF($I132<-1.41*$L132,"HELICAL BUCKLING - CHECK",IF($I132<-$L132,"SINUSOIDAL - MARGINAL",""))) | N132: =IF($A132="",NA(),$A132) | O132: =IF($A132="",NA(),$H132/1000) | P132: =IF($A132="",NA(),$I132/1000) | Q132: =IF($A132="",NA(),$J132/1000) | R132: =IF($A132="",NA(),$K132/1000)
A134: Surface Results
A136: Hookloads & Torque | F136: Hookload = string tension at surface + block weight
F137: Compare against measured pick-up/slack-off to calibrate friction factors. Overpull margin vs pipe yield is on the Drill String sheet.
A138: Pick-up hookload | B138: =$H$33/1000+$B$23 | C138: klbf | D138: =IFERROR($B$138*4.448222,NA()) | E138: kN
A139: Slack-off hookload | B139: =$I$33/1000+$B$23 | C139: klbf | D139: =IFERROR($B$139*4.448222,NA()) | E139: kN
A140: Rotating on-bottom hookload | B140: =$J$33/1000+$B$23 | C140: klbf | D140: =IFERROR($B$140*4.448222,NA()) | E140: kN | F140: Rotating case carries WOB at the bit; set WOB to 0 on Well Data for rotating off-bottom.
A141: Surface torque (rotating) | B141: =$K$33 | C141: ft-lbf | D141: =IFERROR($B$141*1.355818,NA()) | E141: N-m
A142: Buckling anywhere in string | B142: =IF(COUNTIF($M$33:$M$132,"*BUCKLING*")>0,"CHECK: helical buckling flagged - reduce WOB or add HWDP",IF(COUNTIF($M$33:$M$132,"*SINUSOIDAL*")>0,"MARGINAL - sinusoidal buckling flagged","OK - no buckling flags"))

Sheet Hole Cleaning
A1: Hole Cleaning - High-Angle Wells
A2: Annular velocity, carrying capacity index, angle-band minimum flow, slip velocity, transport ratio and cuttings concentration
A4: Parameter | B4: Value | C4: Unit | D4: SI Value | E4: SI Unit | F4: Notes / Equation
A6: Annular Velocity & Flow
A8: Annular Velocity | F8: AV [ft/min] = 24.5 x Q [gpm] / (Dh^2 - Dp^2)
F9: Typical minimums: 100-120 ft/min below 35 deg, 150-180 ft/min at 35-65 deg, >= 180 ft/min above 65 deg (with pipe rotation).
A10: Hole diameter (Dh) | B10: =WD_HoleDiam | C10: in | D10: =IFERROR($B$10*25.4,NA()) | E10: mm | F10: Linked to Well Data sheet - overwrite locally if this well differs.
A11: Pipe OD (Dp) | B11: 5 | C11: in | D11: =IFERROR($B$11*25.4,NA()) | E11: mm
A12: Flow rate (Q) | B12: 600 | C12: gpm | D12: =IFERROR($B$12*3.785412,NA()) | E12: L/min
A13: Annular velocity (AV) | B13: =24.5*$B$12/($B$10^2-$B$11^2) | C13: ft/min | D13: =IFERROR($B$13*0.3048,NA()) | E13: m/min
A15: Carrying Capacity Index
A17: Carrying Capacity Index (CCI) | F17: CCI = K x AV x MW / 400000; K = 511^(1-n) x (PV + YP); n = 3.32 x LOG10((2 x PV + YP) / (PV + YP))
F18: AV in ft/min, MW in ppg, K = power-law consistency (eq. cP). CCI >= 1 indicates good hole cleaning.
A19: Mud weight (MW) | B19: =WD_OMW | C19: ppg | D19: =IFERROR($B$19*119.8264,NA()) | E19: kg/m3 | F19: Linked to Well Data sheet - overwrite locally if this well differs.
A20: Plastic viscosity (PV) | B20: =WD_PV | C20: cP | F20: Linked to Well Data sheet - overwrite locally if this well differs.
A21: Yield point (YP) | B21: =WD_YP | F21: lb/100ft2. Linked to Well Data - overwrite locally if needed.
A22: Flow behavior index (n) | B22: =3.32*LOG10((2*$B$20+$B$21)/($B$20+$B$21))
A23: Power-law consistency (K) | B23: =511^(1-$B$22)*($B$20+$B$21) | F23: Equivalent centipoise.
A24: Carrying capacity index (CCI) | B24: =$B$23*$B$13*$B$19/400000
A25: Hole cleaning status | B25: =IF($B$24>=1,"OK - good cleaning",IF($B$24>=0.5,"MARGINAL - increase flow/rheology","CHECK: poor hole cleaning likely"))
A27: Angle-Band Minimum Flow Guidance
A29: Minimum Flow by Angle Band | F29: Qmin [gpm] = AVmin x (Dh^2 - Dp^2) / 24.5
F30: Band minimum AV: < 35 deg -> 120 ft/min; 35 deg and above -> 180 ft/min (top of the 150-180 range in the hardest 35-65 deg band, and the bed-prevention minimum above 65 deg).
A31: Hole angle | B31: 90 | C31: deg | F31: Degrees from vertical.
A32: Angle band guidance | B32: =IF($B$31<35,"OK to clean with AV 100-120 ft/min",IF($B$31<=65,"CHECK: hardest band - avalanche/cuttings bed risk; AV 150-180 ft/min + rotation","CHECK: bed forms unless AV >= 180 ft/min with pipe rotation"))
A33: Minimum recommended AV for band | B33: =IF($B$31<35,120,IF($B$31<=65,180,180)) | C33: ft/min | D33: =IFERROR($B$33*0.3048,NA()) | E33: m/min
A34: Minimum recommended flow rate (Qmin) | B34: =$B$33*($B$10^2-$B$11^2)/24.5 | C34: gpm | D34: =IFERROR($B$34*3.785412,NA()) | E34: L/min
A35: Current flow vs band minimum | B35: =IF($B$12>=$B$34,"OK - flow meets band minimum","INSUFFICIENT flow for this angle band - increase rate")
A37: Slip Velocity & Transport (vertical baseline)
A39: Slip Velocity (Moore-style, turbulent) | F39: Vs [ft/min] = 92.6 x SQRT(Dc x (rho_c - MW) / MW)
F40: Turbulent-regime approximation; Dc in inches, densities in ppg. Vertical-well baseline - above ~65 deg cuttings beds, not slip, control cleaning.
A41: Cutting diameter (Dc) | B41: 0.25 | C41: in | D41: =IFERROR($B$41*25.4,NA()) | E41: mm
A42: Cutting density (rho_c) | B42: 21.7 | C42: ppg | D42: =IFERROR($B$42*119.8264,NA()) | E42: kg/m3 | F42: ~2.6 SG for typical shale/sand cuttings.
A43: Slip velocity (Vs) | B43: =92.6*SQRT($B$41*($B$42-$B$19)/$B$19) | C43: ft/min | D43: =IFERROR($B$43*0.3048,NA()) | E43: m/min
A44: Transport ratio (TR) | B44: =1-$B$43/$B$13 | F44: TR = 1 - Vs/AV. Net upward cuttings velocity fraction.
A45: Transport status | B45: =IF($B$44>0.5,"OK - good transport",IF($B$44>0.3,"MARGINAL - watch cuttings returns","CHECK: increase flow"))
A47: Cuttings Concentration
A49: Annular Cuttings Concentration | F49: Gen [bbl/hr] = ROP x Dh^2 / 1029.4; Conc [%] = 100 x Gen / (Gen + Q x 60/42)
F50: Keep annular cuttings concentration below ~5% to avoid pack-off and ECD spikes.
A51: Rate of penetration (ROP) | B51: 60 | C51: ft/hr | D51: =IFERROR($B$51*0.3048,NA()) | E51: m/hr
A52: Cuttings generation rate | B52: =$B$51*$B$10^2/1029.4 | C52: bbl/hr | D52: =IFERROR($B$52*0.1589873,NA()) | E52: m3/hr
A53: Circulation rate | B53: =$B$12*60/42 | C53: bbl/hr | D53: =IFERROR($B$53*0.1589873,NA()) | E53: m3/hr
A54: Annular cuttings concentration | B54: =100*$B$52/($B$52+$B$53) | F54: Percent by volume, steady state.
A55: Concentration status | B55: =IF($B$54<=4,"OK",IF($B$54<=6,"MARGINAL","CHECK: exceeds 5% guideline - reduce ROP or raise flow"))
A57: Pipe Rotation & Practices
A59: Good Practices - High-Angle Cleaning
A60: Pipe rotation | F60: Rotation >= 120 rpm agitates and disturbs cuttings beds in laterals - the single most effective mechanical aid to cleaning.
A61: Sweeps | F61: Pump sweeps (hi-vis or weighted) have limited value above 65 deg - flow rate and rotation do the work, not viscosity alone.
A62: Before tripping | F62: Circulate 2-3 bottoms-up at full rate with rotation before tripping in high-angle hole.
A63: Monitoring | F63: Monitor shaker returns against the expected cuttings volume (generation rate x circulating time) - a shortfall means a bed is building downhole.

Sheet Trip Speed Schedule
A1: Maximum Trip Speed vs Depth - Surge & Swab Limits
A2: Burkhardt closed-ended clinging + laminar Bingham friction, inverted for pipe speed; running and pulling speed schedule with seconds per stand
A4: Parameter | B4: Value | C4: Unit | D4: SI Value | E4: SI Unit | F4: Notes / Equation
A6: Geometry & Fluid
A8: Annulus Geometry
F9: Closed-ended (float / bullnose / plugged bit) is the worst case and is what the schedule below assumes. Open-ended pipe surges less.
A10: Casing / hole ID (Dc) | B10: =WD_CsgID | C10: in | D10: =IFERROR($B$10*25.4,NA()) | E10: mm | F10: Linked to Well Data. Use the smallest restriction the pipe runs through (casing ID here; overwrite with open-hole size if smaller).
A11: Pipe OD (Dp) | B11: 5 | C11: in | D11: =IFERROR($B$11*25.4,NA()) | E11: mm
A12: Pipe ID | B12: 4.276 | C12: in | D12: =IFERROR($B$12*25.4,NA()) | E12: mm | F12: Reference only - closed-ended assumption ignores the pipe bore.
A13: Clinging factor (K) | B13: =0.45+$B$11^2/($B$10^2-$B$11^2) | F13: Burkhardt closed-ended: Ve = Vp x K, K = 0.45 + Dp^2/(Dc^2-Dp^2).
A15: Mud Properties
A16: Mud weight (MW) | B16: =WD_OMW | C16: ppg | D16: =IFERROR($B$16*119.8264,NA()) | E16: kg/m3 | F16: Linked to Well Data sheet - overwrite locally if this well differs.
A17: Plastic viscosity (PV) | B17: =WD_PV | F17: cP.
A18: Yield point (YP) | B18: =WD_YP | F18: lb/100 ft2.
A20: Pressure Limits
A22: Allowable Surge & Swab | F22: dP_surge_allow = (EMW_frac - MW) x 0.052 x TVD; dP_swab_allow = (MW - EMW_pore) x 0.052 x TVD
F23: Surge side is limited by the frac/loss EMW (running in raises BHP); swab side by the pore + kick-margin EMW (pulling out lowers BHP). The table below evaluates both at each bit depth with L = depth.
A24: Frac / loss limit EMW | B24: =WD_LOT | C24: ppg | D24: =IFERROR($B$24*119.8264,NA()) | E24: kg/m3 | F24: Linked to the LOT/FIT EMW - overwrite with a loss-zone EMW if lower.
A25: Pore / swab limit EMW | B25: 12 | C25: ppg | D25: =IFERROR($B$25*119.8264,NA()) | E25: kg/m3 | F25: Pore pressure EMW plus kick margin on the swab side. If this is at/above MW, tripping out swabs the well in - raise MW first.
A26: TVD at TD (reference) | B26: =WD_TVD | C26: ft | D26: =IFERROR($B$26*0.3048,NA()) | E26: m | F26: Linked to Well Data sheet - overwrite locally if this well differs.
A27: Rig handling speed cap | B27: 400 | C27: ft/min | D27: =IFERROR($B$27*0.3048,NA()) | E27: m/min | F27: Practical block-speed/handling ceiling; the schedule shows MIN(cap, hydraulic limit). Laminar surge model loses validity at very high speeds anyway.
A28: Surge margin (frac EMW - MW) | B28: =$B$24-$B$16 | C28: ppg | D28: =IFERROR($B$28*119.8264,NA()) | E28: kg/m3
A29: Swab margin (MW - swab limit) | B29: =$B$16-$B$25 | C29: ppg | D29: =IFERROR($B$29*119.8264,NA()) | E29: kg/m3
A30: Surge status | B30: =IF($B$28>=0.5,"OK - surge margin adequate",IF($B$28>0,"MARGINAL - thin surge margin - run slowly","DO NOT run in - MW at/above frac limit"))
A31: Swab status | B31: =IF($B$29>=0.3,"OK - swab margin adequate",IF($B$29>0,"MARGINAL - thin swab margin - pull slowly","DO NOT trip out on this mud - MW at/below swab limit; raise MW first"))
A33: Trip Speed Schedule - enter bit depths (yellow, MD = TVD assumed; use survey TVDs on deviated wells)
A34: Bit depth (ft) | B34: Allow surge (psi) | C34: Allow swab (psi) | D34: Max run (ft/min) | E34: Max pull (ft/min) | F34: s/stand run | G34: s/stand pull | H34: RUNh* | I34: PULLh* | J34: DEPTHh*
A35: 1000 | B35: =IF($A35="","",MAX(0,($B$24-$B$16)*0.052*$A35)) | C35: =IF($A35="","",MAX(0,($B$16-$B$25)*0.052*$A35)) | D35: =IF($A35="","",MIN($B$27,MAX(0,(B35-$A35*$B$18/(200*($B$10-$B$11)))*60000*($B$10-$B$11)^2/($A35*$B$17*$B$13)))) | E35: =IF($A35="","",MIN($B$27,MAX(0,(C35-$A35*$B$18/(200*($B$10-$B$11)))*60000*($B$10-$B$11)^2/($A35*$B$17*$B$13)))) | F35: =IF($A35="","",IF(D35<=0,"-",93/D35*60)) | G35: =IF($A35="","",IF(E35<=0,"-",93/E35*60)) | H35: =IF($A35="",NA(),D35) | I35: =IF($A35="",NA(),E35) | J35: =IF($A35="",NA(),$A35)
A36: 2000 | B36: =IF($A36="","",MAX(0,($B$24-$B$16)*0.052*$A36)) | C36: =IF($A36="","",MAX(0,($B$16-$B$25)*0.052*$A36)) | D36: =IF($A36="","",MIN($B$27,MAX(0,(B36-$A36*$B$18/(200*($B$10-$B$11)))*60000*($B$10-$B$11)^2/($A36*$B$17*$B$13)))) | E36: =IF($A36="","",MIN($B$27,MAX(0,(C36-$A36*$B$18/(200*($B$10-$B$11)))*60000*($B$10-$B$11)^2/($A36*$B$17*$B$13)))) | F36: =IF($A36="","",IF(D36<=0,"-",93/D36*60)) | G36: =IF($A36="","",IF(E36<=0,"-",93/E36*60)) | H36: =IF($A36="",NA(),D36) | I36: =IF($A36="",NA(),E36) | J36: =IF($A36="",NA(),$A36)
A37: 3000 | B37: =IF($A37="","",MAX(0,($B$24-$B$16)*0.052*$A37)) | C37: =IF($A37="","",MAX(0,($B$16-$B$25)*0.052*$A37)) | D37: =IF($A37="","",MIN($B$27,MAX(0,(B37-$A37*$B$18/(200*($B$10-$B$11)))*60000*($B$10-$B$11)^2/($A37*$B$17*$B$13)))) | E37: =IF($A37="","",MIN($B$27,MAX(0,(C37-$A37*$B$18/(200*($B$10-$B$11)))*60000*($B$10-$B$11)^2/($A37*$B$17*$B$13)))) | F37: =IF($A37="","",IF(D37<=0,"-",93/D37*60)) | G37: =IF($A37="","",IF(E37<=0,"-",93/E37*60)) | H37: =IF($A37="",NA(),D37) | I37: =IF($A37="",NA(),E37) | J37: =IF($A37="",NA(),$A37)
A38: 4000 | B38: =IF($A38="","",MAX(0,($B$24-$B$16)*0.052*$A38)) | C38: =IF($A38="","",MAX(0,($B$16-$B$25)*0.052*$A38)) | D38: =IF($A38="","",MIN($B$27,MAX(0,(B38-$A38*$B$18/(200*($B$10-$B$11)))*60000*($B$10-$B$11)^2/($A38*$B$17*$B$13)))) | E38: =IF($A38="","",MIN($B$27,MAX(0,(C38-$A38*$B$18/(200*($B$10-$B$11)))*60000*($B$10-$B$11)^2/($A38*$B$17*$B$13)))) | F38: =IF($A38="","",IF(D38<=0,"-",93/D38*60)) | G38: =IF($A38="","",IF(E38<=0,"-",93/E38*60)) | H38: =IF($A38="",NA(),D38) | I38: =IF($A38="",NA(),E38) | J38: =IF($A38="",NA(),$A38)
A39: 5000 | B39: =IF($A39="","",MAX(0,($B$24-$B$16)*0.052*$A39)) | C39: =IF($A39="","",MAX(0,($B$16-$B$25)*0.052*$A39)) | D39: =IF($A39="","",MIN($B$27,MAX(0,(B39-$A39*$B$18/(200*($B$10-$B$11)))*60000*($B$10-$B$11)^2/($A39*$B$17*$B$13)))) | E39: =IF($A39="","",MIN($B$27,MAX(0,(C39-$A39*$B$18/(200*($B$10-$B$11)))*60000*($B$10-$B$11)^2/($A39*$B$17*$B$13)))) | F39: =IF($A39="","",IF(D39<=0,"-",93/D39*60)) | G39: =IF($A39="","",IF(E39<=0,"-",93/E39*60)) | H39: =IF($A39="",NA(),D39) | I39: =IF($A39="",NA(),E39) | J39: =IF($A39="",NA(),$A39)
A40: 6000 | B40: =IF($A40="","",MAX(0,($B$24-$B$16)*0.052*$A40)) | C40: =IF($A40="","",MAX(0,($B$16-$B$25)*0.052*$A40)) | D40: =IF($A40="","",MIN($B$27,MAX(0,(B40-$A40*$B$18/(200*($B$10-$B$11)))*60000*($B$10-$B$11)^2/($A40*$B$17*$B$13)))) | E40: =IF($A40="","",MIN($B$27,MAX(0,(C40-$A40*$B$18/(200*($B$10-$B$11)))*60000*($B$10-$B$11)^2/($A40*$B$17*$B$13)))) | F40: =IF($A40="","",IF(D40<=0,"-",93/D40*60)) | G40: =IF($A40="","",IF(E40<=0,"-",93/E40*60)) | H40: =IF($A40="",NA(),D40) | I40: =IF($A40="",NA(),E40) | J40: =IF($A40="",NA(),$A40)
A41: 7000 | B41: =IF($A41="","",MAX(0,($B$24-$B$16)*0.052*$A41)) | C41: =IF($A41="","",MAX(0,($B$16-$B$25)*0.052*$A41)) | D41: =IF($A41="","",MIN($B$27,MAX(0,(B41-$A41*$B$18/(200*($B$10-$B$11)))*60000*($B$10-$B$11)^2/($A41*$B$17*$B$13)))) | E41: =IF($A41="","",MIN($B$27,MAX(0,(C41-$A41*$B$18/(200*($B$10-$B$11)))*60000*($B$10-$B$11)^2/($A41*$B$17*$B$13)))) | F41: =IF($A41="","",IF(D41<=0,"-",93/D41*60)) | G41: =IF($A41="","",IF(E41<=0,"-",93/E41*60)) | H41: =IF($A41="",NA(),D41) | I41: =IF($A41="",NA(),E41) | J41: =IF($A41="",NA(),$A41)
A42: 8000 | B42: =IF($A42="","",MAX(0,($B$24-$B$16)*0.052*$A42)) | C42: =IF($A42="","",MAX(0,($B$16-$B$25)*0.052*$A42)) | D42: =IF($A42="","",MIN($B$27,MAX(0,(B42-$A42*$B$18/(200*($B$10-$B$11)))*60000*($B$10-$B$11)^2/($A42*$B$17*$B$13)))) | E42: =IF($A42="","",MIN($B$27,MAX(0,(C42-$A42*$B$18/(200*($B$10-$B$11)))*60000*($B$10-$B$11)^2/($A42*$B$17*$B$13)))) | F42: =IF($A42="","",IF(D42<=0,"-",93/D42*60)) | G42: =IF($A42="","",IF(E42<=0,"-",93/E42*60)) | H42: =IF($A42="",NA(),D42) | I42: =IF($A42="",NA(),E42) | J42: =IF($A42="",NA(),$A42)
A43: 9000 | B43: =IF($A43="","",MAX(0,($B$24-$B$16)*0.052*$A43)) | C43: =IF($A43="","",MAX(0,($B$16-$B$25)*0.052*$A43)) | D43: =IF($A43="","",MIN($B$27,MAX(0,(B43-$A43*$B$18/(200*($B$10-$B$11)))*60000*($B$10-$B$11)^2/($A43*$B$17*$B$13)))) | E43: =IF($A43="","",MIN($B$27,MAX(0,(C43-$A43*$B$18/(200*($B$10-$B$11)))*60000*($B$10-$B$11)^2/($A43*$B$17*$B$13)))) | F43: =IF($A43="","",IF(D43<=0,"-",93/D43*60)) | G43: =IF($A43="","",IF(E43<=0,"-",93/E43*60)) | H43: =IF($A43="",NA(),D43) | I43: =IF($A43="",NA(),E43) | J43: =IF($A43="",NA(),$A43)
A44: 10000 | B44: =IF($A44="","",MAX(0,($B$24-$B$16)*0.052*$A44)) | C44: =IF($A44="","",MAX(0,($B$16-$B$25)*0.052*$A44)) | D44: =IF($A44="","",MIN($B$27,MAX(0,(B44-$A44*$B$18/(200*($B$10-$B$11)))*60000*($B$10-$B$11)^2/($A44*$B$17*$B$13)))) | E44: =IF($A44="","",MIN($B$27,MAX(0,(C44-$A44*$B$18/(200*($B$10-$B$11)))*60000*($B$10-$B$11)^2/($A44*$B$17*$B$13)))) | F44: =IF($A44="","",IF(D44<=0,"-",93/D44*60)) | G44: =IF($A44="","",IF(E44<=0,"-",93/E44*60)) | H44: =IF($A44="",NA(),D44) | I44: =IF($A44="",NA(),E44) | J44: =IF($A44="",NA(),$A44)
A45: 11000 | B45: =IF($A45="","",MAX(0,($B$24-$B$16)*0.052*$A45)) | C45: =IF($A45="","",MAX(0,($B$16-$B$25)*0.052*$A45)) | D45: =IF($A45="","",MIN($B$27,MAX(0,(B45-$A45*$B$18/(200*($B$10-$B$11)))*60000*($B$10-$B$11)^2/($A45*$B$17*$B$13)))) | E45: =IF($A45="","",MIN($B$27,MAX(0,(C45-$A45*$B$18/(200*($B$10-$B$11)))*60000*($B$10-$B$11)^2/($A45*$B$17*$B$13)))) | F45: =IF($A45="","",IF(D45<=0,"-",93/D45*60)) | G45: =IF($A45="","",IF(E45<=0,"-",93/E45*60)) | H45: =IF($A45="",NA(),D45) | I45: =IF($A45="",NA(),E45) | J45: =IF($A45="",NA(),$A45)
A46: 12000 | B46: =IF($A46="","",MAX(0,($B$24-$B$16)*0.052*$A46)) | C46: =IF($A46="","",MAX(0,($B$16-$B$25)*0.052*$A46)) | D46: =IF($A46="","",MIN($B$27,MAX(0,(B46-$A46*$B$18/(200*($B$10-$B$11)))*60000*($B$10-$B$11)^2/($A46*$B$17*$B$13)))) | E46: =IF($A46="","",MIN($B$27,MAX(0,(C46-$A46*$B$18/(200*($B$10-$B$11)))*60000*($B$10-$B$11)^2/($A46*$B$17*$B$13)))) | F46: =IF($A46="","",IF(D46<=0,"-",93/D46*60)) | G46: =IF($A46="","",IF(E46<=0,"-",93/E46*60)) | H46: =IF($A46="",NA(),D46) | I46: =IF($A46="",NA(),E46) | J46: =IF($A46="",NA(),$A46)
A47: * helper columns H-J feed the speed chart - do not edit. #N/A on unused rows by design (chart gaps).
A48: Crews should round speeds DOWN and time the fastest stand, not the average - peak speed within a stand can be 1.5-2x the average.
A49: Closed-ended (float/bullnose) is shown - worst case. Open-ended pipe displaces less fluid and allows faster tripping; a speed of 0 or '-' means the margin is gone at that depth on this mud.

Sheet Pressure Window
A1: Pore & Fracture Pressure - Drilling Window
A2: Eaton pore pressure, Eaton / Hubbert & Willis fracture gradient with LOT calibration, depth-table drilling window plot and shoe kick tolerance
A4: Parameter | B4: Value | C4: Unit | D4: SI Value | E4: SI Unit | F4: Notes / Equation
A6: Overburden & Eaton Pore Pressure
A8: Eaton Pore Pressure from Trend Ratio | F8: PP_grad = OBG - (OBG - PN) x R^n
F9: R = dt_normal/dt_observed (sonic form) or R_observed/R_normal (resistivity form) - both arranged so R < 1 means overpressure. n = 3.0 is the classic Eaton exponent for both forms (use ~1.2 for the d-exponent form).
A10: Depth of interest TVD | B10: =WD_TVD | C10: ft | D10: =IFERROR($B$10*0.3048,NA()) | E10: m | F10: Linked to Well Data sheet - overwrite locally if this well differs.
A11: Overburden gradient (OBG) | B11: 1 | C11: psi/ft | D11: =IFERROR($B$11*22.62059,NA()) | E11: kPa/m | F11: 1.0 psi/ft is a common onshore default; integrate density logs offshore.
A12: Normal pore gradient (PN) | B12: 0.465 | C12: psi/ft | D12: =IFERROR($B$12*22.62059,NA()) | E12: kPa/m
A13: Eaton exponent (n) | B13: 3
A14: Observed/normal trend ratio (R) | B14: 0.9
A15: Pore pressure gradient | B15: =$B$11-($B$11-$B$12)*$B$14^$B$13 | C15: psi/ft | D15: =IFERROR($B$15*22.62059,NA()) | E15: kPa/m
A16: Pore pressure at depth | B16: =$B$15*$B$10 | C16: psi | D16: =IFERROR($B$16*6.894757,NA()) | E16: kPa
A17: Pore pressure EMW | B17: =$B$15/0.052 | C17: ppg | D17: =IFERROR($B$17*119.8264,NA()) | E17: kg/m3
A19: Fracture Gradient
A21: Fracture Gradient (Eaton / Hubbert & Willis) | F21: Eaton: FG = (PR/(1-PR)) x (OBG - PP_grad) + PP_grad; H&W minimum: FG_min = (OBG + 2 x PP_grad)/3
F22: Both are estimates - always calibrate against LOT/FIT or minifrac data from the actual area before relying on the window.
A23: Poisson ratio (PR) | B23: 0.25 | F23: Typical 0.20-0.30 for shale; higher for unconsolidated sediments.
A24: Eaton fracture gradient | B24: =($B$23/(1-$B$23))*($B$11-$B$15)+$B$15 | C24: psi/ft | D24: =IFERROR($B$24*22.62059,NA()) | E24: kPa/m
A25: Eaton fracture EMW | B25: =$B$24/0.052 | C25: ppg | D25: =IFERROR($B$25*119.8264,NA()) | E25: kg/m3
A26: Hubbert & Willis minimum FG | B26: =($B$11+2*$B$15)/3 | C26: psi/ft | D26: =IFERROR($B$26*22.62059,NA()) | E26: kPa/m
A27: Hubbert & Willis minimum EMW | B27: =$B$26/0.052 | C27: ppg | D27: =IFERROR($B$27*119.8264,NA()) | E27: kg/m3
A28: LOT / FIT EMW (measured) | B28: =WD_LOT | C28: ppg | D28: =IFERROR($B$28*119.8264,NA()) | E28: kg/m3 | F28: Linked to Well Data sheet - overwrite locally if this well differs.
A29: Calibration check | B29: =IF(ABS($B$28-$B$25)<=0.5,"OK - matches LOT within 0.5 ppg","CHECK: calibrate to LOT/minifrac")
A31: Drilling Window vs Depth
A33: Current Mud & ECD (for the window plot) | F33: ECD = MW + APL / (0.052 x TVD)
F34: APL at full circulating rate. A constant APL overstates ECD at shallow depths - refine per-section on the Hydraulics sheet.
A35: Current mud weight (MW) | B35: =WD_OMW | C35: ppg | D35: =IFERROR($B$35*119.8264,NA()) | E35: kg/m3 | F35: Linked to Well Data sheet - overwrite locally if this well differs.
A36: Annular pressure loss (APL) | B36: 200 | C36: psi | D36: =IFERROR($B$36*6.894757,NA()) | E36: kPa
A38: Depth Table - enter TVD / pore EMW / frac EMW per row (yellow); MW and ECD compute from the block above
A39: TVD (ft) | B39: Pore EMW (ppg) | C39: Frac EMW (ppg) | D39: MW (ppg) | E39: ECD (ppg) | G39: TVDh* | H39: POREh* | I39: FRACh* | J39: MWh* | K39: ECDh*
A40: 1000 | B40: 8.9 | C40: 12 | D40: =IF($A40="","",$B$35) | E40: =IF($A40="","",$B$35+$B$36/(0.052*$A40)) | G40: =IF($A40="",NA(),$A40) | H40: =IF(OR($A40="",$B40=""),NA(),$B40) | I40: =IF(OR($A40="",$C40=""),NA(),$C40) | J40: =IF($A40="",NA(),D40) | K40: =IF($A40="",NA(),E40)
A41: 1500 | B41: 8.9 | C41: 12.4 | D41: =IF($A41="","",$B$35) | E41: =IF($A41="","",$B$35+$B$36/(0.052*$A41)) | G41: =IF($A41="",NA(),$A41) | H41: =IF(OR($A41="",$B41=""),NA(),$B41) | I41: =IF(OR($A41="",$C41=""),NA(),$C41) | J41: =IF($A41="",NA(),D41) | K41: =IF($A41="",NA(),E41)
A42: 2000 | B42: 8.9 | C42: 12.8 | D42: =IF($A42="","",$B$35) | E42: =IF($A42="","",$B$35+$B$36/(0.052*$A42)) | G42: =IF($A42="",NA(),$A42) | H42: =IF(OR($A42="",$B42=""),NA(),$B42) | I42: =IF(OR($A42="",$C42=""),NA(),$C42) | J42: =IF($A42="",NA(),D42) | K42: =IF($A42="",NA(),E42)
A43: 2500 | B43: 8.9 | C43: 13.1 | D43: =IF($A43="","",$B$35) | E43: =IF($A43="","",$B$35+$B$36/(0.052*$A43)) | G43: =IF($A43="",NA(),$A43) | H43: =IF(OR($A43="",$B43=""),NA(),$B43) | I43: =IF(OR($A43="",$C43=""),NA(),$C43) | J43: =IF($A43="",NA(),D43) | K43: =IF($A43="",NA(),E43)
A44: 3000 | B44: 9 | C44: 13.4 | D44: =IF($A44="","",$B$35) | E44: =IF($A44="","",$B$35+$B$36/(0.052*$A44)) | G44: =IF($A44="",NA(),$A44) | H44: =IF(OR($A44="",$B44=""),NA(),$B44) | I44: =IF(OR($A44="",$C44=""),NA(),$C44) | J44: =IF($A44="",NA(),D44) | K44: =IF($A44="",NA(),E44)
A45: 3500 | B45: 9.2 | C45: 13.7 | D45: =IF($A45="","",$B$35) | E45: =IF($A45="","",$B$35+$B$36/(0.052*$A45)) | G45: =IF($A45="",NA(),$A45) | H45: =IF(OR($A45="",$B45=""),NA(),$B45) | I45: =IF(OR($A45="",$C45=""),NA(),$C45) | J45: =IF($A45="",NA(),D45) | K45: =IF($A45="",NA(),E45)
A46: 4000 | B46: 9.6 | C46: 14 | D46: =IF($A46="","",$B$35) | E46: =IF($A46="","",$B$35+$B$36/(0.052*$A46)) | G46: =IF($A46="",NA(),$A46) | H46: =IF(OR($A46="",$B46=""),NA(),$B46) | I46: =IF(OR($A46="",$C46=""),NA(),$C46) | J46: =IF($A46="",NA(),D46) | K46: =IF($A46="",NA(),E46)
A47: 4250 | B47: 10.2 | C47: 14.2 | D47: =IF($A47="","",$B$35) | E47: =IF($A47="","",$B$35+$B$36/(0.052*$A47)) | G47: =IF($A47="",NA(),$A47) | H47: =IF(OR($A47="",$B47=""),NA(),$B47) | I47: =IF(OR($A47="",$C47=""),NA(),$C47) | J47: =IF($A47="",NA(),D47) | K47: =IF($A47="",NA(),E47)
A48: 4500 | B48: 11 | C48: 14.4 | D48: =IF($A48="","",$B$35) | E48: =IF($A48="","",$B$35+$B$36/(0.052*$A48)) | G48: =IF($A48="",NA(),$A48) | H48: =IF(OR($A48="",$B48=""),NA(),$B48) | I48: =IF(OR($A48="",$C48=""),NA(),$C48) | J48: =IF($A48="",NA(),D48) | K48: =IF($A48="",NA(),E48)
A49: 4750 | B49: 11.8 | C49: 14.6 | D49: =IF($A49="","",$B$35) | E49: =IF($A49="","",$B$35+$B$36/(0.052*$A49)) | G49: =IF($A49="",NA(),$A49) | H49: =IF(OR($A49="",$B49=""),NA(),$B49) | I49: =IF(OR($A49="",$C49=""),NA(),$C49) | J49: =IF($A49="",NA(),D49) | K49: =IF($A49="",NA(),E49)
A50: 5000 | B50: 12.6 | C50: 14.8 | D50: =IF($A50="","",$B$35) | E50: =IF($A50="","",$B$35+$B$36/(0.052*$A50)) | G50: =IF($A50="",NA(),$A50) | H50: =IF(OR($A50="",$B50=""),NA(),$B50) | I50: =IF(OR($A50="",$C50=""),NA(),$C50) | J50: =IF($A50="",NA(),D50) | K50: =IF($A50="",NA(),E50)
A51: 5200 | B51: 13.2 | C51: 15 | D51: =IF($A51="","",$B$35) | E51: =IF($A51="","",$B$35+$B$36/(0.052*$A51)) | G51: =IF($A51="",NA(),$A51) | H51: =IF(OR($A51="",$B51=""),NA(),$B51) | I51: =IF(OR($A51="",$C51=""),NA(),$C51) | J51: =IF($A51="",NA(),D51) | K51: =IF($A51="",NA(),E51)
... A54: 5573 | B54: 14.2 | C54: 15.2 | D54: =IF($A54="","",$B$35) | E54: =IF($A54="","",$B$35+$B$36/(0.052*$A54)) | G54: =IF($A54="",NA(),$A54) | H54: =IF(OR($A54="",$B54=""),NA(),$B54) | I54: =IF(OR($A54="",$C54=""),NA(),$C54) | J54: =IF($A54="",NA(),D54) | K54: =IF($A54="",NA(),E54)
A55: * helper columns G-K feed the Drilling Window chart - do not edit. They show #N/A on unused rows by design (chart gaps).
A57: Kick Tolerance at Current Shoe
A59: Kick Margin at the Shoe | F59: Margin EMW = LOT EMW - MAX(pore EMW at TD, current MW)
F60: Simple shoe-strength margin: what the shoe can hold above the heavier of the pore pressure EMW and the current mud. For a full kick-volume tolerance use the Well Control sheet.
A61: LOT / FIT EMW at shoe | B61: =WD_LOT | C61: ppg | D61: =IFERROR($B$61*119.8264,NA()) | E61: kg/m3 | F61: Linked to Well Data sheet - overwrite locally if this well differs.
A62: Current mud weight | B62: =WD_OMW | C62: ppg | D62: =IFERROR($B$62*119.8264,NA()) | E62: kg/m3 | F62: Linked to Well Data sheet - overwrite locally if this well differs.
A63: Casing shoe TVD | B63: =WD_ShoeTVD | C63: ft | D63: =IFERROR($B$63*0.3048,NA()) | E63: m | F63: Linked to Well Data sheet - overwrite locally if this well differs.
A64: Well TD TVD | B64: =WD_TVD | C64: ft | D64: =IFERROR($B$64*0.3048,NA()) | E64: m | F64: Linked to Well Data sheet - overwrite locally if this well differs.
A65: Pore pressure EMW at TD | B65: 14.3 | C65: ppg | D65: =IFERROR($B$65*119.8264,NA()) | E65: kg/m3 | F65: Use the Eaton estimate above, calibrated to any kicks/connection gas.
A66: Open hole below shoe (TVD) | B66: =$B$64-$B$63 | C66: ft | D66: =IFERROR($B$66*0.3048,NA()) | E66: m | F66: 0 ft is normal for a horizontal well with the shoe at reservoir TVD.
A67: Kick margin EMW at shoe | B67: =$B$61-MAX($B$65,$B$62) | C67: ppg | D67: =IFERROR($B$67*119.8264,NA()) | E67: kg/m3
A68: Margin as pressure at shoe | B68: =0.052*$B$67*$B$63 | C68: psi | D68: =IFERROR($B$68*6.894757,NA()) | E68: kPa
A69: Status | B69: =IF($B$67>=0.5,"OK - kick margin adequate",IF($B$67>0,"MARGINAL - thin kick margin at shoe","CHECK: no kick margin - shoe cannot hold a kick on this mud"))

Sheet Log Interpretation
A1: Open-Hole Log Interpretation - Quick-Look Petrophysics
A2: Vsh from GR, density/neutron/sonic porosity, Archie Sw, Rw from SP, Timur permeability, net pay cutoffs and a 25-point log data table
A4: Parameter | B4: Value | C4: Unit | D4: SI Value | E4: SI Unit | F4: Notes / Equation
A6: Single-Point Petrophysics
A8: Shale Volume from Gamma Ray | F8: IGR = (GR - GR_clean)/(GR_shale - GR_clean); Vsh(Larionov Tertiary) = 0.083 x (2^(3.7 x IGR) - 1); Vsh(Larionov older) = 0.33 x (2^(2 x IGR) - 1)
F9: Pick GR_clean in the cleanest sand and GR_shale in a thick shale on the same log run.
A10: Gamma ray reading (GR) | B10: 45 | C10: API
A11: Clean sand baseline (GR_clean) | B11: 20 | C11: API
A12: Shale baseline (GR_shale) | B12: 120 | C12: API
A13: Gamma ray index (IGR) | B13: =($B$10-$B$11)/($B$12-$B$11)
A14: Vsh - linear (Vsh = IGR) | B14: =$B$13 | F14: Linear index overstates Vsh in most rocks - use as an upper bound.
A15: Vsh - Larionov Tertiary | B15: =0.083*(2^(3.7*$B$13)-1) | F15: Larionov (1969) Tertiary (unconsolidated) rocks - use for young clastics (Gulf Coast type).
A16: Vsh - Larionov older rocks | B16: =0.33*(2^(2*$B$13)-1) | F16: Larionov older (consolidated, pre-Tertiary) rocks. Both curves reduce the linear IGR; pick the one matching rock age/compaction.
A18: Density Porosity | F18: PHID = (rho_ma - rho_b) / (rho_ma - rho_f)
F19: Matrix density 2.65 g/cc sandstone, 2.71 limestone, 2.87 dolomite. Fluid density 1.0 fresh filtrate, ~1.1 salt filtrate.
A20: Bulk density log (RHOB) | B20: 2.35 | F20: g/cc.
A21: Matrix density (rho_ma) | B21: 2.65 | F21: g/cc - 2.65 sandstone (default), 2.71 limestone.
A22: Fluid density (rho_f) | B22: 1 | F22: g/cc - mud filtrate in the flushed zone.
A23: Density porosity (PHID) | B23: =($B$21-$B$20)/($B$21-$B$22) | C23: v/v
A25: Neutron-Density & Gas Flag | F25: PHIND = (PHID + NPHI)/2; gas flag when PHID - NPHI > 0.04
F26: On sandstone-scaled logs in a gas zone the density curve reads high porosity and the neutron reads low (crossover, PHID >> NPHI). Convention here: positive PHID - NPHI beyond 0.04 v/v flags likely gas effect.
A27: Neutron porosity (NPHI) | B27: 0.12 | C27: v/v | F27: Sandstone matrix scale, environmentally corrected.
A28: Neutron-density porosity (PHIND) | B28: =($B$23+$B$27)/2 | C28: v/v | F28: Simple average; use SQRT((PHID^2+NPHI^2)/2) in gas zones.
A29: Gas crossover status | B29: =IF($B$23-$B$27>0.04,"CHECK: N-D crossover - gas effect likely (PHID >> NPHI)","OK - no significant gas crossover")
A31: Sonic Porosity (Wyllie) | F31: PHIS = (DT - DT_ma) / (DT_f - DT_ma); corrected = PHIS / Cp
F32: Wyllie time-average (1956) - compacted, water-filled clean rock. DT_ma: 55.5 us/ft sandstone, 47.5 limestone, 43.5 dolomite; DT_f 189 us/ft fresh mud.
A33: Sonic transit time (DT) | B33: 75 | F33: us/ft.
A34: Matrix transit time (DT_ma) | B34: 55.5 | F34: us/ft - 55.5 sandstone (default).
A35: Fluid transit time (DT_f) | B35: 189 | F35: us/ft.
A36: Sonic porosity (PHIS) | B36: =($B$33-$B$34)/($B$35-$B$34) | C36: v/v
A37: Compaction correction factor (Cp) | B37: 1 | F37: Divide PHIS by Cp > 1 in uncompacted sands (Cp ~ DT_shale x C / 100, typically 1.0-1.3 where shale DT > 100 us/ft).
A38: Sonic porosity, compaction corrected | B38: =$B$36/$B$37 | C38: v/v
A40: Effective Porosity | F40: PHIE = PHIND x (1 - Vsh)
F41: Shale-corrected total porosity; uses the Larionov Tertiary Vsh and neutron-density porosity from the blocks above.
A42: Effective porosity (PHIE) | B42: =$B$28*(1-$B$15) | C42: v/v
A44: Water Saturation (Archie) | F44: Sw = ( (a x Rw) / (PHI^m x Rt) )^(1/n)
F45: Archie (1942) - clean (shale-free) formations. Defaults a = 1, m = 2, n = 2 (carbonate/consolidated sand); a = 0.62, m = 2.15 (Humble) for unconsolidated sands. For shaly sands use Simandoux or dual-water instead - Archie overstates Sw when clay conductivity is significant.
A46: Formation water resistivity (Rw) | B46: 0.05 | C46: ohm-m
A47: True formation resistivity (Rt) | B47: 20 | C47: ohm-m
A48: Tortuosity factor (a) | B48: 1
A49: Cementation exponent (m) | B49: 2
A50: Saturation exponent (n) | B50: 2
A51: Porosity for Sw (PHI) | B51: 0.22 | C51: v/v | F51: Use PHIE (effective porosity) here.
A52: Water saturation (Archie) | B52: =(($B$48*$B$46)/($B$51^$B$49*$B$47))^(1/$B$50) | C52: v/v
A53: Water saturation | B53: =$B$52*100 | F53: percent.
A54: Bulk volume water (BVW) | B54: =$B$51*$B$52 | C54: v/v | F54: Near-constant BVW over an interval indicates the zone is at irreducible water saturation (will produce water-free).
A56: Rw from SP | F56: K = 61 + 0.133 x T [degF]; Rw ~ Rmf / 10^(-SSP/K)
F57: Quick-look only: clean, thick, water-bearing zone, NaCl-equivalent filtrate and formation water. Strictly the SP gives Rwe/Rmfe (equivalent resistivities) - correct via SP charts for precise work.
A58: Static SP deflection (SSP) | B58: -80 | F58: mV, negative in a wet sand with Rmf > Rw.
A59: Formation temperature | B59: 150 | C59: degF | D59: =IFERROR(($B$59-32)/1.8,NA()) | E59: degC
A60: Mud filtrate resistivity at formation temp (Rmf) | B60: 0.35 | C60: ohm-m
A61: SP coefficient (K) | B61: =61+0.133*$B$59
A62: Formation water resistivity (Rw, approx) | B62: =$B$60/10^(-$B$58/$B$61) | C62: ohm-m
A64: Permeability Estimates | F64: Timur (1968): k [mD] = 0.136 x (PHI x 100)^4.4 / (Swi x 100)^2
F65: Timur correlation from sandstone core data - order-of-magnitude estimate only; requires porosity as a fraction and IRREDUCIBLE water saturation. Coates free-fluid / NMR forms (e.g. k = ((100 x PHI)^2 x (1-Swi)/Swi)^2 variants) need local core calibration before use - not computed here.
A66: Porosity (PHI) | B66: 0.22 | C66: v/v
A67: Irreducible water saturation (Swi) | B67: 0.25 | C67: v/v | F67: From capillary pressure data or BVW in a zone at irreducible conditions.
A68: Timur permeability (k) | B68: =0.136*($B$66*100)^4.4/($B$67*100)^2 | C68: mD | D68: =IFERROR($B$68*0.9869233,NA()) | E68: um2 x1e-3
A69: Rough permeability class | B69: =IF($B$68<1,"tight (< 1 mD)",IF($B$68<10,"poor (1-10 mD)",IF($B$68<100,"moderate (10-100 mD)",IF($B$68<1000,"good (100-1,000 mD)","excellent (> 1,000 mD)"))))
A71: Net Pay Cutoffs | F71: pay when Vsh <= Vsh_max AND PHIE >= PHIE_min AND Sw <= Sw_max
F72: Typical clastic quick-look cutoffs; tighten PHIE_min for gas (lower viscosity) and loosen for heavy oil per field practice. These cells drive the pay flag in the table below.
A73: Maximum shale volume (Vsh_max) | B73: 0.4 | C73: v/v
A74: Minimum effective porosity (PHIE_min) | B74: 0.08 | C74: v/v
A75: Maximum water saturation (Sw_max) | B75: 0.6 | C75: v/v
A76: Cutoff set | B76: ="Pay = Vsh <= "&TEXT($B$73,"0.00")&", PHIE >= "&TEXT($B$74,"0.00")&", Sw <= "&TEXT($B$75,"0.00")
A78: Log Data Table & Quick-Look
A80: 25-point log listing - enter Depth/GR/RHOB/NPHI/RT (yellow); IGR through pay flag computed with the single-point parameters above
A81: Depth (ft) | B81: GR (API) | C81: RHOB (g/cc) | D81: NPHI (v/v) | E81: RT (ohm-m) | F81: IGR | G81: Vsh | H81: PHID | I81: PHIND | J81: PHIE | K81: Sw | L81: pay | M81: D* | N81: Sw* | O81: Vsh* | P81: PHIE*
A82: 5400 | B82: 108 | C82: 2.55 | D82: 0.33 | E82: 4 | F82: =IF(ISNUMBER($B82),MAX(0,MIN(1,($B82-$B$11)/($B$12-$B$11))),"") | G82: =IF(ISNUMBER($F82),0.083*(2^(3.7*$F82)-1),"") | H82: =IF(ISNUMBER($C82),MAX(0,MIN(1,($B$21-$C82)/($B$21-$B$22))),"") | I82: =IF(AND(ISNUMBER($H82),ISNUMBER($D82)),($H82+$D82)/2,"") | J82: =IF(AND(ISNUMBER($I82),ISNUMBER($G82)),$I82*(1-$G82),"") | K82: =IF(OR(NOT(ISNUMBER($J82)),NOT(ISNUMBER($E82))),"",IF($J82<=0,"",MIN(1,(($B$48*$B$46)/($J82^$B$49*$E82))^(1/$B$50)))) | L82: =IF(AND(ISNUMBER($G82),ISNUMBER($J82),ISNUMBER($K82)),IF(AND($G82<=$B$73,$J82>=$B$74,$K82<=$B$75),1,0),0) | M82: =IF(ISNUMBER($A82),$A82,NA()) | N82: =IF(AND(ISNUMBER($A82),ISNUMBER($K82)),$K82,NA()) | O82: =IF(AND(ISNUMBER($A82),ISNUMBER($G82)),$G82,NA()) | P82: =IF(AND(ISNUMBER($A82),ISNUMBER($J82)),$J82,NA())
A83: 5402 | B83: 112 | C83: 2.56 | D83: 0.34 | E83: 3.5 | F83: =IF(ISNUMBER($B83),MAX(0,MIN(1,($B83-$B$11)/($B$12-$B$11))),"") | G83: =IF(ISNUMBER($F83),0.083*(2^(3.7*$F83)-1),"") | H83: =IF(ISNUMBER($C83),MAX(0,MIN(1,($B$21-$C83)/($B$21-$B$22))),"") | I83: =IF(AND(ISNUMBER($H83),ISNUMBER($D83)),($H83+$D83)/2,"") | J83: =IF(AND(ISNUMBER($I83),ISNUMBER($G83)),$I83*(1-$G83),"") | K83: =IF(OR(NOT(ISNUMBER($J83)),NOT(ISNUMBER($E83))),"",IF($J83<=0,"",MIN(1,(($B$48*$B$46)/($J83^$B$49*$E83))^(1/$B$50)))) | L83: =IF(AND(ISNUMBER($G83),ISNUMBER($J83),ISNUMBER($K83)),IF(AND($G83<=$B$73,$J83>=$B$74,$K83<=$B$75),1,0),0) | M83: =IF(ISNUMBER($A83),$A83,NA()) | N83: =IF(AND(ISNUMBER($A83),ISNUMBER($K83)),$K83,NA()) | O83: =IF(AND(ISNUMBER($A83),ISNUMBER($G83)),$G83,NA()) | P83: =IF(AND(ISNUMBER($A83),ISNUMBER($J83)),$J83,NA())
A84: 5404 | B84: 118 | C84: 2.58 | D84: 0.35 | E84: 3 | F84: =IF(ISNUMBER($B84),MAX(0,MIN(1,($B84-$B$11)/($B$12-$B$11))),"") | G84: =IF(ISNUMBER($F84),0.083*(2^(3.7*$F84)-1),"") | H84: =IF(ISNUMBER($C84),MAX(0,MIN(1,($B$21-$C84)/($B$21-$B$22))),"") | I84: =IF(AND(ISNUMBER($H84),ISNUMBER($D84)),($H84+$D84)/2,"") | J84: =IF(AND(ISNUMBER($I84),ISNUMBER($G84)),$I84*(1-$G84),"") | K84: =IF(OR(NOT(ISNUMBER($J84)),NOT(ISNUMBER($E84))),"",IF($J84<=0,"",MIN(1,(($B$48*$B$46)/($J84^$B$49*$E84))^(1/$B$50)))) | L84: =IF(AND(ISNUMBER($G84),ISNUMBER($J84),ISNUMBER($K84)),IF(AND($G84<=$B$73,$J84>=$B$74,$K84<=$B$75),1,0),0) | M84: =IF(ISNUMBER($A84),$A84,NA()) | N84: =IF(AND(ISNUMBER($A84),ISNUMBER($K84)),$K84,NA()) | O84: =IF(AND(ISNUMBER($A84),ISNUMBER($G84)),$G84,NA()) | P84: =IF(AND(ISNUMBER($A84),ISNUMBER($J84)),$J84,NA())
A85: 5406 | B85: 110 | C85: 2.55 | D85: 0.33 | E85: 4 | F85: =IF(ISNUMBER($B85),MAX(0,MIN(1,($B85-$B$11)/($B$12-$B$11))),"") | G85: =IF(ISNUMBER($F85),0.083*(2^(3.7*$F85)-1),"") | H85: =IF(ISNUMBER($C85),MAX(0,MIN(1,($B$21-$C85)/($B$21-$B$22))),"") | I85: =IF(AND(ISNUMBER($H85),ISNUMBER($D85)),($H85+$D85)/2,"") | J85: =IF(AND(ISNUMBER($I85),ISNUMBER($G85)),$I85*(1-$G85),"") | K85: =IF(OR(NOT(ISNUMBER($J85)),NOT(ISNUMBER($E85))),"",IF($J85<=0,"",MIN(1,(($B$48*$B$46)/($J85^$B$49*$E85))^(1/$B$50)))) | L85: =IF(AND(ISNUMBER($G85),ISNUMBER($J85),ISNUMBER($K85)),IF(AND($G85<=$B$73,$J85>=$B$74,$K85<=$B$75),1,0),0) | M85: =IF(ISNUMBER($A85),$A85,NA()) | N85: =IF(AND(ISNUMBER($A85),ISNUMBER($K85)),$K85,NA()) | O85: =IF(AND(ISNUMBER($A85),ISNUMBER($G85)),$G85,NA()) | P85: =IF(AND(ISNUMBER($A85),ISNUMBER($J85)),$J85,NA())
A86: 5408 | B86: 95 | C86: 2.5 | D86: 0.3 | E86: 5 | F86: =IF(ISNUMBER($B86),MAX(0,MIN(1,($B86-$B$11)/($B$12-$B$11))),"") | G86: =IF(ISNUMBER($F86),0.083*(2^(3.7*$F86)-1),"") | H86: =IF(ISNUMBER($C86),MAX(0,MIN(1,($B$21-$C86)/($B$21-$B$22))),"") | I86: =IF(AND(ISNUMBER($H86),ISNUMBER($D86)),($H86+$D86)/2,"") | J86: =IF(AND(ISNUMBER($I86),ISNUMBER($G86)),$I86*(1-$G86),"") | K86: =IF(OR(NOT(ISNUMBER($J86)),NOT(ISNUMBER($E86))),"",IF($J86<=0,"",MIN(1,(($B$48*$B$46)/($J86^$B$49*$E86))^(1/$B$50)))) | L86: =IF(AND(ISNUMBER($G86),ISNUMBER($J86),ISNUMBER($K86)),IF(AND($G86<=$B$73,$J86>=$B$74,$K86<=$B$75),1,0),0) | M86: =IF(ISNUMBER($A86),$A86,NA()) | N86: =IF(AND(ISNUMBER($A86),ISNUMBER($K86)),$K86,NA()) | O86: =IF(AND(ISNUMBER($A86),ISNUMBER($G86)),$G86,NA()) | P86: =IF(AND(ISNUMBER($A86),ISNUMBER($J86)),$J86,NA())
A87: 5410 | B87: 62 | C87: 2.42 | D87: 0.24 | E87: 5 | F87: =IF(ISNUMBER($B87),MAX(0,MIN(1,($B87-$B$11)/($B$12-$B$11))),"") | G87: =IF(ISNUMBER($F87),0.083*(2^(3.7*$F87)-1),"") | H87: =IF(ISNUMBER($C87),MAX(0,MIN(1,($B$21-$C87)/($B$21-$B$22))),"") | I87: =IF(AND(ISNUMBER($H87),ISNUMBER($D87)),($H87+$D87)/2,"") | J87: =IF(AND(ISNUMBER($I87),ISNUMBER($G87)),$I87*(1-$G87),"") | K87: =IF(OR(NOT(ISNUMBER($J87)),NOT(ISNUMBER($E87))),"",IF($J87<=0,"",MIN(1,(($B$48*$B$46)/($J87^$B$49*$E87))^(1/$B$50)))) | L87: =IF(AND(ISNUMBER($G87),ISNUMBER($J87),ISNUMBER($K87)),IF(AND($G87<=$B$73,$J87>=$B$74,$K87<=$B$75),1,0),0) | M87: =IF(ISNUMBER($A87),$A87,NA()) | N87: =IF(AND(ISNUMBER($A87),ISNUMBER($K87)),$K87,NA()) | O87: =IF(AND(ISNUMBER($A87),ISNUMBER($G87)),$G87,NA()) | P87: =IF(AND(ISNUMBER($A87),ISNUMBER($J87)),$J87,NA())
